Workbook

Sheet Maize Labor Rates
A1: Rate Sheet Maize
A6: 2025 PROJECT MAIZE RATE SHEET
A7: LABOR CLASSIFICATIONS AND MANAGEMENT SCHEDULED RATES | K7: included
A8: 1. Labor Classifications - Onsite | E8: Standard (1.0x) | H8: Overtime (1.5x) | I8: Doubletime (2.0x) | K8: Per Diem
A9: Project Engineer (daily reporting, RFI's, tracking installation, schedule) | E9: 140 | H9: =E9*1.5 -> 210 | I9: =E9*2 -> 280 | K9: 150
A10: General Superintendent | E10: 175 | H10: =E10*1.5 -> 262.5 | I10: =E10*2 -> 350
A11: Site Superintendent | E11: 175 | H11: =E11*1.5 -> 262.5 | I11: =E11*2 -> 350
A12: Foreman | E12: 162.5 | H12: =E12*1.5 -> 243.75 | I12: =E12*2 -> 325
A13: Electrician | E13: 150 | H13: =E13*1.5 -> 225 | I13: =E13*2 -> 300
A14: Apprentice | E14: 126.5 | H14: =E14*1.5 -> 189.75 | I14: =E14*2 -> 253
A15: Operator | E15: 102.31 | F15: 102.31 | G15: 102.31 | H15: =E15*1.5 -> 153.465 | I15: =E15*2 -> 204.62
A16: Steel Fabrication & Welding | B16: Steel Fabrication & Welding | C16: Steel Fabrication & Welding | D16: Steel Fabrication & Welding | E16: 150 | F16: 86.74 | G16: 86.74 | H16: =E16*1.5 -> 225 | I16: =E16*2 -> 300
A17: QA/QC Director | E17: 190 | H17: =E17*1.5 -> 285 | I17: =E17*2 -> 380
A18: QA/QC Manager | E18: 165 | H18: =E18*1.5 -> 247.5 | I18: =E18*2 -> 330
A19: QA/QC Agent | E19: 150 | H19: =E19*1.5 -> 225 | I19: =E19*2 -> 300
A20: Safety Agent | E20: 172.5 | H20: =E20*1.5 -> 258.75 | I20: =E20*2 -> 345
A21: Project Coordinator | E21: 135 | H21: =E21*1.5 -> 202.5 | I21: =E21*2 -> 270
A22: Site Resource Coordinator | E22: 135 | H22: =E22*1.5 -> 202.5 | I22: =E22*2 -> 270
A23: Administrative Coordinator (logistics, manpower) | E23: 125 | H23: =E23*1.5 -> 187.5 | I23: =E23*2 -> 250
A24: Project Accountanting (time entry, payroll) | E24: 135 | H24: =E24*1.5 -> 202.5 | I24: =E24*2 -> 270
A25: Billing Specialist (auditor, time, equipment, materials, billing) | E25: 140 | H25: =E25*1.5 -> 210 | I25: =E25*2 -> 280
A26: Project Executive | E26: 200 | H26: =E26*1.5 -> 300 | I26: =E26*2 -> 400
A27: Sr. Project Management | E27: 190 | H27: =E27*1.5 -> 285 | I27: =E27*2 -> 380
A28: Project Management | E28: 160 | H28: =E28*1.5 -> 240 | I28: =E28*2 -> 320
A35: 2. Labor Classifications Off-Site | E35: Standard (1.0x) | H35: Overtime (1.5x) | I35: Doubletime (2.0x) | K35: No Per Diem
A36: QA/QC Director | E36: 175 | H36: =E36*1.5 -> 262.5 | I36: =E36*2 -> 350
A37: Project Coordinator | E37: 120 | H37: =E37*1.5 -> 180 | I37: =E37*2 -> 240
A38: Administrative Coordinator (logistics, manpower) | E38: 110 | H38: =E38*1.5 -> 165 | I38: =E38*2 -> 220
A39: Project Accountanting (time entry, payroll) | E39: 120 | H39: =E39*1.5 -> 180 | I39: =E39*2 -> 240
A40: Billing Specialist (auditor, time, equipment, materials, billing) | E40: 90 | H40: =E40*1.5 -> 135 | I40: =E40*2 -> 180
A41: Project Executive | E41: 185 | H41: =E41*1.5 -> 277.5 | I41: =E41*2 -> 370
A42: Sr. Project Management | E42: 175 | H42: =E42*1.5 -> 262.5 | I42: =E42*2 -> 350
A43: Project Management | E43: 145 | H43: =E43*1.5 -> 217.5 | I43: =E43*2 -> 290
A44: Safety Director | E44: 135 | H44: =E44*1.5 -> 202.5 | I44: =E44*2 -> 270
A45: Electrical Engineer | E45: 150 | H45: =E45*1.5 -> 225 | I45: =E45*2 -> 300
A46: Electrical Designer (BIM, VDC, Pre-Construction) | E46: 125 | H46: =E46*1.5 -> 187.5 | I46: =E46*2 -> 250
A47: Estimator | E47: 125 | H47: =E47*1.5 -> 187.5 | I47: =E47*2 -> 250
E48: 0 | H48: =E48*1.5 -> 0 | I48: =E48*2 -> 0
E49: 0 | H49: =E49*1.5 -> 0 | I49: =E49*2 -> 0
E50: 0 | H50: =E50*1.5 -> 0 | I50: =E50*2 -> 0
E51: 0 | H51: =E51*1.5 -> 0 | I51: =E51*2 -> 0
E52: 0 | H52: =E52*1.5 -> 0 | I52: =E52*2 -> 0
E53: 0 | H53: =E53*1.5 -> 0 | I53: =E53*2 -> 0
E54: 0 | H54: =E54*1.5 -> 0 | I54: =E54*2 -> 0
E55: 0 | H55: =E55*1.5 -> 0 | I55: =E55*2 -> 0
E56: 0 | H56: =E56*1.5 -> 0 | I56: =E56*2 -> 0
E57: 0 | H57: =E57*1.5 -> 0 | I57: =E57*2 -> 0
E58: 0 | H58: =E58*1.5 -> 0 | I58: =E58*2 -> 0
E59: 0 | H59: =E59*1.5 -> 0 | I59: =E59*2 -> 0
... E92: 0 | H92: =E92*1.5 -> 0 | I92: =E92*2 -> 0

Sheet INVOICE COVER
D1: INVOICE # 25108-39
D2: INVOICE DATE | E2: CUSTOMER NO. | F2: INVOICE NUMBER
A3: 10640 Deme Drive Suite M, Indianapolis IN 46236 | D3: 46190 | F3: 25108-39
A4: Customer Information | C4: Job Information | D4: P.O. NUMBER | E4: JOB. NO. | F4: PERIOD ENDING
A5: X-Wavetech LLC | C5: Marble NC | D5: 7277 | E5: 25108 | F5: 46180
A6: Christopher Remmers | C6: Austin Stoner | D6: Customer AP Contact | E6: InPwr Operations Contact | F6: InPwr Billing Contact
A7: 13994 Lake Price Drive | C7: 155 Palmer Lane | D7: Christopher Remmers | E7: Dave Hedge | F7: Kyah InskeeP
A8: Orlando, FL 32826 | C8: Marble, NC 28905 | D8: 201-314-2811 | E8: 317-417-9885 | F8: 317-723-3375
A9: 201-314-2811 | C9: 463-246-5321 | D9: chris@x-wavetech.com | E9: dhedge@inpwrinc.com | F9: AR@INPWRINC.COM
A10: *Please note, progress billing only and does not represent all applicable charges for this period; future invoicing may be applicable and billed upon substantial completion
A11: 6 | B11: DESCRIPTION | F11: Amount | K11: 1
A12: 1 | B12: Labor | F12: ='1ST Shift'!AG68 -> 2041.25
A13: 2 | B13: Equipment | F13: ='3rd Party Equipment'!F60+'IP Equip'!D38+'IP Equip_Tools'!S34 -> 0
A14: 3 | B14: Materials | F14: =Materials!F60 -> 0
A15: 4 | B15: Incurred Cost | F15: ='Incurred Costs'!F57 -> 0
A16: 5 | B16: SubContractors | F16: =Subcontractors!F60 -> 0
H17: =37+43 -> 80
B19: Extended ROM Total | F19: =F12+F13+F14+F15+F16+F17 -> 2041.25
I20: ='6001 1st'!AC168+'6002 2nd'!AC168+'6005 1ST'!AC182+'6006 2nd'!AC169+'6007 1st '!AC181+'6008 2nd'!AC181+#REF!+#REF! -> #REF!
G23: =D3+50 -> 46240
A47: Invoice Total Due 8/6/26 | F47: =F19 -> 2041.25

Sheet INVOICE COVER 7256
D1: INVOICE # 25108-09
D2: INVOICE DATE | E2: CUSTOMER NO. | F2: INVOICE NUMBER
A3: 10640 Deme Drive Suite M, Indianapolis IN 46236 | D3: 45951 | F3: 25108-09
A4: Customer Information | C4: Job Information | D4: P.O. NUMBER | E4: JOB. NO. | F4: PERIOD ENDING
A5: X-Wavetech LLC | C5: Marble NC | D5: 7256 | E5: 25108 | F5: 45942
A6: Christopher Remmers | C6: Austin Stoner | D6: Customer AP Contact | E6: InPwr Operations Contact | F6: InPwr Billing Contact
A7: 13994 Lake Price Drive | C7: 155 Palmer Lane | D7: Christopher Remmers | E7: Dave Hedge | F7: Kyah Inskeep/Mandy Vo
A8: Orlando, FL 32826 | C8: Marble, NC 28905 | D8: 201-314-2811 | E8: 317-417-9885 | F8: 317-723-3375
A9: 201-314-2811 | C9: 463-246-5321 | D9: chris@x-wavetech.com | E9: dhedge@inpwrinc.com | F9: AR@INPWRINC.COM
A10: *Please note, progress billing only and does not represent all applicable charges for this period; future invoicing may be applicable and billed upon substantial completion | K10: 12
A11: 6 | B11: DESCRIPTION | F11: Amount | K11: 1
A12: 1 | B12: Extended ROM TM Labor | F12: ='1ST Shift'!AG68+'2ND SHIFT'!AG294 -> #REF!
A13: 2 | B13: Equipment | F13: ='3rd Party Equipment'!F60+'IP Equip_Tools'!S34 -> 0
A14: 3 | B14: Materials | F14: =Materials!F60 -> 0
A15: 4 | B15: Incurred Cost | F15: ='Incurred Costs'!F57 -> 0
A16: 5 | B16: SubContractors | F16: =Subcontractors!F60 -> 0
A17: 6 | B17: Mobilization Charge - 12 Mobilized from 9.29.25 thru 10.12.25 | F17: 12000 | H17: =37+43 -> 80
B19: Extended ROM TM Total from 9.29.25 thru 10.12.25 | F19: =F12+F13+F14+F15+F16+F17 -> #REF!
I20: ='6001 1st'!AC168+'6002 2nd'!AC168+'6005 1ST'!AC182+'6006 2nd'!AC169+'6007 1st '!AC181+'6008 2nd'!AC181+#REF!+#REF! -> #REF!
B22: Total Left to Bill under PO #7256 - This Total Closes out PO #7256 | F22: 1700000
G23: =D3+50 -> 46001
A47: Invoice Total Due 12/10/25 | F47: =F22 -> 1700000

Sheet INVOICE COVER 7277
D1: INVOICE # 25108-10
D2: INVOICE DATE | E2: CUSTOMER NO. | F2: INVOICE NUMBER
A3: 10640 Deme Drive Suite M, Indianapolis IN 46236 | D3: 45951 | F3: 25108-10
A4: Customer Information | C4: Job Information | D4: P.O. NUMBER | E4: JOB. NO. | F4: PERIOD ENDING
A5: X-Wavetech LLC | C5: Marble NC | D5: 7277 | E5: 25108 | F5: 45942
A6: Christopher Remmers | C6: Austin Stoner | D6: Customer AP Contact | E6: InPwr Operations Contact | F6: InPwr Billing Contact
A7: 13994 Lake Price Drive | C7: 155 Palmer Lane | D7: Christopher Remmers | E7: Dave Hedge | F7: Kyah Inskeep/Mandy Vo
A8: Orlando, FL 32826 | C8: Marble, NC 28905 | D8: 201-314-2811 | E8: 317-417-9885 | F8: 317-723-3375
A9: 201-314-2811 | C9: 463-246-5321 | D9: chris@x-wavetech.com | E9: dhedge@inpwrinc.com | F9: AR@INPWRINC.COM
A10: *Please note, progress billing only and does not represent all applicable charges for this period; future invoicing may be applicable and billed upon substantial completion | K10: 12
A11: 6 | B11: DESCRIPTION | F11: Amount | K11: 1
A12: 1 | B12: Extended ROM TM Labor | F12: ='1ST Shift'!AG68+'2ND SHIFT'!AG294 -> #REF!
A13: 2 | B13: Equipment | F13: ='3rd Party Equipment'!F60+'IP Equip_Tools'!S34 -> 0
A14: 3 | B14: Materials | F14: =Materials!F60 -> 0
A15: 4 | B15: Incurred Cost | F15: ='Incurred Costs'!F57 -> 0
A16: 5 | B16: SubContractors | F16: =Subcontractors!F60 -> 0
A17: 6 | B17: Mobilization Charge - 12 Mobilized from 9.29.25 thru 10.12.25 | F17: 12000 | H17: =37+43 -> 80
B19: Extended ROM TM Total from 9.29.25 thru 10.12.25 | F19: =F12+F13+F14+F15+F16+F17 -> #REF!
I20: ='6001 1st'!AC168+'6002 2nd'!AC168+'6005 1ST'!AC182+'6006 2nd'!AC169+'6007 1st '!AC181+'6008 2nd'!AC181+#REF!+#REF! -> #REF!
B22: Subtotal to start billing under PO #7277. All other billing going forward will fall under this PO | F22: 1471448.8
B23: Inclusive of this total on invoice 25108-10 | G23: =D3+50 -> 46001
A47: Invoice Total Due 12/10/25 | F47: =F22 -> 1471448.8

Sheet 1ST Shift
A1: Extended ROM 1st Shift | AK1: On 11.21.25 Previously Billed | AL1: will hit 12.5.25 payroll | AM1: Should be on JCH
A2: INPWR INVOICE NUMBER | B2: ='INVOICE COVER'!F3 -> 25108-39
A3: CUSTOMER REFERENCE | B3: ='INVOICE COVER'!D5 -> 7277
A4: JOB NAME | B4: ='INVOICE COVER 7256'!C5 -> Marble NC
A5: JOB NUMBER | B5: ='INVOICE COVER 7256'!E5 -> 25108
A6: Preiod Ending | B6: ='INVOICE COVER'!F5 -> 46180
A7: EMPLOYEE NAME | B7: CLASS | C7: REGULAR | D7: Per Diem | E7: PER DAY | L7: =B6-6 -> 46174 | N7: =B6-5 -> 46175 | P7: =B6-4 -> 46176 | R7: =B6-3 -> 46177 | T7: =B6-2 -> 46178 | V7: =B6-1 -> 46179 | X7: =B6 -> 46180 | Z7: REG | AA7: OT | AB7: DT | AC7: Total | AD7: ST. LABOR | AE7: OT LABOR | AF7: DT LABOR | AG7: LABOR
C8: RATE | D8: Y/N | E8: =B6-6 -> 46174 | F8: =E8+1 -> 46175 | G8: =F8+1 -> 46176 | H8: =G8+1 -> 46177 | I8: =H8+1 -> 46178 | J8: =I8+1 -> 46179 | K8: =J8+1 -> 46180 | L8: REG. | M8: OT | N8: REG. | O8: OT | P8: REG | Q8: OT | R8: REG | S8: OT | T8: REG | U8: OT | V8: REG | W8: OT | X8: REG | Y8: OT | Z8: TOT | AA8: TOT | AB8: Hours | AC8: Hours | AD8: TOTAL | AE8: TOTAL | AF8: TOTAL | AG8: TOTAL
A10: ALEMAN, GABRIEL | B10: Electrician | C10: =VLOOKUP('1ST Shift'!$B10,Table6[],2,FALSE) -> 150 | L10: =(IF(E10>0,MIN(8,E10),"")) | M10: =IF((E10)>8,SUM(E10-L10),"") | N10: =(IF(F10>0,MIN(8,F10),"")) | O10: =IF((F10)>8,SUM(F10-N10),"") | P10: =(IF(G10>0,MIN(8,G10),"")) | Q10: =IF((G10)>8,SUM(G10-P10),"") | R10: =(IF(H10>0,MIN(8,H10),"")) | S10: =IF((H10)>8,SUM(H10-R10),"") | T10: =(IF(I10>0,MIN(8,I10),"")) | U10: =IF((I10)>8,SUM(I10-T10),"") | V10: =(IF(J10>0,MIN(8,J10),"")) | W10: =IF((J10)>8,SUM(J10-V10),"") | X10: =(IF(K10>0,MIN(8,K10),"")) | Y10: =IF((K10)>8,SUM(K10-X10),"") | Z10: =VLOOKUP(A10,Table4[#All],2,FALSE) -> 0 | AA10: =VLOOKUP(A10,Table4[#All],3,FALSE) -> 0 | AB10: =IFERROR(VLOOKUP(A10,Table13[[#Headers],[#Data]],7,FALSE),0) -> 0 | AC10: =SUM(Z10:AB10) -> 0 | AD10: =Z10*C10 -> 0 | AE10: =AA10*C10*1.5 -> 0 | AF10: =AB10*C10*2 -> 0 | AG10: =AD10+AE10+AF10 -> 0
A11: ARNOLD, CHARLES | B11: QA/QC | C11: =VLOOKUP('1ST Shift'!$B11,Table6[],2,FALSE) -> 165 | L11: =(IF(E11>0,MIN(8,E11),"")) | M11: =IF((E11)>8,SUM(E11-L11),"") | N11: =(IF(F11>0,MIN(8,F11),"")) | O11: =IF((F11)>8,SUM(F11-N11),"") | P11: =(IF(G11>0,MIN(8,G11),"")) | Q11: =IF((G11)>8,SUM(G11-P11),"") | R11: =(IF(H11>0,MIN(8,H11),"")) | S11: =IF((H11)>8,SUM(H11-R11),"") | T11: =(IF(I11>0,MIN(8,I11),"")) | U11: =IF((I11)>8,SUM(I11-T11),"") | V11: =(IF(J11>0,MIN(8,J11),"")) | W11: =IF((J11)>8,SUM(J11-V11),"") | X11: =(IF(K11>0,MIN(8,K11),"")) | Y11: =IF((K11)>8,SUM(K11-X11),"") | Z11: =VLOOKUP(A11,Table4[#All],2,FALSE) -> 0 | AA11: =VLOOKUP(A11,Table4[#All],3,FALSE) -> 0 | AB11: =IFERROR(VLOOKUP(A11,Table13[[#Headers],[#Data]],7,FALSE),0) -> 0 | AC11: =SUM(Z11:AB11) -> 0 | AD11: =Z11*C11 -> 0 | AE11: =AA11*C11*1.5 -> 0 | AF11: =AB11*C11*2 -> 0 | AG11: =AD11+AE11+AF11 -> 0
A12: BASTIDAS, OMARELYS QUERO | B12: Electrician | C12: =VLOOKUP('1ST Shift'!$B12,Table6[],2,FALSE) -> 150 | L12: =(IF(E12>0,MIN(8,E12),"")) | M12: =IF((E12)>8,SUM(E12-L12),"") | N12: =(IF(F12>0,MIN(8,F12),"")) | O12: =IF((F12)>8,SUM(F12-N12),"") | P12: =(IF(G12>0,MIN(8,G12),"")) | Q12: =IF((G12)>8,SUM(G12-P12),"") | R12: =(IF(H12>0,MIN(8,H12),"")) | S12: =IF((H12)>8,SUM(H12-R12),"") | T12: =(IF(I12>0,MIN(8,I12),"")) | U12: =IF((I12)>8,SUM(I12-T12),"") | V12: =(IF(J12>0,MIN(8,J12),"")) | W12: =IF((J12)>8,SUM(J12-V12),"") | X12: =(IF(K12>0,MIN(8,K12),"")) | Y12: =IF((K12)>8,SUM(K12-X12),"") | Z12: =VLOOKUP(A12,Table4[#All],2,FALSE) -> 0 | AA12: =VLOOKUP(A12,Table4[#All],3,FALSE) -> 0 | AB12: =IFERROR(VLOOKUP(A12,Table13[[#Headers],[#Data]],7,FALSE),0) -> 0 | AC12: =SUM(Z12:AB12) -> 0 | AD12: =Z12*C12 -> 0 | AE12: =AA12*C12*1.5 -> 0 | AF12: =AB12*C12*2 -> 0 | AG12: =AD12+AE12+AF12 -> 0
A13: BAUTISTA, MELVIN HERNANDEZ | B13: Electrician | C13: =VLOOKUP('1ST Shift'!$B13,Table6[],2,FALSE) -> 150 | L13: =(IF(E13>0,MIN(8,E13),"")) | M13: =IF((E13)>8,SUM(E13-L13),"") | N13: =(IF(F13>0,MIN(8,F13),"")) | O13: =IF((F13)>8,SUM(F13-N13),"") | P13: =(IF(G13>0,MIN(8,G13),"")) | Q13: =IF((G13)>8,SUM(G13-P13),"") | R13: =(IF(H13>0,MIN(8,H13),"")) | S13: =IF((H13)>8,SUM(H13-R13),"") | T13: =(IF(I13>0,MIN(8,I13),"")) | U13: =IF((I13)>8,SUM(I13-T13),"") | V13: =(IF(J13>0,MIN(8,J13),"")) | W13: =IF((J13)>8,SUM(J13-V13),"") | X13: =(IF(K13>0,MIN(8,K13),"")) | Y13: =IF((K13)>8,SUM(K13-X13),"") | Z13: =VLOOKUP(A13,Table4[#All],2,FALSE) -> 0 | AA13: =VLOOKUP(A13,Table4[#All],3,FALSE) -> 0 | AB13: =IFERROR(VLOOKUP(A13,Table13[[#Headers],[#Data]],7,FALSE),0) -> 0 | AC13: =SUM(Z13:AB13) -> 0 | AD13: =Z13*C13 -> 0 | AE13: =AA13*C13*1.5 -> 0 | AF13: =AB13*C13*2 -> 0 | AG13: =AD13+AE13+AF13 -> 0
A14: BEARER, BENJAMIN | B14: QA/QC | C14: =VLOOKUP('1ST Shift'!$B14,Table6[],2,FALSE) -> 165 | L14: =(IF(E14>0,MIN(8,E14),"")) | M14: =IF((E14)>8,SUM(E14-L14),"") | N14: =(IF(F14>0,MIN(8,F14),"")) | O14: =IF((F14)>8,SUM(F14-N14),"") | P14: =(IF(G14>0,MIN(8,G14),"")) | Q14: =IF((G14)>8,SUM(G14-P14),"") | R14: =(IF(H14>0,MIN(8,H14),"")) | S14: =IF((H14)>8,SUM(H14-R14),"") | T14: =(IF(I14>0,MIN(8,I14),"")) | U14: =IF((I14)>8,SUM(I14-T14),"") | V14: =(IF(J14>0,MIN(8,J14),"")) | W14: =IF((J14)>8,SUM(J14-V14),"") | X14: =(IF(K14>0,MIN(8,K14),"")) | Y14: =IF((K14)>8,SUM(K14-X14),"") | Z14: =VLOOKUP(A14,Table4[#All],2,FALSE) -> 0 | AA14: =VLOOKUP(A14,Table4[#All],3,FALSE) -> 0 | AB14: =IFERROR(VLOOKUP(A14,Table13[[#Headers],[#Data]],7,FALSE),0) -> 0 | AC14: =SUM(Z14:AB14) -> 0 | AD14: =Z14*C14 -> 0 | AE14: =AA14*C14*1.5 -> 0 | AF14: =AB14*C14*2 -> 0 | AG14: =AD14+AE14+AF14 -> 0 | AH14: biweekly | AL14: 24 | AM14: =AC14-AL14 -> -24
A15: BONILLA, DOMINGO | B15: Electrician | C15: =VLOOKUP('1ST Shift'!$B15,Table6[],2,FALSE) -> 150 | L15: =(IF(E15>0,MIN(8,E15),"")) | M15: =IF((E15)>8,SUM(E15-L15),"") | N15: =(IF(F15>0,MIN(8,F15),"")) | O15: =IF((F15)>8,SUM(F15-N15),"") | P15: =(IF(G15>0,MIN(8,G15),"")) | Q15: =IF((G15)>8,SUM(G15-P15),"") | R15: =(IF(H15>0,MIN(8,H15),"")) | S15: =IF((H15)>8,SUM(H15-R15),"") | T15: =(IF(I15>0,MIN(8,I15),"")) | U15: =IF((I15)>8,SUM(I15-T15),"") | V15: =(IF(J15>0,MIN(8,J15),"")) | W15: =IF((J15)>8,SUM(J15-V15),"") | X15: =(IF(K15>0,MIN(8,K15),"")) | Y15: =IF((K15)>8,SUM(K15-X15),"") | Z15: =VLOOKUP(A15,Table4[#All],2,FALSE) -> 0 | AA15: =VLOOKUP(A15,Table4[#All],3,FALSE) -> 0 | AB15: =IFERROR(VLOOKUP(A15,Table13[[#Headers],[#Data]],7,FALSE),0) -> 0 | AC15: =SUM(Z15:AB15) -> 0 | AD15: =Z15*C15 -> 0 | AE15: =AA15*C15*1.5 -> 0 | AF15: =AB15*C15*2 -> 0 | AG15: =AD15+AE15+AF15 -> 0
A16: BRAVO, JOSE BRICERNO | B16: Electrician | C16: =VLOOKUP('1ST Shift'!$B16,Table6[],2,FALSE) -> 150 | L16: =(IF(E16>0,MIN(8,E16),"")) | M16: =IF((E16)>8,SUM(E16-L16),"") | N16: =(IF(F16>0,MIN(8,F16),"")) | O16: =IF((F16)>8,SUM(F16-N16),"") | P16: =(IF(G16>0,MIN(8,G16),"")) | Q16: =IF((G16)>8,SUM(G16-P16),"") | R16: =(IF(H16>0,MIN(8,H16),"")) | S16: =IF((H16)>8,SUM(H16-R16),"") | T16: =(IF(I16>0,MIN(8,I16),"")) | U16: =IF((I16)>8,SUM(I16-T16),"") | V16: =(IF(J16>0,MIN(8,J16),"")) | W16: =IF((J16)>8,SUM(J16-V16),"") | X16: =(IF(K16>0,MIN(8,K16),"")) | Y16: =IF((K16)>8,SUM(K16-X16),"") | Z16: =VLOOKUP(A16,Table4[#All],2,FALSE) -> 0 | AA16: =VLOOKUP(A16,Table4[#All],3,FALSE) -> 0 | AB16: =IFERROR(VLOOKUP(A16,Table13[[#Headers],[#Data]],7,FALSE),0) -> 0 | AC16: =SUM(Z16:AB16) -> 0 | AD16: =Z16*C16 -> 0 | AE16: =AA16*C16*1.5 -> 0 | AF16: =AB16*C16*2 -> 0 | AG16: =AD16+AE16+AF16 -> 0
A17: BURGOS, FERNANDO | B17: QA/QC | C17: =VLOOKUP('1ST Shift'!$B17,Table6[],2,FALSE) -> 165 | L17: =(IF(E17>0,MIN(8,E17),"")) | M17: =IF((E17)>8,SUM(E17-L17),"") | N17: =(IF(F17>0,MIN(8,F17),"")) | O17: =IF((F17)>8,SUM(F17-N17),"") | P17: =(IF(G17>0,MIN(8,G17),"")) | Q17: =IF((G17)>8,SUM(G17-P17),"") | R17: =(IF(H17>0,MIN(8,H17),"")) | S17: =IF((H17)>8,SUM(H17-R17),"") | T17: =(IF(I17>0,MIN(8,I17),"")) | U17: =IF((I17)>8,SUM(I17-T17),"") | V17: =(IF(J17>0,MIN(8,J17),"")) | W17: =IF((J17)>8,SUM(J17-V17),"") | X17: =(IF(K17>0,MIN(8,K17),"")) | Y17: =IF((K17)>8,SUM(K17-X17),"") | Z17: =VLOOKUP(A17,Table4[#All],2,FALSE) -> 0 | AA17: =VLOOKUP(A17,Table4[#All],3,FALSE) -> 0 | AB17: =IFERROR(VLOOKUP(A17,Table13[[#Headers],[#Data]],7,FALSE),0) -> 0 | AC17: =SUM(Z17:AB17) -> 0 | AD17: =Z17*C17 -> 0 | AE17: =AA17*C17*1.5 -> 0 | AF17: =AB17*C17*2 -> 0 | AG17: =AD17+AE17+AF17 -> 0
A18: CARDOZO, ENRIQUE | B18: Electrician | C18: =VLOOKUP('1ST Shift'!$B18,Table6[],2,FALSE) -> 150 | L18: =(IF(E18>0,MIN(8,E18),"")) | M18: =IF((E18)>8,SUM(E18-L18),"") | N18: =(IF(F18>0,MIN(8,F18),"")) | O18: =IF((F18)>8,SUM(F18-N18),"") | P18: =(IF(G18>0,MIN(8,G18),"")) | Q18: =IF((G18)>8,SUM(G18-P18),"") | R18: =(IF(H18>0,MIN(8,H18),"")) | S18: =IF((H18)>8,SUM(H18-R18),"") | T18: =(IF(I18>0,MIN(8,I18),"")) | U18: =IF((I18)>8,SUM(I18-T18),"") | V18: =(IF(J18>0,MIN(8,J18),"")) | W18: =IF((J18)>8,SUM(J18-V18),"") | X18: =(IF(K18>0,MIN(8,K18),"")) | Y18: =IF((K18)>8,SUM(K18-X18),"") | Z18: =VLOOKUP(A18,Table4[#All],2,FALSE) -> 0 | AA18: =VLOOKUP(A18,Table4[#All],3,FALSE) -> 0 | AB18: =IFERROR(VLOOKUP(A18,Table13[[#Headers],[#Data]],7,FALSE),0) -> 0 | AC18: =SUM(Z18:AB18) -> 0 | AD18: =Z18*C18 -> 0 | AE18: =AA18*C18*1.5 -> 0 | AF18: =AB18*C18*2 -> 0 | AG18: =AD18+AE18+AF18 -> 0
A19: CASTRILLON, DERWIN ZABALA | B19: Electrician | C19: =VLOOKUP('1ST Shift'!$B19,Table6[],2,FALSE) -> 150 | L19: =(IF(E19>0,MIN(8,E19),"")) | M19: =IF((E19)>8,SUM(E19-L19),"") | N19: =(IF(F19>0,MIN(8,F19),"")) | O19: =IF((F19)>8,SUM(F19-N19),"") | P19: =(IF(G19>0,MIN(8,G19),"")) | Q19: =IF((G19)>8,SUM(G19-P19),"") | R19: =(IF(H19>0,MIN(8,H19),"")) | S19: =IF((H19)>8,SUM(H19-R19),"") | T19: =(IF(I19>0,MIN(8,I19),"")) | U19: =IF((I19)>8,SUM(I19-T19),"") | V19: =(IF(J19>0,MIN(8,J19),"")) | W19: =IF((J19)>8,SUM(J19-V19),"") | X19: =(IF(K19>0,MIN(8,K19),"")) | Y19: =IF((K19)>8,SUM(K19-X19),"") | Z19: =VLOOKUP(A19,Table4[#All],2,FALSE) -> 0 | AA19: =VLOOKUP(A19,Table4[#All],3,FALSE) -> 0 | AB19: =IFERROR(VLOOKUP(A19,Table13[[#Headers],[#Data]],7,FALSE),0) -> 0 | AC19: =SUM(Z19:AB19) -> 0 | AD19: =Z19*C19 -> 0 | AE19: =AA19*C19*1.5 -> 0 | AF19: =AB19*C19*2 -> 0 | AG19: =AD19+AE19+AF19 -> 0
A20: CHAVEZ, RICARDO | B20: Electrician | C20: =VLOOKUP('1ST Shift'!$B20,Table6[],2,FALSE) -> 150 | L20: =(IF(E20>0,MIN(8,E20),"")) | M20: =IF((E20)>8,SUM(E20-L20),"") | N20: =(IF(F20>0,MIN(8,F20),"")) | O20: =IF((F20)>8,SUM(F20-N20),"") | P20: =(IF(G20>0,MIN(8,G20),"")) | Q20: =IF((G20)>8,SUM(G20-P20),"") | R20: =(IF(H20>0,MIN(8,H20),"")) | S20: =IF((H20)>8,SUM(H20-R20),"") | T20: =(IF(I20>0,MIN(8,I20),"")) | U20: =IF((I20)>8,SUM(I20-T20),"") | V20: =(IF(J20>0,MIN(8,J20),"")) | W20: =IF((J20)>8,SUM(J20-V20),"") | X20: =(IF(K20>0,MIN(8,K20),"")) | Y20: =IF((K20)>8,SUM(K20-X20),"") | Z20: =VLOOKUP(A20,Table4[#All],2,FALSE) -> 0 | AA20: =VLOOKUP(A20,Table4[#All],3,FALSE) -> 0 | AB20: =IFERROR(VLOOKUP(A20,Table13[[#Headers],[#Data]],7,FALSE),0) -> 0 | AC20: =SUM(Z20:AB20) -> 0 | AD20: =Z20*C20 -> 0 | AE20: =AA20*C20*1.5 -> 0 | AF20: =AB20*C20*2 -> 0 | AG20: =AD20+AE20+AF20 -> 0
A21: CHINCHILLA, FRANK ESTUARDO | B21: Electrician | C21: =VLOOKUP('1ST Shift'!$B21,Table6[],2,FALSE) -> 150 | L21: =(IF(E21>0,MIN(8,E21),"")) | M21: =IF((E21)>8,SUM(E21-L21),"") | N21: =(IF(F21>0,MIN(8,F21),"")) | O21: =IF((F21)>8,SUM(F21-N21),"") | P21: =(IF(G21>0,MIN(8,G21),"")) | Q21: =IF((G21)>8,SUM(G21-P21),"") | R21: =(IF(H21>0,MIN(8,H21),"")) | S21: =IF((H21)>8,SUM(H21-R21),"") | T21: =(IF(I21>0,MIN(8,I21),"")) | U21: =IF((I21)>8,SUM(I21-T21),"") | V21: =(IF(J21>0,MIN(8,J21),"")) | W21: =IF((J21)>8,SUM(J21-V21),"") | X21: =(IF(K21>0,MIN(8,K21),"")) | Y21: =IF((K21)>8,SUM(K21-X21),"") | Z21: =VLOOKUP(A21,Table4[#All],2,FALSE) -> 0 | AA21: =VLOOKUP(A21,Table4[#All],3,FALSE) -> 0 | AB21: =IFERROR(VLOOKUP(A21,Table13[[#Headers],[#Data]],7,FALSE),0) -> 0 | AC21: =SUM(Z21:AB21) -> 0 | AD21: =Z21*C21 -> 0 | AE21: =AA21*C21*1.5 -> 0 | AF21: =AB21*C21*2 -> 0 | AG21: =AD21+AE21+AF21 -> 0
A22: COLON, CHRISTIAN RODRIGUEZ | B22: Electrician | C22: =VLOOKUP('1ST Shift'!$B22,Table6[],2,FALSE) -> 150 | L22: =(IF(E22>0,MIN(8,E22),"")) | M22: =IF((E22)>8,SUM(E22-L22),"") | N22: =(IF(F22>0,MIN(8,F22),"")) | O22: =IF((F22)>8,SUM(F22-N22),"") | P22: =(IF(G22>0,MIN(8,G22),"")) | Q22: =IF((G22)>8,SUM(G22-P22),"") | R22: =(IF(H22>0,MIN(8,H22),"")) | S22: =IF((H22)>8,SUM(H22-R22),"") | T22: =(IF(I22>0,MIN(8,I22),"")) | U22: =IF((I22)>8,SUM(I22-T22),"") | V22: =(IF(J22>0,MIN(8,J22),"")) | W22: =IF((J22)>8,SUM(J22-V22),"") | X22: =(IF(K22>0,MIN(8,K22),"")) | Y22: =IF((K22)>8,SUM(K22-X22),"") | Z22: =VLOOKUP(A22,Table4[#All],2,FALSE) -> 0 | AA22: =VLOOKUP(A22,Table4[#All],3,FALSE) -> 0 | AB22: =IFERROR(VLOOKUP(A22,Table13[[#Headers],[#Data]],7,FALSE),0) -> 0 | AC22: =SUM(Z22:AB22) -> 0 | AD22: =Z22*C22 -> 0 | AE22: =AA22*C22*1.5 -> 0 | AF22: =AB22*C22*2 -> 0 | AG22: =AD22+AE22+AF22 -> 0
A23: CONCHA, RAFAEL | B23: Electrician | C23: =VLOOKUP('1ST Shift'!$B23,Table6[],2,FALSE) -> 150 | L23: =(IF(E23>0,MIN(8,E23),"")) | M23: =IF((E23)>8,SUM(E23-L23),"") | N23: =(IF(F23>0,MIN(8,F23),"")) | O23: =IF((F23)>8,SUM(F23-N23),"") | P23: =(IF(G23>0,MIN(8,G23),"")) | Q23: =IF((G23)>8,SUM(G23-P23),"") | R23: =(IF(H23>0,MIN(8,H23),"")) | S23: =IF((H23)>8,SUM(H23-R23),"") | T23: =(IF(I23>0,MIN(8,I23),"")) | U23: =IF((I23)>8,SUM(I23-T23),"") | V23: =(IF(J23>0,MIN(8,J23),"")) | W23: =IF((J23)>8,SUM(J23-V23),"") | X23: =(IF(K23>0,MIN(8,K23),"")) | Y23: =IF((K23)>8,SUM(K23-X23),"") | Z23: =VLOOKUP(A23,Table4[#All],2,FALSE) -> 0 | AA23: =VLOOKUP(A23,Table4[#All],3,FALSE) -> 0 | AB23: =IFERROR(VLOOKUP(A23,Table13[[#Headers],[#Data]],7,FALSE),0) -> 0 | AC23: =SUM(Z23:AB23) -> 0 | AD23: =Z23*C23 -> 0 | AE23: =AA23*C23*1.5 -> 0 | AF23: =AB23*C23*2 -> 0 | AG23: =AD23+AE23+AF23 -> 0
A24: CONCHA, RUBEN | B24: QA/QC | C24: =VLOOKUP('1ST Shift'!$B24,Table6[],2,FALSE) -> 165 | L24: =(IF(E24>0,MIN(8,E24),"")) | M24: =IF((E24)>8,SUM(E24-L24),"") | N24: =(IF(F24>0,MIN(8,F24),"")) | O24: =IF((F24)>8,SUM(F24-N24),"") | P24: =(IF(G24>0,MIN(8,G24),"")) | Q24: =IF((G24)>8,SUM(G24-P24),"") | R24: =(IF(H24>0,MIN(8,H24),"")) | S24: =IF((H24)>8,SUM(H24-R24),"") | T24: =(IF(I24>0,MIN(8,I24),"")) | U24: =IF((I24)>8,SUM(I24-T24),"") | V24: =(IF(J24>0,MIN(8,J24),"")) | W24: =IF((J24)>8,SUM(J24-V24),"") | X24: =(IF(K24>0,MIN(8,K24),"")) | Y24: =IF((K24)>8,SUM(K24-X24),"") | Z24: =VLOOKUP(A24,Table4[#All],2,FALSE) -> 0 | AA24: =VLOOKUP(A24,Table4[#All],3,FALSE) -> 0 | AB24: =IFERROR(VLOOKUP(A24,Table13[[#Headers],[#Data]],7,FALSE),0) -> 0 | AC24: =SUM(Z24:AB24) -> 0 | AD24: =Z24*C24 -> 0 | AE24: =AA24*C24*1.5 -> 0 | AF24: =AB24*C24*2 -> 0 | AG24: =AD24+AE24+AF24 -> 0
A25: DE PALACIOS, JOSEFINA MOSCARELLA | B25: Electrician | C25: =VLOOKUP('1ST Shift'!$B25,Table6[],2,FALSE) -> 150 | L25: =(IF(E25>0,MIN(8,E25),"")) | M25: =IF((E25)>8,SUM(E25-L25),"") | N25: =(IF(F25>0,MIN(8,F25),"")) | O25: =IF((F25)>8,SUM(F25-N25),"") | P25: =(IF(G25>0,MIN(8,G25),"")) | Q25: =IF((G25)>8,SUM(G25-P25),"") | R25: =(IF(H25>0,MIN(8,H25),"")) | S25: =IF((H25)>8,SUM(H25-R25),"") | T25: =(IF(I25>0,MIN(8,I25),"")) | U25: =IF((I25)>8,SUM(I25-T25),"") | V25: =(IF(J25>0,MIN(8,J25),"")) | W25: =IF((J25)>8,SUM(J25-V25),"") | X25: =(IF(K25>0,MIN(8,K25),"")) | Y25: =IF((K25)>8,SUM(K25-X25),"") | Z25: =VLOOKUP(A25,Table4[#All],2,FALSE) -> 0 | AA25: =VLOOKUP(A25,Table4[#All],3,FALSE) -> 0 | AB25: =IFERROR(VLOOKUP(A25,Table13[[#Headers],[#Data]],7,FALSE),0) -> 0 | AC25: =SUM(Z25:AB25) -> 0 | AD25: =Z25*C25 -> 0 | AE25: =AA25*C25*1.5 -> 0 | AF25: =AB25*C25*2 -> 0 | AG25: =AD25+AE25+AF25 -> 0
A26: FERNANDEZ, JHON KENNETH HOWARD | B26: Electrician | C26: =VLOOKUP('1ST Shift'!$B26,Table6[],2,FALSE) -> 150 | L26: =(IF(E26>0,MIN(8,E26),"")) | M26: =IF((E26)>8,SUM(E26-L26),"") | N26: =(IF(F26>0,MIN(8,F26),"")) | O26: =IF((F26)>8,SUM(F26-N26),"") | P26: =(IF(G26>0,MIN(8,G26),"")) | Q26: =IF((G26)>8,SUM(G26-P26),"") | R26: =(IF(H26>0,MIN(8,H26),"")) | S26: =IF((H26)>8,SUM(H26-R26),"") | T26: =(IF(I26>0,MIN(8,I26),"")) | U26: =IF((I26)>8,SUM(I26-T26),"") | V26: =(IF(J26>0,MIN(8,J26),"")) | W26: =IF((J26)>8,SUM(J26-V26),"") | X26: =(IF(K26>0,MIN(8,K26),"")) | Y26: =IF((K26)>8,SUM(K26-X26),"") | Z26: =VLOOKUP(A26,Table4[#All],2,FALSE) -> 0 | AA26: =VLOOKUP(A26,Table4[#All],3,FALSE) -> 0 | AB26: =IFERROR(VLOOKUP(A26,Table13[[#Headers],[#Data]],7,FALSE),0) -> 0 | AC26: =SUM(Z26:AB26) -> 0 | AD26: =Z26*C26 -> 0 | AE26: =AA26*C26*1.5 -> 0 | AF26: =AB26*C26*2 -> 0 | AG26: =AD26+AE26+AF26 -> 0
... A32: GONZALEZ, ELDER | B32: Electrician | C32: =VLOOKUP('1ST Shift'!$B32,Table6[],2,FALSE) -> 150 | L32: =(IF(E32>0,MIN(8,E32),"")) | M32: =IF((E32)>8,SUM(E32-L32),"") | N32: =(IF(F32>0,MIN(8,F32),"")) | O32: =IF((F32)>8,SUM(F32-N32),"") | P32: =(IF(G32>0,MIN(8,G32),"")) | Q32: =IF((G32)>8,SUM(G32-P32),"") | R32: =(IF(H32>0,MIN(8,H32),"")) | S32: =IF((H32)>8,SUM(H32-R32),"") | T32: =(IF(I32>0,MIN(8,I32),"")) | U32: =IF((I32)>8,SUM(I32-T32),"") | V32: =(IF(J32>0,MIN(8,J32),"")) | W32: =IF((J32)>8,SUM(J32-V32),"") | X32: =(IF(K32>0,MIN(8,K32),"")) | Y32: =IF((K32)>8,SUM(K32-X32),"") | Z32: =VLOOKUP(A32,Table4[#All],2,FALSE) -> 0 | AA32: =VLOOKUP(A32,Table4[#All],3,FALSE) -> 0 | AB32: =IFERROR(VLOOKUP(A32,Table13[[#Headers],[#Data]],7,FALSE),0) -> 0 | AC32: =SUM(Z32:AB32) -> 0 | AD32: =Z32*C32 -> 0 | AE32: =AA32*C32*1.5 -> 0 | AF32: =AB32*C32*2 -> 0 | AG32: =AD32+AE32+AF32 -> 0
A33: INSKEEP, KYAH | B33: Project Coordinator Offsite | C33: =VLOOKUP('1ST Shift'!$B33,Table6[],2,FALSE) -> 165 | L33: =(IF(E33>0,MIN(8,E33),"")) | M33: =IF((E33)>8,SUM(E33-L33),"") | N33: =(IF(F33>0,MIN(8,F33),"")) | O33: =IF((F33)>8,SUM(F33-N33),"") | P33: =(IF(G33>0,MIN(8,G33),"")) | Q33: =IF((G33)>8,SUM(G33-P33),"") | R33: =(IF(H33>0,MIN(8,H33),"")) | S33: =IF((H33)>8,SUM(H33-R33),"") | T33: =(IF(I33>0,MIN(8,I33),"")) | U33: =IF((I33)>8,SUM(I33-T33),"") | V33: =(IF(J33>0,MIN(8,J33),"")) | W33: =IF((J33)>8,SUM(J33-V33),"") | X33: =(IF(K33>0,MIN(8,K33),"")) | Y33: =IF((K33)>8,SUM(K33-X33),"") | Z33: 3 | AA33: =VLOOKUP(A33,Table4[#All],3,FALSE) -> 0 | AB33: =IFERROR(VLOOKUP(A33,Table13[[#Headers],[#Data]],7,FALSE),0) -> 0 | AC33: =SUM(Z33:AB33) -> 3 | AD33: =Z33*C33 -> 495 | AE33: =AA33*C33*1.5 -> 0 | AF33: =AB33*C33*2 -> 0 | AG33: =AD33+AE33+AF33 -> 495 | AL33: 4 | AM33: =AC33-AL33 -> -1
A34: KONSTADINIDIS, BILL | B34: QA/QC | C34: =VLOOKUP('1ST Shift'!$B34,Table6[],2,FALSE) -> 165 | L34: =(IF(E34>0,MIN(8,E34),"")) | M34: =IF((E34)>8,SUM(E34-L34),"") | N34: =(IF(F34>0,MIN(8,F34),"")) | O34: =IF((F34)>8,SUM(F34-N34),"") | P34: =(IF(G34>0,MIN(8,G34),"")) | Q34: =IF((G34)>8,SUM(G34-P34),"") | R34: =(IF(H34>0,MIN(8,H34),"")) | S34: =IF((H34)>8,SUM(H34-R34),"") | T34: =(IF(I34>0,MIN(8,I34),"")) | U34: =IF((I34)>8,SUM(I34-T34),"") | V34: =(IF(J34>0,MIN(8,J34),"")) | W34: =IF((J34)>8,SUM(J34-V34),"") | X34: =(IF(K34>0,MIN(8,K34),"")) | Y34: =IF((K34)>8,SUM(K34-X34),"") | Z34: =VLOOKUP(A34,Table4[#All],2,FALSE) -> 0 | AA34: =VLOOKUP(A34,Table4[#All],3,FALSE) -> 0 | AB34: =IFERROR(VLOOKUP(A34,Table13[[#Headers],[#Data]],7,FALSE),0) -> 0 | AC34: =SUM(Z34:AB34) -> 0 | AD34: =Z34*C34 -> 0 | AE34: =AA34*C34*1.5 -> 0 | AF34: =AB34*C34*2 -> 0 | AG34: =AD34+AE34+AF34 -> 0 | AH34: biweekly | AK34: 40 | AL34: 40 | AM34: =AC34-AL34 -> -40
A35: LA CRUZ, JAVIER | B35: Electrician | C35: =VLOOKUP('1ST Shift'!$B35,Table6[],2,FALSE) -> 150 | L35: =(IF(E35>0,MIN(8,E35),"")) | M35: =IF((E35)>8,SUM(E35-L35),"") | N35: =(IF(F35>0,MIN(8,F35),"")) | O35: =IF((F35)>8,SUM(F35-N35),"") | P35: =(IF(G35>0,MIN(8,G35),"")) | Q35: =IF((G35)>8,SUM(G35-P35),"") | R35: =(IF(H35>0,MIN(8,H35),"")) | S35: =IF((H35)>8,SUM(H35-R35),"") | T35: =(IF(I35>0,MIN(8,I35),"")) | U35: =IF((I35)>8,SUM(I35-T35),"") | V35: =(IF(J35>0,MIN(8,J35),"")) | W35: =IF((J35)>8,SUM(J35-V35),"") | X35: =(IF(K35>0,MIN(8,K35),"")) | Y35: =IF((K35)>8,SUM(K35-X35),"") | Z35: =VLOOKUP(A35,Table4[#All],2,FALSE) -> 0 | AA35: =VLOOKUP(A35,Table4[#All],3,FALSE) -> 0 | AB35: =IFERROR(VLOOKUP(A35,Table13[[#Headers],[#Data]],7,FALSE),0) -> 0 | AC35: =SUM(Z35:AB35) -> 0 | AD35: =Z35*C35 -> 0 | AE35: =AA35*C35*1.5 -> 0 | AF35: =AB35*C35*2 -> 0 | AG35: =AD35+AE35+AF35 -> 0
A36: LINO, KEVIN | B36: Electrician | C36: =VLOOKUP('1ST Shift'!$B36,Table6[],2,FALSE) -> 150 | L36: =(IF(E36>0,MIN(8,E36),"")) | M36: =IF((E36)>8,SUM(E36-L36),"") | N36: =(IF(F36>0,MIN(8,F36),"")) | O36: =IF((F36)>8,SUM(F36-N36),"") | P36: =(IF(G36>0,MIN(8,G36),"")) | Q36: =IF((G36)>8,SUM(G36-P36),"") | R36: =(IF(H36>0,MIN(8,H36),"")) | S36: =IF((H36)>8,SUM(H36-R36),"") | T36: =(IF(I36>0,MIN(8,I36),"")) | U36: =IF((I36)>8,SUM(I36-T36),"") | V36: =(IF(J36>0,MIN(8,J36),"")) | W36: =IF((J36)>8,SUM(J36-V36),"") | X36: =(IF(K36>0,MIN(8,K36),"")) | Y36: =IF((K36)>8,SUM(K36-X36),"") | Z36: =VLOOKUP(A36,Table4[#All],2,FALSE) -> 0 | AA36: =VLOOKUP(A36,Table4[#All],3,FALSE) -> 0 | AB36: =IFERROR(VLOOKUP(A36,Table13[[#Headers],[#Data]],7,FALSE),0) -> 0 | AC36: =SUM(Z36:AB36) -> 0 | AD36: =Z36*C36 -> 0 | AE36: =AA36*C36*1.5 -> 0 | AF36: =AB36*C36*2 -> 0 | AG36: =AD36+AE36+AF36 -> 0
A37: MAVAREZ, FABRICIO MOLERO | B37: Electrician | C37: =VLOOKUP('1ST Shift'!$B37,Table6[],2,FALSE) -> 150 | L37: =(IF(E37>0,MIN(8,E37),"")) | M37: =IF((E37)>8,SUM(E37-L37),"") | N37: =(IF(F37>0,MIN(8,F37),"")) | O37: =IF((F37)>8,SUM(F37-N37),"") | P37: =(IF(G37>0,MIN(8,G37),"")) | Q37: =IF((G37)>8,SUM(G37-P37),"") | R37: =(IF(H37>0,MIN(8,H37),"")) | S37: =IF((H37)>8,SUM(H37-R37),"") | T37: =(IF(I37>0,MIN(8,I37),"")) | U37: =IF((I37)>8,SUM(I37-T37),"") | V37: =(IF(J37>0,MIN(8,J37),"")) | W37: =IF((J37)>8,SUM(J37-V37),"") | X37: =(IF(K37>0,MIN(8,K37),"")) | Y37: =IF((K37)>8,SUM(K37-X37),"") | Z37: =VLOOKUP(A37,Table4[#All],2,FALSE) -> 0 | AA37: =VLOOKUP(A37,Table4[#All],3,FALSE) -> 0 | AB37: =IFERROR(VLOOKUP(A37,Table13[[#Headers],[#Data]],7,FALSE),0) -> 0 | AC37: =SUM(Z37:AB37) -> 0 | AD37: =Z37*C37 -> 0 | AE37: =AA37*C37*1.5 -> 0 | AF37: =AB37*C37*2 -> 0 | AG37: =AD37+AE37+AF37 -> 0
A38: TURNER, MIRANDA | B38: Project Coordinator Offsite | C38: =VLOOKUP('1ST Shift'!$B38,Table6[],2,FALSE) -> 165 | L38: =(IF(E38>0,MIN(8,E38),"")) | M38: =IF((E38)>8,SUM(E38-L38),"") | N38: =(IF(F38>0,MIN(8,F38),"")) | O38: =IF((F38)>8,SUM(F38-N38),"") | P38: =(IF(G38>0,MIN(8,G38),"")) | Q38: =IF((G38)>8,SUM(G38-P38),"") | R38: =(IF(H38>0,MIN(8,H38),"")) | S38: =IF((H38)>8,SUM(H38-R38),"") | T38: =(IF(I38>0,MIN(8,I38),"")) | U38: =IF((I38)>8,SUM(I38-T38),"") | V38: =(IF(J38>0,MIN(8,J38),"")) | W38: =IF((J38)>8,SUM(J38-V38),"") | X38: =(IF(K38>0,MIN(8,K38),"")) | Y38: =IF((K38)>8,SUM(K38-X38),"") | Z38: 5.25 | AB38: =IFERROR(VLOOKUP(A38,Table13[[#Headers],[#Data]],7,FALSE),0) -> 0 | AC38: =SUM(Z38:AB38) -> 5.25 | AD38: =Z38*C38 -> 866.25 | AE38: =AA38*C38*1.5 -> 0 | AF38: =AB38*C38*2 -> 0 | AG38: =AD38+AE38+AF38 -> 866.25
A39: MEREZ, JESUS PALOMINO | B39: Electrician | C39: =VLOOKUP('1ST Shift'!$B39,Table6[],2,FALSE) -> 150 | L39: =(IF(E39>0,MIN(8,E39),"")) | M39: =IF((E39)>8,SUM(E39-L39),"") | N39: =(IF(F39>0,MIN(8,F39),"")) | O39: =IF((F39)>8,SUM(F39-N39),"") | P39: =(IF(G39>0,MIN(8,G39),"")) | Q39: =IF((G39)>8,SUM(G39-P39),"") | R39: =(IF(H39>0,MIN(8,H39),"")) | S39: =IF((H39)>8,SUM(H39-R39),"") | T39: =(IF(I39>0,MIN(8,I39),"")) | U39: =IF((I39)>8,SUM(I39-T39),"") | V39: =(IF(J39>0,MIN(8,J39),"")) | W39: =IF((J39)>8,SUM(J39-V39),"") | X39: =(IF(K39>0,MIN(8,K39),"")) | Y39: =IF((K39)>8,SUM(K39-X39),"") | Z39: =VLOOKUP(A39,Table4[#All],2,FALSE) -> 0 | AA39: =VLOOKUP(A39,Table4[#All],3,FALSE) -> 0 | AB39: =IFERROR(VLOOKUP(A39,Table13[[#Headers],[#Data]],7,FALSE),0) -> 0 | AC39: =SUM(Z39:AB39) -> 0 | AD39: =Z39*C39 -> 0 | AE39: =AA39*C39*1.5 -> 0 | AF39: =AB39*C39*2 -> 0 | AG39: =AD39+AE39+AF39 -> 0
A40: MEREDITH, ELISA | B40: Project Coordinator Offsite | C40: =VLOOKUP('1ST Shift'!$B40,Table6[],2,FALSE) -> 165 | L40: =(IF(E40>0,MIN(8,E40),"")) | M40: =IF((E40)>8,SUM(E40-L40),"") | N40: =(IF(F40>0,MIN(8,F40),"")) | O40: =IF((F40)>8,SUM(F40-N40),"") | P40: =(IF(G40>0,MIN(8,G40),"")) | Q40: =IF((G40)>8,SUM(G40-P40),"") | R40: =(IF(H40>0,MIN(8,H40),"")) | S40: =IF((H40)>8,SUM(H40-R40),"") | T40: =(IF(I40>0,MIN(8,I40),"")) | U40: =IF((I40)>8,SUM(I40-T40),"") | V40: =(IF(J40>0,MIN(8,J40),"")) | W40: =IF((J40)>8,SUM(J40-V40),"") | X40: =(IF(K40>0,MIN(8,K40),"")) | Y40: =IF((K40)>8,SUM(K40-X40),"") | Z40: 2 | AA40: =VLOOKUP(A40,Table4[#All],3,FALSE) -> 0 | AB40: =IFERROR(VLOOKUP(A40,Table13[[#Headers],[#Data]],7,FALSE),0) -> 0 | AC40: =SUM(Z40:AB40) -> 2 | AD40: =Z40*C40 -> 330 | AE40: =AA40*C40*1.5 -> 0 | AF40: =AB40*C40*2 -> 0 | AG40: =AD40+AE40+AF40 -> 330
A41: MUBIN, NASIR | B41: QA/QC Director | C41: =VLOOKUP('1ST Shift'!$B41,Table6[],2,FALSE) -> 175 | L41: =(IF(E41>0,MIN(8,E41),"")) | M41: =IF((E41)>8,SUM(E41-L41),"") | N41: =(IF(F41>0,MIN(8,F41),"")) | O41: =IF((F41)>8,SUM(F41-N41),"") | P41: =(IF(G41>0,MIN(8,G41),"")) | Q41: =IF((G41)>8,SUM(G41-P41),"") | R41: =(IF(H41>0,MIN(8,H41),"")) | S41: =IF((H41)>8,SUM(H41-R41),"") | T41: =(IF(I41>0,MIN(8,I41),"")) | U41: =IF((I41)>8,SUM(I41-T41),"") | V41: =(IF(J41>0,MIN(8,J41),"")) | W41: =IF((J41)>8,SUM(J41-V41),"") | X41: =(IF(K41>0,MIN(8,K41),"")) | Y41: =IF((K41)>8,SUM(K41-X41),"") | Z41: =VLOOKUP(A41,Table4[#All],2,FALSE) -> 0 | AA41: =VLOOKUP(A41,Table4[#All],3,FALSE) -> 0 | AB41: =IFERROR(VLOOKUP(A41,Table13[[#Headers],[#Data]],7,FALSE),0) -> 0 | AC41: =SUM(Z41:AB41) -> 0 | AD41: =Z41*C41 -> 0 | AE41: =AA41*C41*1.5 -> 0 | AF41: =AB41*C41*2 -> 0 | AG41: =AD41+AE41+AF41 -> 0
A42: ORDONES, MATHEUS | B42: Electrician | C42: =VLOOKUP('1ST Shift'!$B42,Table6[],2,FALSE) -> 150 | L42: =(IF(E42>0,MIN(8,E42),"")) | M42: =IF((E42)>8,SUM(E42-L42),"") | N42: =(IF(F42>0,MIN(8,F42),"")) | O42: =IF((F42)>8,SUM(F42-N42),"") | P42: =(IF(G42>0,MIN(8,G42),"")) | Q42: =IF((G42)>8,SUM(G42-P42),"") | R42: =(IF(H42>0,MIN(8,H42),"")) | S42: =IF((H42)>8,SUM(H42-R42),"") | T42: =(IF(I42>0,MIN(8,I42),"")) | U42: =IF((I42)>8,SUM(I42-T42),"") | V42: =(IF(J42>0,MIN(8,J42),"")) | W42: =IF((J42)>8,SUM(J42-V42),"") | X42: =(IF(K42>0,MIN(8,K42),"")) | Y42: =IF((K42)>8,SUM(K42-X42),"") | Z42: =VLOOKUP(A42,Table4[#All],2,FALSE) -> 0 | AA42: =VLOOKUP(A42,Table4[#All],3,FALSE) -> 0 | AB42: =IFERROR(VLOOKUP(A42,Table13[[#Headers],[#Data]],7,FALSE),0) -> 0 | AC42: =SUM(Z42:AB42) -> 0 | AD42: =Z42*C42 -> 0 | AE42: =AA42*C42*1.5 -> 0 | AF42: =AB42*C42*2 -> 0 | AG42: =AD42+AE42+AF42 -> 0
A43: OSORIO, JUAN BENCARDINO | B43: Electrician | C43: =VLOOKUP('1ST Shift'!$B43,Table6[],2,FALSE) -> 150 | L43: =(IF(E43>0,MIN(8,E43),"")) | M43: =IF((E43)>8,SUM(E43-L43),"") | N43: =(IF(F43>0,MIN(8,F43),"")) | O43: =IF((F43)>8,SUM(F43-N43),"") | P43: =(IF(G43>0,MIN(8,G43),"")) | Q43: =IF((G43)>8,SUM(G43-P43),"") | R43: =(IF(H43>0,MIN(8,H43),"")) | S43: =IF((H43)>8,SUM(H43-R43),"") | T43: =(IF(I43>0,MIN(8,I43),"")) | U43: =IF((I43)>8,SUM(I43-T43),"") | V43: =(IF(J43>0,MIN(8,J43),"")) | W43: =IF((J43)>8,SUM(J43-V43),"") | X43: =(IF(K43>0,MIN(8,K43),"")) | Y43: =IF((K43)>8,SUM(K43-X43),"") | Z43: =VLOOKUP(A43,Table4[#All],2,FALSE) -> 0 | AA43: =VLOOKUP(A43,Table4[#All],3,FALSE) -> 0 | AB43: =IFERROR(VLOOKUP(A43,Table13[[#Headers],[#Data]],7,FALSE),0) -> 0 | AC43: =SUM(Z43:AB43) -> 0 | AD43: =Z43*C43 -> 0 | AE43: =AA43*C43*1.5 -> 0 | AF43: =AB43*C43*2 -> 0 | AG43: =AD43+AE43+AF43 -> 0
A44: PALMAR, LUIS A. LABARCA | B44: Electrician | C44: =VLOOKUP('1ST Shift'!$B44,Table6[],2,FALSE) -> 150 | L44: =(IF(E44>0,MIN(8,E44),"")) | M44: =IF((E44)>8,SUM(E44-L44),"") | N44: =(IF(F44>0,MIN(8,F44),"")) | O44: =IF((F44)>8,SUM(F44-N44),"") | P44: =(IF(G44>0,MIN(8,G44),"")) | Q44: =IF((G44)>8,SUM(G44-P44),"") | R44: =(IF(H44>0,MIN(8,H44),"")) | S44: =IF((H44)>8,SUM(H44-R44),"") | T44: =(IF(I44>0,MIN(8,I44),"")) | U44: =IF((I44)>8,SUM(I44-T44),"") | V44: =(IF(J44>0,MIN(8,J44),"")) | W44: =IF((J44)>8,SUM(J44-V44),"") | X44: =(IF(K44>0,MIN(8,K44),"")) | Y44: =IF((K44)>8,SUM(K44-X44),"") | Z44: =VLOOKUP(A44,Table4[#All],2,FALSE) -> 0 | AA44: =VLOOKUP(A44,Table4[#All],3,FALSE) -> 0 | AB44: =IFERROR(VLOOKUP(A44,Table13[[#Headers],[#Data]],7,FALSE),0) -> 0 | AC44: =SUM(Z44:AB44) -> 0 | AD44: =Z44*C44 -> 0 | AE44: =AA44*C44*1.5 -> 0 | AF44: =AB44*C44*2 -> 0 | AG44: =AD44+AE44+AF44 -> 0
A45: PERDOMO, FELIX OMAR SEPULVEDA | B45: Electrician | C45: =VLOOKUP('1ST Shift'!$B45,Table6[],2,FALSE) -> 150 | L45: =(IF(E45>0,MIN(8,E45),"")) | M45: =IF((E45)>8,SUM(E45-L45),"") | N45: =(IF(F45>0,MIN(8,F45),"")) | O45: =IF((F45)>8,SUM(F45-N45),"") | P45: =(IF(G45>0,MIN(8,G45),"")) | Q45: =IF((G45)>8,SUM(G45-P45),"") | R45: =(IF(H45>0,MIN(8,H45),"")) | S45: =IF((H45)>8,SUM(H45-R45),"") | T45: =(IF(I45>0,MIN(8,I45),"")) | U45: =IF((I45)>8,SUM(I45-T45),"") | V45: =(IF(J45>0,MIN(8,J45),"")) | W45: =IF((J45)>8,SUM(J45-V45),"") | X45: =(IF(K45>0,MIN(8,K45),"")) | Y45: =IF((K45)>8,SUM(K45-X45),"") | Z45: =VLOOKUP(A45,Table4[#All],2,FALSE) -> 0 | AA45: =VLOOKUP(A45,Table4[#All],3,FALSE) -> 0 | AB45: =IFERROR(VLOOKUP(A45,Table13[[#Headers],[#Data]],7,FALSE),0) -> 0 | AC45: =SUM(Z45:AB45) -> 0 | AD45: =Z45*C45 -> 0 | AE45: =AA45*C45*1.5 -> 0 | AF45: =AB45*C45*2 -> 0 | AG45: =AD45+AE45+AF45 -> 0
A46: PEREIRA, MIGUEL | B46: Electrician | C46: =VLOOKUP('1ST Shift'!$B46,Table6[],2,FALSE) -> 150 | L46: =(IF(E46>0,MIN(8,E46),"")) | M46: =IF((E46)>8,SUM(E46-L46),"") | N46: =(IF(F46>0,MIN(8,F46),"")) | O46: =IF((F46)>8,SUM(F46-N46),"") | P46: =(IF(G46>0,MIN(8,G46),"")) | Q46: =IF((G46)>8,SUM(G46-P46),"") | R46: =(IF(H46>0,MIN(8,H46),"")) | S46: =IF((H46)>8,SUM(H46-R46),"") | T46: =(IF(I46>0,MIN(8,I46),"")) | U46: =IF((I46)>8,SUM(I46-T46),"") | V46: =(IF(J46>0,MIN(8,J46),"")) | W46: =IF((J46)>8,SUM(J46-V46),"") | X46: =(IF(K46>0,MIN(8,K46),"")) | Y46: =IF((K46)>8,SUM(K46-X46),"") | Z46: =VLOOKUP(A46,Table4[#All],2,FALSE) -> 0 | AA46: =VLOOKUP(A46,Table4[#All],3,FALSE) -> 0 | AB46: =IFERROR(VLOOKUP(A46,Table13[[#Headers],[#Data]],7,FALSE),0) -> 0 | AC46: =SUM(Z46:AB46) -> 0 | AD46: =Z46*C46 -> 0 | AE46: =AA46*C46*1.5 -> 0 | AF46: =AB46*C46*2 -> 0 | AG46: =AD46+AE46+AF46 -> 0
A47: PICADO, LARRY | B47: Electrician | C47: =VLOOKUP('1ST Shift'!$B47,Table6[],2,FALSE) -> 150 | L47: =(IF(E47>0,MIN(8,E47),"")) | M47: =IF((E47)>8,SUM(E47-L47),"") | N47: =(IF(F47>0,MIN(8,F47),"")) | O47: =IF((F47)>8,SUM(F47-N47),"") | P47: =(IF(G47>0,MIN(8,G47),"")) | Q47: =IF((G47)>8,SUM(G47-P47),"") | R47: =(IF(H47>0,MIN(8,H47),"")) | S47: =IF((H47)>8,SUM(H47-R47),"") | T47: =(IF(I47>0,MIN(8,I47),"")) | U47: =IF((I47)>8,SUM(I47-T47),"") | V47: =(IF(J47>0,MIN(8,J47),"")) | W47: =IF((J47)>8,SUM(J47-V47),"") | X47: =(IF(K47>0,MIN(8,K47),"")) | Y47: =IF((K47)>8,SUM(K47-X47),"") | Z47: =VLOOKUP(A47,Table4[#All],2,FALSE) -> 0 | AA47: =VLOOKUP(A47,Table4[#All],3,FALSE) -> 0 | AB47: =IFERROR(VLOOKUP(A47,Table13[[#Headers],[#Data]],7,FALSE),0) -> 0 | AC47: =SUM(Z47:AB47) -> 0 | AD47: =Z47*C47 -> 0 | AE47: =AA47*C47*1.5 -> 0 | AF47: =AB47*C47*2 -> 0 | AG47: =AD47+AE47+AF47 -> 0
A48: PINON, JESUS | B48: Electrician | C48: =VLOOKUP('1ST Shift'!$B48,Table6[],2,FALSE) -> 150 | L48: =(IF(E48>0,MIN(8,E48),"")) | M48: =IF((E48)>8,SUM(E48-L48),"") | N48: =(IF(F48>0,MIN(8,F48),"")) | O48: =IF((F48)>8,SUM(F48-N48),"") | P48: =(IF(G48>0,MIN(8,G48),"")) | Q48: =IF((G48)>8,SUM(G48-P48),"") | R48: =(IF(H48>0,MIN(8,H48),"")) | S48: =IF((H48)>8,SUM(H48-R48),"") | T48: =(IF(I48>0,MIN(8,I48),"")) | U48: =IF((I48)>8,SUM(I48-T48),"") | V48: =(IF(J48>0,MIN(8,J48),"")) | W48: =IF((J48)>8,SUM(J48-V48),"") | X48: =(IF(K48>0,MIN(8,K48),"")) | Y48: =IF((K48)>8,SUM(K48-X48),"") | Z48: =VLOOKUP(A48,Table4[#All],2,FALSE) -> 0 | AA48: =VLOOKUP(A48,Table4[#All],3,FALSE) -> 0 | AB48: =IFERROR(VLOOKUP(A48,Table13[[#Headers],[#Data]],7,FALSE),0) -> 0 | AC48: =SUM(Z48:AB48) -> 0 | AD48: =Z48*C48 -> 0 | AE48: =AA48*C48*1.5 -> 0 | AF48: =AB48*C48*2 -> 0 | AG48: =AD48+AE48+AF48 -> 0
A49: QUERALES, YOHANY | B49: Electrician | C49: =VLOOKUP('1ST Shift'!$B49,Table6[],2,FALSE) -> 150 | L49: =(IF(E49>0,MIN(8,E49),"")) | M49: =IF((E49)>8,SUM(E49-L49),"") | N49: =(IF(F49>0,MIN(8,F49),"")) | O49: =IF((F49)>8,SUM(F49-N49),"") | P49: =(IF(G49>0,MIN(8,G49),"")) | Q49: =IF((G49)>8,SUM(G49-P49),"") | R49: =(IF(H49>0,MIN(8,H49),"")) | S49: =IF((H49)>8,SUM(H49-R49),"") | T49: =(IF(I49>0,MIN(8,I49),"")) | U49: =IF((I49)>8,SUM(I49-T49),"") | V49: =(IF(J49>0,MIN(8,J49),"")) | W49: =IF((J49)>8,SUM(J49-V49),"") | X49: =(IF(K49>0,MIN(8,K49),"")) | Y49: =IF((K49)>8,SUM(K49-X49),"") | Z49: =VLOOKUP(A49,Table4[#All],2,FALSE) -> 0 | AA49: =VLOOKUP(A49,Table4[#All],3,FALSE) -> 0 | AB49: =IFERROR(VLOOKUP(A49,Table13[[#Headers],[#Data]],7,FALSE),0) -> 0 | AC49: =SUM(Z49:AB49) -> 0 | AD49: =Z49*C49 -> 0 | AE49: =AA49*C49*1.5 -> 0 | AF49: =AB49*C49*2 -> 0 | AG49: =AD49+AE49+AF49 -> 0
A50: RAMOS, DAVID | B50: Electrician | C50: =VLOOKUP('1ST Shift'!$B50,Table6[],2,FALSE) -> 150 | L50: =(IF(E50>0,MIN(8,E50),"")) | M50: =IF((E50)>8,SUM(E50-L50),"") | N50: =(IF(F50>0,MIN(8,F50),"")) | O50: =IF((F50)>8,SUM(F50-N50),"") | P50: =(IF(G50>0,MIN(8,G50),"")) | Q50: =IF((G50)>8,SUM(G50-P50),"") | R50: =(IF(H50>0,MIN(8,H50),"")) | S50: =IF((H50)>8,SUM(H50-R50),"") | T50: =(IF(I50>0,MIN(8,I50),"")) | U50: =IF((I50)>8,SUM(I50-T50),"") | V50: =(IF(J50>0,MIN(8,J50),"")) | W50: =IF((J50)>8,SUM(J50-V50),"") | X50: =(IF(K50>0,MIN(8,K50),"")) | Y50: =IF((K50)>8,SUM(K50-X50),"") | Z50: =VLOOKUP(A50,Table4[#All],2,FALSE) -> 0 | AA50: =VLOOKUP(A50,Table4[#All],3,FALSE) -> 0 | AB50: =IFERROR(VLOOKUP(A50,Table13[[#Headers],[#Data]],7,FALSE),0) -> 0 | AC50: =SUM(Z50:AB50) -> 0 | AD50: =Z50*C50 -> 0 | AE50: =AA50*C50*1.5 -> 0 | AF50: =AB50*C50*2 -> 0 | AG50: =AD50+AE50+AF50 -> 0
A51: REYES, JOSE PUENTE | B51: Electrician | C51: =VLOOKUP('1ST Shift'!$B51,Table6[],2,FALSE) -> 150 | L51: =(IF(E51>0,MIN(8,E51),"")) | M51: =IF((E51)>8,SUM(E51-L51),"") | N51: =(IF(F51>0,MIN(8,F51),"")) | O51: =IF((F51)>8,SUM(F51-N51),"") | P51: =(IF(G51>0,MIN(8,G51),"")) | Q51: =IF((G51)>8,SUM(G51-P51),"") | R51: =(IF(H51>0,MIN(8,H51),"")) | S51: =IF((H51)>8,SUM(H51-R51),"") | T51: =(IF(I51>0,MIN(8,I51),"")) | U51: =IF((I51)>8,SUM(I51-T51),"") | V51: =(IF(J51>0,MIN(8,J51),"")) | W51: =IF((J51)>8,SUM(J51-V51),"") | X51: =(IF(K51>0,MIN(8,K51),"")) | Y51: =IF((K51)>8,SUM(K51-X51),"") | Z51: =VLOOKUP(A51,Table4[#All],2,FALSE) -> 0 | AA51: =VLOOKUP(A51,Table4[#All],3,FALSE) -> 0 | AB51: =IFERROR(VLOOKUP(A51,Table13[[#Headers],[#Data]],7,FALSE),0) -> 0 | AC51: =SUM(Z51:AB51) -> 0 | AD51: =Z51*C51 -> 0 | AE51: =AA51*C51*1.5 -> 0 | AF51: =AB51*C51*2 -> 0 | AG51: =AD51+AE51+AF51 -> 0
A52: REYES, HELIVER | B52: Electrician | C52: =VLOOKUP('1ST Shift'!$B52,Table6[],2,FALSE) -> 150 | L52: =(IF(E52>0,MIN(8,E52),"")) | M52: =IF((E52)>8,SUM(E52-L52),"") | N52: =(IF(F52>0,MIN(8,F52),"")) | O52: =IF((F52)>8,SUM(F52-N52),"") | P52: =(IF(G52>0,MIN(8,G52),"")) | Q52: =IF((G52)>8,SUM(G52-P52),"") | R52: =(IF(H52>0,MIN(8,H52),"")) | S52: =IF((H52)>8,SUM(H52-R52),"") | T52: =(IF(I52>0,MIN(8,I52),"")) | U52: =IF((I52)>8,SUM(I52-T52),"") | V52: =(IF(J52>0,MIN(8,J52),"")) | W52: =IF((J52)>8,SUM(J52-V52),"") | X52: =(IF(K52>0,MIN(8,K52),"")) | Y52: =IF((K52)>8,SUM(K52-X52),"") | Z52: =VLOOKUP(A52,Table4[#All],2,FALSE) -> 0 | AA52: =VLOOKUP(A52,Table4[#All],3,FALSE) -> 0 | AB52: =IFERROR(VLOOKUP(A52,Table13[[#Headers],[#Data]],7,FALSE),0) -> 0 | AC52: =SUM(Z52:AB52) -> 0 | AD52: =Z52*C52 -> 0 | AE52: =AA52*C52*1.5 -> 0 | AF52: =AB52*C52*2 -> 0 | AG52: =AD52+AE52+AF52 -> 0
... A55: ROMERO, GABRIEL | B55: Electrician | C55: =VLOOKUP('1ST Shift'!$B55,Table6[],2,FALSE) -> 150 | L55: =(IF(E55>0,MIN(8,E55),"")) | M55: =IF((E55)>8,SUM(E55-L55),"") | N55: =(IF(F55>0,MIN(8,F55),"")) | O55: =IF((F55)>8,SUM(F55-N55),"") | P55: =(IF(G55>0,MIN(8,G55),"")) | Q55: =IF((G55)>8,SUM(G55-P55),"") | R55: =(IF(H55>0,MIN(8,H55),"")) | S55: =IF((H55)>8,SUM(H55-R55),"") | T55: =(IF(I55>0,MIN(8,I55),"")) | U55: =IF((I55)>8,SUM(I55-T55),"") | V55: =(IF(J55>0,MIN(8,J55),"")) | W55: =IF((J55)>8,SUM(J55-V55),"") | X55: =(IF(K55>0,MIN(8,K55),"")) | Y55: =IF((K55)>8,SUM(K55-X55),"") | Z55: =VLOOKUP(A55,Table4[#All],2,FALSE) -> 0 | AA55: =VLOOKUP(A55,Table4[#All],3,FALSE) -> 0 | AB55: =IFERROR(VLOOKUP(A55,Table13[[#Headers],[#Data]],7,FALSE),0) -> 0 | AC55: =SUM(Z55:AB55) -> 0 | AD55: =Z55*C55 -> 0 | AE55: =AA55*C55*1.5 -> 0 | AF55: =AB55*C55*2 -> 0 | AG55: =AD55+AE55+AF55 -> 0
A56: ROCCO, CLINT | B56: QA/QC | C56: =VLOOKUP('1ST Shift'!$B56,Table6[],2,FALSE) -> 165 | L56: =(IF(E56>0,MIN(8,E56),"")) | M56: =IF((E56)>8,SUM(E56-L56),"") | N56: =(IF(F56>0,MIN(8,F56),"")) | O56: =IF((F56)>8,SUM(F56-N56),"") | P56: =(IF(G56>0,MIN(8,G56),"")) | Q56: =IF((G56)>8,SUM(G56-P56),"") | R56: =(IF(H56>0,MIN(8,H56),"")) | S56: =IF((H56)>8,SUM(H56-R56),"") | T56: =(IF(I56>0,MIN(8,I56),"")) | U56: =IF((I56)>8,SUM(I56-T56),"") | V56: =(IF(J56>0,MIN(8,J56),"")) | W56: =IF((J56)>8,SUM(J56-V56),"") | X56: =(IF(K56>0,MIN(8,K56),"")) | Y56: =IF((K56)>8,SUM(K56-X56),"") | Z56: =VLOOKUP(A56,Table4[#All],2,FALSE) -> 0 | AA56: =VLOOKUP(A56,Table4[#All],3,FALSE) -> 0 | AB56: =IFERROR(VLOOKUP(A56,Table13[[#Headers],[#Data]],7,FALSE),0) -> 0 | AC56: =SUM(Z56:AB56) -> 0 | AD56: =Z56*C56 -> 0 | AE56: =AA56*C56*1.5 -> 0 | AF56: =AB56*C56*2 -> 0 | AG56: =AD56+AE56+AF56 -> 0 | AH56: Biweekly | AK56: 40 | AL56: 49.25 | AM56: =AC56-AL56 -> -49.25
A57: SANTOS, CRISTOBAL | B57: Electrician | C57: =VLOOKUP('1ST Shift'!$B57,Table6[],2,FALSE) -> 150 | L57: =(IF(E57>0,MIN(8,E57),"")) | M57: =IF((E57)>8,SUM(E57-L57),"") | N57: =(IF(F57>0,MIN(8,F57),"")) | O57: =IF((F57)>8,SUM(F57-N57),"") | P57: =(IF(G57>0,MIN(8,G57),"")) | Q57: =IF((G57)>8,SUM(G57-P57),"") | R57: =(IF(H57>0,MIN(8,H57),"")) | S57: =IF((H57)>8,SUM(H57-R57),"") | T57: =(IF(I57>0,MIN(8,I57),"")) | U57: =IF((I57)>8,SUM(I57-T57),"") | V57: =(IF(J57>0,MIN(8,J57),"")) | W57: =IF((J57)>8,SUM(J57-V57),"") | X57: =(IF(K57>0,MIN(8,K57),"")) | Y57: =IF((K57)>8,SUM(K57-X57),"") | Z57: =VLOOKUP(A57,Table4[#All],2,FALSE) -> 0 | AA57: =VLOOKUP(A57,Table4[#All],3,FALSE) -> 0 | AB57: =IFERROR(VLOOKUP(A57,Table13[[#Headers],[#Data]],7,FALSE),0) -> 0 | AC57: =SUM(Z57:AB57) -> 0 | AD57: =Z57*C57 -> 0 | AE57: =AA57*C57*1.5 -> 0 | AF57: =AB57*C57*2 -> 0 | AG57: =AD57+AE57+AF57 -> 0
A58: SCHESKE, TRENT | B58: Project Manager | C58: =VLOOKUP('1ST Shift'!$B58,Table6[],2,FALSE) -> 175 | L58: =(IF(E58>0,MIN(8,E58),"")) | M58: =IF((E58)>8,SUM(E58-L58),"") | N58: =(IF(F58>0,MIN(8,F58),"")) | O58: =IF((F58)>8,SUM(F58-N58),"") | P58: =(IF(G58>0,MIN(8,G58),"")) | Q58: =IF((G58)>8,SUM(G58-P58),"") | R58: =(IF(H58>0,MIN(8,H58),"")) | S58: =IF((H58)>8,SUM(H58-R58),"") | T58: =(IF(I58>0,MIN(8,I58),"")) | U58: =IF((I58)>8,SUM(I58-T58),"") | V58: =(IF(J58>0,MIN(8,J58),"")) | W58: =IF((J58)>8,SUM(J58-V58),"") | X58: =(IF(K58>0,MIN(8,K58),"")) | Y58: =IF((K58)>8,SUM(K58-X58),"") | AA58: =VLOOKUP(A58,Table4[#All],3,FALSE) -> 0 | AB58: =IFERROR(VLOOKUP(A58,Table13[[#Headers],[#Data]],7,FALSE),0) -> 0 | AC58: =SUM(Z58:AB58) -> 0 | AD58: =Z58*C58 -> 0 | AE58: =AA58*C58*1.5 -> 0 | AF58: =AB58*C58*2 -> 0 | AG58: =AD58+AE58+AF58 -> 0
A59: SEVERSON, SCOTT | B59: QA/QC | C59: =VLOOKUP('1ST Shift'!$B59,Table6[],2,FALSE) -> 165 | L59: =(IF(E59>0,MIN(8,E59),"")) | M59: =IF((E59)>8,SUM(E59-L59),"") | N59: =(IF(F59>0,MIN(8,F59),"")) | O59: =IF((F59)>8,SUM(F59-N59),"") | P59: =(IF(G59>0,MIN(8,G59),"")) | Q59: =IF((G59)>8,SUM(G59-P59),"") | R59: =(IF(H59>0,MIN(8,H59),"")) | S59: =IF((H59)>8,SUM(H59-R59),"") | T59: =(IF(I59>0,MIN(8,I59),"")) | U59: =IF((I59)>8,SUM(I59-T59),"") | V59: =(IF(J59>0,MIN(8,J59),"")) | W59: =IF((J59)>8,SUM(J59-V59),"") | X59: =(IF(K59>0,MIN(8,K59),"")) | Y59: =IF((K59)>8,SUM(K59-X59),"") | Z59: =VLOOKUP(A59,Table4[#All],2,FALSE) -> 0 | AA59: =VLOOKUP(A59,Table4[#All],3,FALSE) -> 0 | AB59: =IFERROR(VLOOKUP(A59,Table13[[#Headers],[#Data]],7,FALSE),0) -> 0 | AC59: =SUM(Z59:AB59) -> 0 | AD59: =Z59*C59 -> 0 | AE59: =AA59*C59*1.5 -> 0 | AF59: =AB59*C59*2 -> 0 | AG59: =AD59+AE59+AF59 -> 0 | AH59: Biweekly | AM59: =AC59-AL59 -> 0
A60: SUDANO, ANTONIO | B60: Electrician | C60: =VLOOKUP('1ST Shift'!$B60,Table6[],2,FALSE) -> 150 | L60: =(IF(E60>0,MIN(8,E60),"")) | M60: =IF((E60)>8,SUM(E60-L60),"") | N60: =(IF(F60>0,MIN(8,F60),"")) | O60: =IF((F60)>8,SUM(F60-N60),"") | P60: =(IF(G60>0,MIN(8,G60),"")) | Q60: =IF((G60)>8,SUM(G60-P60),"") | R60: =(IF(H60>0,MIN(8,H60),"")) | S60: =IF((H60)>8,SUM(H60-R60),"") | T60: =(IF(I60>0,MIN(8,I60),"")) | U60: =IF((I60)>8,SUM(I60-T60),"") | V60: =(IF(J60>0,MIN(8,J60),"")) | W60: =IF((J60)>8,SUM(J60-V60),"") | X60: =(IF(K60>0,MIN(8,K60),"")) | Y60: =IF((K60)>8,SUM(K60-X60),"") | Z60: =VLOOKUP(A60,Table4[#All],2,FALSE) -> 0 | AA60: =VLOOKUP(A60,Table4[#All],3,FALSE) -> 0 | AB60: =IFERROR(VLOOKUP(A60,Table13[[#Headers],[#Data]],7,FALSE),0) -> 0 | AC60: =SUM(Z60:AB60) -> 0 | AD60: =Z60*C60 -> 0 | AE60: =AA60*C60*1.5 -> 0 | AF60: =AB60*C60*2 -> 0 | AG60: =AD60+AE60+AF60 -> 0
A61: TORRES, EVER | B61: Electrician | C61: =VLOOKUP('1ST Shift'!$B61,Table6[],2,FALSE) -> 150 | L61: =(IF(E61>0,MIN(8,E61),"")) | M61: =IF((E61)>8,SUM(E61-L61),"") | N61: =(IF(F61>0,MIN(8,F61),"")) | O61: =IF((F61)>8,SUM(F61-N61),"") | P61: =(IF(G61>0,MIN(8,G61),"")) | Q61: =IF((G61)>8,SUM(G61-P61),"") | R61: =(IF(H61>0,MIN(8,H61),"")) | S61: =IF((H61)>8,SUM(H61-R61),"") | T61: =(IF(I61>0,MIN(8,I61),"")) | U61: =IF((I61)>8,SUM(I61-T61),"") | V61: =(IF(J61>0,MIN(8,J61),"")) | W61: =IF((J61)>8,SUM(J61-V61),"") | X61: =(IF(K61>0,MIN(8,K61),"")) | Y61: =IF((K61)>8,SUM(K61-X61),"") | Z61: =VLOOKUP(A61,Table4[#All],2,FALSE) -> 0 | AA61: =VLOOKUP(A61,Table4[#All],3,FALSE) -> 0 | AB61: =IFERROR(VLOOKUP(A61,Table13[[#Headers],[#Data]],7,FALSE),0) -> 0 | AC61: =SUM(Z61:AB61) -> 0 | AD61: =Z61*C61 -> 0 | AE61: =AA61*C61*1.5 -> 0 | AF61: =AB61*C61*2 -> 0 | AG61: =AD61+AE61+AF61 -> 0
A62: URDANETA, RONALD | B62: Electrician | C62: =VLOOKUP('1ST Shift'!$B62,Table6[],2,FALSE) -> 150 | L62: =(IF(E62>0,MIN(8,E62),"")) | M62: =IF((E62)>8,SUM(E62-L62),"") | N62: =(IF(F62>0,MIN(8,F62),"")) | O62: =IF((F62)>8,SUM(F62-N62),"") | P62: =(IF(G62>0,MIN(8,G62),"")) | Q62: =IF((G62)>8,SUM(G62-P62),"") | R62: =(IF(H62>0,MIN(8,H62),"")) | S62: =IF((H62)>8,SUM(H62-R62),"") | T62: =(IF(I62>0,MIN(8,I62),"")) | U62: =IF((I62)>8,SUM(I62-T62),"") | V62: =(IF(J62>0,MIN(8,J62),"")) | W62: =IF((J62)>8,SUM(J62-V62),"") | X62: =(IF(K62>0,MIN(8,K62),"")) | Y62: =IF((K62)>8,SUM(K62-X62),"") | Z62: =VLOOKUP(A62,Table4[#All],2,FALSE) -> 0 | AA62: =VLOOKUP(A62,Table4[#All],3,FALSE) -> 0 | AB62: =IFERROR(VLOOKUP(A62,Table13[[#Headers],[#Data]],7,FALSE),0) -> 0 | AC62: =SUM(Z62:AB62) -> 0 | AD62: =Z62*C62 -> 0 | AE62: =AA62*C62*1.5 -> 0 | AF62: =AB62*C62*2 -> 0 | AG62: =AD62+AE62+AF62 -> 0
A63: VILLAGOMEZ, ADOLFO PINON | B63: Electrician | C63: =VLOOKUP('1ST Shift'!$B63,Table6[],2,FALSE) -> 150 | L63: =(IF(E63>0,MIN(8,E63),"")) | M63: =IF((E63)>8,SUM(E63-L63),"") | N63: =(IF(F63>0,MIN(8,F63),"")) | O63: =IF((F63)>8,SUM(F63-N63),"") | P63: =(IF(G63>0,MIN(8,G63),"")) | Q63: =IF((G63)>8,SUM(G63-P63),"") | R63: =(IF(H63>0,MIN(8,H63),"")) | S63: =IF((H63)>8,SUM(H63-R63),"") | T63: =(IF(I63>0,MIN(8,I63),"")) | U63: =IF((I63)>8,SUM(I63-T63),"") | V63: =(IF(J63>0,MIN(8,J63),"")) | W63: =IF((J63)>8,SUM(J63-V63),"") | X63: =(IF(K63>0,MIN(8,K63),"")) | Y63: =IF((K63)>8,SUM(K63-X63),"") | Z63: =VLOOKUP(A63,Table4[#All],2,FALSE) -> 0 | AA63: =VLOOKUP(A63,Table4[#All],3,FALSE) -> 0 | AB63: =IFERROR(VLOOKUP(A63,Table13[[#Headers],[#Data]],7,FALSE),0) -> 0 | AC63: =SUM(Z63:AB63) -> 0 | AD63: =Z63*C63 -> 0 | AE63: =AA63*C63*1.5 -> 0 | AF63: =AB63*C63*2 -> 0 | AG63: =AD63+AE63+AF63 -> 0
A64: VILLEGAS, JOSE | B64: Electrician | C64: =VLOOKUP('1ST Shift'!$B64,Table6[],2,FALSE) -> 150 | L64: =(IF(E64>0,MIN(8,E64),"")) | M64: =IF((E64)>8,SUM(E64-L64),"") | N64: =(IF(F64>0,MIN(8,F64),"")) | O64: =IF((F64)>8,SUM(F64-N64),"") | P64: =(IF(G64>0,MIN(8,G64),"")) | Q64: =IF((G64)>8,SUM(G64-P64),"") | R64: =(IF(H64>0,MIN(8,H64),"")) | S64: =IF((H64)>8,SUM(H64-R64),"") | T64: =(IF(I64>0,MIN(8,I64),"")) | U64: =IF((I64)>8,SUM(I64-T64),"") | V64: =(IF(J64>0,MIN(8,J64),"")) | W64: =IF((J64)>8,SUM(J64-V64),"") | X64: =(IF(K64>0,MIN(8,K64),"")) | Y64: =IF((K64)>8,SUM(K64-X64),"") | Z64: =VLOOKUP(A64,Table4[#All],2,FALSE) -> 0 | AA64: =VLOOKUP(A64,Table4[#All],3,FALSE) -> 0 | AB64: =IFERROR(VLOOKUP(A64,Table13[[#Headers],[#Data]],7,FALSE),0) -> 0 | AC64: =SUM(Z64:AB64) -> 0 | AD64: =Z64*C64 -> 0 | AE64: =AA64*C64*1.5 -> 0 | AF64: =AB64*C64*2 -> 0 | AG64: =AD64+AE64+AF64 -> 0
A65: YAMEZ, JESUS VALECILLOS | B65: Electrician | C65: =VLOOKUP('1ST Shift'!$B65,Table6[],2,FALSE) -> 150 | L65: =(IF(E65>0,MIN(8,E65),"")) | M65: =IF((E65)>8,SUM(E65-L65),"") | N65: =(IF(F65>0,MIN(8,F65),"")) | O65: =IF((F65)>8,SUM(F65-N65),"") | P65: =(IF(G65>0,MIN(8,G65),"")) | Q65: =IF((G65)>8,SUM(G65-P65),"") | R65: =(IF(H65>0,MIN(8,H65),"")) | S65: =IF((H65)>8,SUM(H65-R65),"") | T65: =(IF(I65>0,MIN(8,I65),"")) | U65: =IF((I65)>8,SUM(I65-T65),"") | V65: =(IF(J65>0,MIN(8,J65),"")) | W65: =IF((J65)>8,SUM(J65-V65),"") | X65: =(IF(K65>0,MIN(8,K65),"")) | Y65: =IF((K65)>8,SUM(K65-X65),"") | Z65: =VLOOKUP(A65,Table4[#All],2,FALSE) -> 0 | AA65: =VLOOKUP(A65,Table4[#All],3,FALSE) -> 0 | AB65: =IFERROR(VLOOKUP(A65,Table13[[#Headers],[#Data]],7,FALSE),0) -> 0 | AC65: =SUM(Z65:AB65) -> 0 | AD65: =Z65*C65 -> 0 | AE65: =AA65*C65*1.5 -> 0 | AF65: =AB65*C65*2 -> 0 | AG65: =AD65+AE65+AF65 -> 0
A66: VERONA, JOSEPH | B66: Project Manager | C66: =VLOOKUP('1ST Shift'!$B66,Table6[],2,FALSE) -> 175 | L66: =(IF(E66>0,MIN(8,E66),"")) | M66: =IF((E66)>8,SUM(E66-L66),"") | N66: =(IF(F66>0,MIN(8,F66),"")) | O66: =IF((F66)>8,SUM(F66-N66),"") | P66: =(IF(G66>0,MIN(8,G66),"")) | Q66: =IF((G66)>8,SUM(G66-P66),"") | R66: =(IF(H66>0,MIN(8,H66),"")) | S66: =IF((H66)>8,SUM(H66-R66),"") | T66: =(IF(I66>0,MIN(8,I66),"")) | U66: =IF((I66)>8,SUM(I66-T66),"") | V66: =(IF(J66>0,MIN(8,J66),"")) | W66: =IF((J66)>8,SUM(J66-V66),"") | X66: =(IF(K66>0,MIN(8,K66),"")) | Y66: =IF((K66)>8,SUM(K66-X66),"") | Z66: 2 | AA66: 0 | AB66: =IFERROR(VLOOKUP(A66,Table13[[#Headers],[#Data]],7,FALSE),0) -> 0 | AC66: =SUM(Z66:AB66) -> 2 | AD66: =Z66*C66 -> 350 | AE66: =AA66*C66*1.5 -> 0 | AF66: =AB66*C66*2 -> 0 | AG66: =AD66+AE66+AF66 -> 350 | AL66: 6 | AM66: =AC66-AL66 -> -4
A67: VO, AMANDA JOYCE | B67: Project Coordinator Offsite | C67: =VLOOKUP('1ST Shift'!$B67,Table6[],2,FALSE) -> 165 | L67: =(IF(E67>0,MIN(8,E67),"")) | M67: =IF((E67)>8,SUM(E67-L67),"") | N67: =(IF(F67>0,MIN(8,F67),"")) | O67: =IF((F67)>8,SUM(F67-N67),"") | P67: =(IF(G67>0,MIN(8,G67),"")) | Q67: =IF((G67)>8,SUM(G67-P67),"") | R67: =(IF(H67>0,MIN(8,H67),"")) | S67: =IF((H67)>8,SUM(H67-R67),"") | T67: =(IF(I67>0,MIN(8,I67),"")) | U67: =IF((I67)>8,SUM(I67-T67),"") | V67: =(IF(J67>0,MIN(8,J67),"")) | W67: =IF((J67)>8,SUM(J67-V67),"") | X67: =(IF(K67>0,MIN(8,K67),"")) | Y67: =IF((K67)>8,SUM(K67-X67),"") | Z67: =VLOOKUP(A67,Table4[#All],2,FALSE) -> 0 | AA67: =VLOOKUP(A67,Table4[#All],3,FALSE) -> 0 | AB67: =IFERROR(VLOOKUP(A67,Table13[[#Headers],[#Data]],7,FALSE),0) -> 0 | AC67: =SUM(Z67:AB67) -> 0 | AD67: =Z67*C67 -> 0 | AE67: =AA67*C67*1.5 -> 0 | AF67: =AB67*C67*2 -> 0 | AG67: =AD67+AE67+AF67 -> 0
A68: All Labor Totals | E68: =SUM(E14:E67) -> 0 | F68: =SUM(F14:F67) -> 0 | G68: =SUM(G14:G67) -> 0 | H68: =SUM(H14:H67) -> 0 | I68: =SUM(I14:I67) -> 0 | J68: =SUM(J14:J67) -> 0 | K68: =SUM(K14:K67) -> 0 | L68: =SUM(L14:L67) -> 0 | ... Y68: =SUM(Y14:Y67) -> 0 | Z68: =SUM(Z10:Z67) -> 12.25 | AA68: =SUM(AA10:AA67) -> 0 | AB68: =SUM(AB14:AB67) -> 0 | AC68: =SUM(AC10:AC67) -> 12.25 | AD68: =SUM(AD14:AD67) -> 2041.25 | AE68: =SUM(AE14:AE67) -> 0 | AF68: =SUM(AF14:AF67) -> 0 | AG68: =SUM(AG14:AG67) -> 2041.25
AC69: =AC68+'2ND SHIFT'!AC294 -> #REF!
AD70: =AC69+#REF!+#REF!+#REF! -> #REF!
AE71: =AC69+102.5 -> #REF!
Z74: Sheets | AC74: ET | AD74: Difference
Z75: =AC68 -> 12.25 | AA75: 6009 | AC75: =AC68 -> 12.25 | AD75: =Z75-AC75 -> 0
Z76: ='2ND SHIFT'!AC294 -> #REF! | AA76: 6010 | AC76: 11.5 | AD76: =Z76-AC76 -> #REF!
AH77: =923+57 -> 980
Z81: ='6007 1st '!AC183 -> 0 | AD81: =Z81-AC81 -> 0
B82: =1982.75+Z87+Z90+Z91+Z92+Z93 -> 1982.75 | Z82: ='6008 2nd'!AC183 -> 0 | AD82: =Z82-AC82 -> 0
Z83: ='1ST Shift'!AC70 -> 0 | AD83: =Z83-AC83 -> 0
Z84: ='6011 1ST'!AC171 -> 0 | AD84: =Z84-AC84 -> 0
Z86: =AC68+17 -> 29.25 | AA86: All Spreadsheet total on Spreadsheet
AA87: Minus Biweekly Hours - not on this paycheck date
Z89: 10 | AA89: Add back in Drive Time Hours | AI89: =Z86-Z87+Z89+#REF!-Z90+Z91+Z92-Z96 -> #REF!
Z96: =Z86-Z87+Z89-Z90-Z91-Z92-Z93+Z94+Z88-Z95 -> 39.25 | AA96: Spreadsheet total minus hours that will not be found on Specturm
Z97: 568 | AA97: Spectrum Total
Z98: =Z96-Z97 -> -528.75 | AA98: Difference Sheet Vs Spectrum (This should be Zero)

Sheet 6001 1st
A1: 6001 Original ROM TM Labor 1st Shift | AO1: on 8.15.25 payroll previously billed | AP1: will hit 8.29.25 | AQ1: Should be on JCH
A2: INPWR INVOICE NUMBER | B2: ='INVOICE COVER 7256'!F3 -> 25108-09
A3: CUSTOMER REFERENCE | B3: ='INVOICE COVER 7256'!D5 -> 7256
A4: JOB NAME | B4: ='INVOICE COVER 7256'!C5 -> Marble NC
A5: JOB NUMBER | B5: ='INVOICE COVER 7256'!E5 -> 25108
A6: Period Ending Week-ending 8.10.25 Thru | B6: ='INVOICE COVER 7256'!F5 -> 45942
A7: EMPLOYEE NAME | B7: CLASS | C7: REGULAR | D7: Per Diem | E7: PER DAY | L7: =B6-6 -> 45936 | N7: =B6-5 -> 45937 | P7: =B6-4 -> 45938 | R7: =B6-3 -> 45939 | T7: =B6-2 -> 45940 | V7: =B6-1 -> 45941 | X7: =B6 -> 45942 | Z7: REG | AA7: OT | AB7: DT | AC7: Total | AD7: ST. LABOR | AE7: OT LABOR | AF7: DT LABOR | AG7: LABOR
C8: RATE | D8: Y/N | E8: =B6-6 -> 45936 | F8: =E8+1 -> 45937 | G8: =F8+1 -> 45938 | H8: =G8+1 -> 45939 | I8: =H8+1 -> 45940 | J8: =I8+1 -> 45941 | K8: =J8+1 -> 45942 | L8: REG. | M8: OT | N8: REG. | O8: OT | P8: REG | Q8: OT | R8: REG | S8: OT | T8: REG | U8: OT | V8: REG | W8: OT | X8: REG | Y8: OT | Z8: TOT | AA8: TOT | AB8: Hours | AC8: Hours | AD8: TOTAL | AE8: TOTAL | AF8: TOTAL | AG8: TOTAL
A9: MUBIN, NASIR | B9: QA/QC | C9: =VLOOKUP('6001 1st'!$B9,Table6[],2,FALSE) -> 165 | L9: =(IF(E9>0,MIN(8,E9),"")) | M9: =IF((E9)>8,SUM(E9-L9),"") | N9: =(IF(F9>0,MIN(8,F9),"")) | O9: =IF((F9)>8,SUM(F9-N9),"") | P9: =(IF(G9>0,MIN(8,G9),"")) | Q9: =IF((G9)>8,SUM(G9-P9),"") | R9: =(IF(H9>0,MIN(8,H9),"")) | S9: =IF((H9)>8,SUM(H9-R9),"") | T9: =(IF(I9>0,MIN(8,I9),"")) | U9: =IF((I9)>8,SUM(I9-T9),"") | V9: =(IF(J9>0,MIN(8,J9),"")) | W9: =IF((J9)>8,SUM(J9-V9),"") | X9: =(IF(K9>0,MIN(8,K9),"")) | Y9: =IF((K9)>8,SUM(K9-X9),"") | Z9: =VLOOKUP(A9,#REF!,5,FALSE) -> #REF! | AA9: =VLOOKUP(A9,#REF!,6,FALSE) -> #REF! | AC9: =SUM(Z9:AB9) -> #REF! | AD9: =Z9*C9 -> #REF! | AE9: =AA9*C9*1.5 -> #REF! | AF9: =AB9*C9*2 -> 0 | AG9: =AD9+AE9+AF9 -> #REF!
A10: ACERO, MAURICIO | B10: Electrician | C10: =VLOOKUP('6001 1st'!$B10,Table6[],2,FALSE) -> 150 | Z10: =VLOOKUP(A10,#REF!,5,FALSE) -> #REF! | AA10: =VLOOKUP(A10,#REF!,6,FALSE) -> #REF! | AB10: =IFERROR(VLOOKUP(A10,Table13[[#Headers],[#Data]],7,FALSE),0) -> 0 | AC10: =SUM(Z10:AB10) -> #REF! | AD10: =Z10*C10 -> #REF! | AE10: =AA10*C10*1.5 -> #REF! | AF10: =AB10*C10*2 -> 0 | AG10: =AD10+AE10+AF10 -> #REF!
A11: AGUERO, JONATHAN | B11: Electrician | C11: =VLOOKUP('6001 1st'!$B11,Table6[],2,FALSE) -> 150 | L11: =(IF(E11>0,MIN(8,E11),"")) | M11: =IF((E11)>8,SUM(E11-L11),"") | N11: =(IF(F11>0,MIN(8,F11),"")) | O11: =IF((F11)>8,SUM(F11-N11),"") | P11: =(IF(G11>0,MIN(8,G11),"")) | Q11: =IF((G11)>8,SUM(G11-P11),"") | R11: =(IF(H11>0,MIN(8,H11),"")) | S11: =IF((H11)>8,SUM(H11-R11),"") | T11: =(IF(I11>0,MIN(8,I11),"")) | U11: =IF((I11)>8,SUM(I11-T11),"") | V11: =(IF(J11>0,MIN(8,J11),"")) | W11: =IF((J11)>8,SUM(J11-V11),"") | X11: =(IF(K11>0,MIN(8,K11),"")) | Y11: =IF((K11)>8,SUM(K11-X11),"") | Z11: =VLOOKUP(A11,#REF!,5,FALSE) -> #REF! | AA11: =VLOOKUP(A11,#REF!,6,FALSE) -> #REF! | AB11: =IFERROR(VLOOKUP(A11,Table13[[#Headers],[#Data]],7,FALSE),0) -> 0 | AC11: =SUM(Z11:AB11) -> #REF! | AD11: =Z11*C11 -> #REF! | AE11: =AA11*C11*1.5 -> #REF! | AF11: =AB11*C11*2 -> 0 | AG11: =AD11+AE11+AF11 -> #REF!
A12: ASHCRAFT, JOHN | B12: Electrician | C12: =VLOOKUP('6001 1st'!$B12,Table6[],2,FALSE) -> 150 | D12: Y | L12: =(IF(E12>0,MIN(8,E12),"")) | M12: =IF((E12)>8,SUM(E12-L12),"") | N12: =(IF(F12>0,MIN(8,F12),"")) | O12: =IF((F12)>8,SUM(F12-N12),"") | P12: =(IF(G12>0,MIN(8,G12),"")) | Q12: =IF((G12)>8,SUM(G12-P12),"") | R12: =(IF(H12>0,MIN(8,H12),"")) | S12: =IF((H12)>8,SUM(H12-R12),"") | T12: =(IF(I12>0,MIN(8,I12),"")) | U12: =IF((I12)>8,SUM(I12-T12),"") | V12: =(IF(J12>0,MIN(8,J12),"")) | W12: =IF((J12)>8,SUM(J12-V12),"") | X12: =(IF(K12>0,MIN(8,K12),"")) | Y12: =IF((K12)>8,SUM(K12-X12),"") | Z12: =VLOOKUP(A12,#REF!,5,FALSE) -> #REF! | AA12: =VLOOKUP(A12,#REF!,6,FALSE) -> #REF! | AB12: =IFERROR(VLOOKUP(A12,Table13[[#Headers],[#Data]],7,FALSE),0) -> 0 | AC12: =SUM(Z12:AB12) -> #REF! | AD12: =Z12*C12 -> #REF! | AE12: =AA12*C12*1.5 -> #REF! | AF12: =AB12*C12*2 -> 0 | AG12: =AD12+AE12+AF12 -> #REF!
A13: ARROYO, JESUS MACIAS | B13: Electrician | C13: =VLOOKUP('6001 1st'!$B13,Table6[],2,FALSE) -> 150 | L13: =(IF(E13>0,MIN(8,E13),"")) | M13: =IF((E13)>8,SUM(E13-L13),"") | N13: =(IF(F13>0,MIN(8,F13),"")) | O13: =IF((F13)>8,SUM(F13-N13),"") | P13: =(IF(G13>0,MIN(8,G13),"")) | Q13: =IF((G13)>8,SUM(G13-P13),"") | R13: =(IF(H13>0,MIN(8,H13),"")) | S13: =IF((H13)>8,SUM(H13-R13),"") | T13: =(IF(I13>0,MIN(8,I13),"")) | U13: =IF((I13)>8,SUM(I13-T13),"") | V13: =(IF(J13>0,MIN(8,J13),"")) | W13: =IF((J13)>8,SUM(J13-V13),"") | X13: =(IF(K13>0,MIN(8,K13),"")) | Y13: =IF((K13)>8,SUM(K13-X13),"") | Z13: =VLOOKUP(A13,#REF!,5,FALSE) -> #REF! | AA13: =VLOOKUP(A13,#REF!,6,FALSE) -> #REF! | AB13: =IFERROR(VLOOKUP(A13,Table13[[#Headers],[#Data]],7,FALSE),0) -> 0 | AC13: =SUM(Z13:AB13) -> #REF! | AD13: =Z13*C13 -> #REF! | AE13: =AA13*C13*1.5 -> #REF! | AF13: =AB13*C13*2 -> 0 | AG13: =AD13+AE13+AF13 -> #REF!
A14: AVILEZ, IVAN OMAR CASTILLO | B14: Electrician | C14: =VLOOKUP('6001 1st'!$B14,Table6[],2,FALSE) -> 150 | L14: =(IF(E14>0,MIN(8,E14),"")) | M14: =IF((E14)>8,SUM(E14-L14),"") | N14: =(IF(F14>0,MIN(8,F14),"")) | O14: =IF((F14)>8,SUM(F14-N14),"") | P14: =(IF(G14>0,MIN(8,G14),"")) | Q14: =IF((G14)>8,SUM(G14-P14),"") | R14: =(IF(H14>0,MIN(8,H14),"")) | S14: =IF((H14)>8,SUM(H14-R14),"") | T14: =(IF(I14>0,MIN(8,I14),"")) | U14: =IF((I14)>8,SUM(I14-T14),"") | V14: =(IF(J14>0,MIN(8,J14),"")) | W14: =IF((J14)>8,SUM(J14-V14),"") | X14: =(IF(K14>0,MIN(8,K14),"")) | Y14: =IF((K14)>8,SUM(K14-X14),"") | Z14: =VLOOKUP(A14,#REF!,5,FALSE) -> #REF! | AA14: =VLOOKUP(A14,#REF!,6,FALSE) -> #REF! | AB14: =IFERROR(VLOOKUP(A14,Table13[[#Headers],[#Data]],7,FALSE),0) -> 0 | AC14: =SUM(Z14:AB14) -> #REF! | AD14: =Z14*C14 -> #REF! | AE14: =AA14*C14*1.5 -> #REF! | AF14: =AB14*C14*2 -> 0 | AG14: =AD14+AE14+AF14 -> #REF!
A15: BARRIOS, ANDRES | B15: Electrician | C15: =VLOOKUP('6001 1st'!$B15,Table6[],2,FALSE) -> 150 | L15: =(IF(E15>0,MIN(8,E15),"")) | M15: =IF((E15)>8,SUM(E15-L15),"") | N15: =(IF(F15>0,MIN(8,F15),"")) | O15: =IF((F15)>8,SUM(F15-N15),"") | P15: =(IF(G15>0,MIN(8,G15),"")) | Q15: =IF((G15)>8,SUM(G15-P15),"") | R15: =(IF(H15>0,MIN(8,H15),"")) | S15: =IF((H15)>8,SUM(H15-R15),"") | T15: =(IF(I15>0,MIN(8,I15),"")) | U15: =IF((I15)>8,SUM(I15-T15),"") | V15: =(IF(J15>0,MIN(8,J15),"")) | W15: =IF((J15)>8,SUM(J15-V15),"") | X15: =(IF(K15>0,MIN(8,K15),"")) | Y15: =IF((K15)>8,SUM(K15-X15),"") | Z15: =VLOOKUP(A15,#REF!,5,FALSE) -> #REF! | AA15: =VLOOKUP(A15,#REF!,6,FALSE) -> #REF! | AB15: =IFERROR(VLOOKUP(A15,Table13[[#Headers],[#Data]],7,FALSE),0) -> 0 | AC15: =SUM(Z15:AB15) -> #REF! | AD15: =Z15*C15 -> #REF! | AE15: =AA15*C15*1.5 -> #REF! | AF15: =AB15*C15*2 -> 0 | AG15: =AD15+AE15+AF15 -> #REF!
A16: BAUTISTA, MELVIN HERNANDEZ | B16: Electrician | C16: =VLOOKUP('6001 1st'!$B16,Table6[],2,FALSE) -> 150 | L16: =(IF(E16>0,MIN(8,E16),"")) | M16: =IF((E16)>8,SUM(E16-L16),"") | N16: =(IF(F16>0,MIN(8,F16),"")) | O16: =IF((F16)>8,SUM(F16-N16),"") | P16: =(IF(G16>0,MIN(8,G16),"")) | Q16: =IF((G16)>8,SUM(G16-P16),"") | R16: =(IF(H16>0,MIN(8,H16),"")) | S16: =IF((H16)>8,SUM(H16-R16),"") | T16: =(IF(I16>0,MIN(8,I16),"")) | U16: =IF((I16)>8,SUM(I16-T16),"") | V16: =(IF(J16>0,MIN(8,J16),"")) | W16: =IF((J16)>8,SUM(J16-V16),"") | X16: =(IF(K16>0,MIN(8,K16),"")) | Y16: =IF((K16)>8,SUM(K16-X16),"") | Z16: =VLOOKUP(A16,#REF!,5,FALSE) -> #REF! | AA16: =VLOOKUP(A16,#REF!,6,FALSE) -> #REF! | AB16: =IFERROR(VLOOKUP(A16,Table13[[#Headers],[#Data]],7,FALSE),0) -> 0 | AC16: =SUM(Z16:AB16) -> #REF! | AD16: =Z16*C16 -> #REF! | AE16: =AA16*C16*1.5 -> #REF! | AF16: =AB16*C16*2 -> 0 | AG16: =AD16+AE16+AF16 -> #REF!
A17: BLANDON, ELVIN MORENO | B17: Electrician | C17: =VLOOKUP('6001 1st'!$B17,Table6[],2,FALSE) -> 150 | Z17: =VLOOKUP(A17,#REF!,5,FALSE) -> #REF! | AA17: =VLOOKUP(A17,#REF!,6,FALSE) -> #REF! | AB17: =IFERROR(VLOOKUP(A17,Table13[[#Headers],[#Data]],7,FALSE),0) -> 0 | AC17: =SUM(Z17:AB17) -> #REF! | AD17: =Z17*C17 -> #REF! | AE17: =AA17*C17*1.5 -> #REF! | AF17: =AB17*C17*2 -> 0 | AG17: =AD17+AE17+AF17 -> #REF!
A18: BLANDON, OSCAR DANILO MORENO | B18: Electrician | C18: =VLOOKUP('6001 1st'!$B18,Table6[],2,FALSE) -> 150 | Z18: =VLOOKUP(A18,#REF!,5,FALSE) -> #REF! | AA18: =VLOOKUP(A18,#REF!,6,FALSE) -> #REF! | AB18: =IFERROR(VLOOKUP(A18,Table13[[#Headers],[#Data]],7,FALSE),0) -> 0 | AC18: =SUM(Z18:AB18) -> #REF! | AD18: =Z18*C18 -> #REF! | AE18: =AA18*C18*1.5 -> #REF! | AF18: =AB18*C18*2 -> 0 | AG18: =AD18+AE18+AF18 -> #REF!
A19: BOHORQUEZ, AUDIE CHOURIO | B19: Electrician | C19: =VLOOKUP('6001 1st'!$B19,Table6[],2,FALSE) -> 150 | L19: =(IF(E19>0,MIN(8,E19),"")) | M19: =IF((E19)>8,SUM(E19-L19),"") | N19: =(IF(F19>0,MIN(8,F19),"")) | O19: =IF((F19)>8,SUM(F19-N19),"") | P19: =(IF(G19>0,MIN(8,G19),"")) | Q19: =IF((G19)>8,SUM(G19-P19),"") | R19: =(IF(H19>0,MIN(8,H19),"")) | S19: =IF((H19)>8,SUM(H19-R19),"") | T19: =(IF(I19>0,MIN(8,I19),"")) | U19: =IF((I19)>8,SUM(I19-T19),"") | V19: =(IF(J19>0,MIN(8,J19),"")) | W19: =IF((J19)>8,SUM(J19-V19),"") | X19: =(IF(K19>0,MIN(8,K19),"")) | Y19: =IF((K19)>8,SUM(K19-X19),"") | Z19: =VLOOKUP(A19,#REF!,5,FALSE) -> #REF! | AA19: =VLOOKUP(A19,#REF!,6,FALSE) -> #REF! | AB19: =IFERROR(VLOOKUP(A19,Table13[[#Headers],[#Data]],7,FALSE),0) -> 0 | AC19: =SUM(Z19:AB19) -> #REF! | AD19: =Z19*C19 -> #REF! | AE19: =AA19*C19*1.5 -> #REF! | AF19: =AB19*C19*2 -> 0 | AG19: =AD19+AE19+AF19 -> #REF!
A20: BRAVO, JOSE BRICERNO | B20: Electrician | C20: =VLOOKUP('6001 1st'!$B20,Table6[],2,FALSE) -> 150 | L20: =(IF(E20>0,MIN(8,E20),"")) | M20: =IF((E20)>8,SUM(E20-L20),"") | N20: =(IF(F20>0,MIN(8,F20),"")) | O20: =IF((F20)>8,SUM(F20-N20),"") | P20: =(IF(G20>0,MIN(8,G20),"")) | Q20: =IF((G20)>8,SUM(G20-P20),"") | R20: =(IF(H20>0,MIN(8,H20),"")) | S20: =IF((H20)>8,SUM(H20-R20),"") | T20: =(IF(I20>0,MIN(8,I20),"")) | U20: =IF((I20)>8,SUM(I20-T20),"") | V20: =(IF(J20>0,MIN(8,J20),"")) | W20: =IF((J20)>8,SUM(J20-V20),"") | X20: =(IF(K20>0,MIN(8,K20),"")) | Y20: =IF((K20)>8,SUM(K20-X20),"") | Z20: =VLOOKUP(A20,#REF!,5,FALSE) -> #REF! | AA20: =VLOOKUP(A20,#REF!,6,FALSE) -> #REF! | AB20: =IFERROR(VLOOKUP(A20,Table13[[#Headers],[#Data]],7,FALSE),0) -> 0 | AC20: =SUM(Z20:AB20) -> #REF! | AD20: =Z20*C20 -> #REF! | AE20: =AA20*C20*1.5 -> #REF! | AF20: =AB20*C20*2 -> 0 | AG20: =AD20+AE20+AF20 -> #REF!
A21: BUITRON, ROBERTO | B21: Electrician | C21: =VLOOKUP('6001 1st'!$B21,Table6[],2,FALSE) -> 150 | L21: =(IF(E21>0,MIN(8,E21),"")) | M21: =IF((E21)>8,SUM(E21-L21),"") | N21: =(IF(F21>0,MIN(8,F21),"")) | O21: =IF((F21)>8,SUM(F21-N21),"") | P21: =(IF(G21>0,MIN(8,G21),"")) | Q21: =IF((G21)>8,SUM(G21-P21),"") | R21: =(IF(H21>0,MIN(8,H21),"")) | S21: =IF((H21)>8,SUM(H21-R21),"") | T21: =(IF(I21>0,MIN(8,I21),"")) | U21: =IF((I21)>8,SUM(I21-T21),"") | V21: =(IF(J21>0,MIN(8,J21),"")) | W21: =IF((J21)>8,SUM(J21-V21),"") | X21: =(IF(K21>0,MIN(8,K21),"")) | Y21: =IF((K21)>8,SUM(K21-X21),"") | Z21: =VLOOKUP(A21,#REF!,5,FALSE) -> #REF! | AA21: =VLOOKUP(A21,#REF!,6,FALSE) -> #REF! | AB21: =IFERROR(VLOOKUP(A21,Table13[[#Headers],[#Data]],7,FALSE),0) -> 0 | AC21: =SUM(Z21:AB21) -> #REF! | AD21: =Z21*C21 -> #REF! | AE21: =AA21*C21*1.5 -> #REF! | AF21: =AB21*C21*2 -> 0 | AG21: =AD21+AE21+AF21 -> #REF!
A22: CAMPOS, JONATHAN RAMOS | B22: Electrician | C22: =VLOOKUP('6001 1st'!$B22,Table6[],2,FALSE) -> 150 | D22: Y | L22: =(IF(E22>0,MIN(8,E22),"")) | M22: =IF((E22)>8,SUM(E22-L22),"") | N22: =(IF(F22>0,MIN(8,F22),"")) | O22: =IF((F22)>8,SUM(F22-N22),"") | P22: =(IF(G22>0,MIN(8,G22),"")) | Q22: =IF((G22)>8,SUM(G22-P22),"") | R22: =(IF(H22>0,MIN(8,H22),"")) | S22: =IF((H22)>8,SUM(H22-R22),"") | T22: =(IF(I22>0,MIN(8,I22),"")) | U22: =IF((I22)>8,SUM(I22-T22),"") | V22: =(IF(J22>0,MIN(8,J22),"")) | W22: =IF((J22)>8,SUM(J22-V22),"") | X22: =(IF(K22>0,MIN(8,K22),"")) | Y22: =IF((K22)>8,SUM(K22-X22),"") | Z22: =VLOOKUP(A22,#REF!,5,FALSE) -> #REF! | AA22: =VLOOKUP(A22,#REF!,6,FALSE) -> #REF! | AB22: =IFERROR(VLOOKUP(A22,Table13[[#Headers],[#Data]],7,FALSE),0) -> 0 | AC22: =SUM(Z22:AB22) -> #REF! | AD22: =Z22*C22 -> #REF! | AE22: =AA22*C22*1.5 -> #REF! | AF22: =AB22*C22*2 -> 0 | AG22: =AD22+AE22+AF22 -> #REF!
A23: CARBALLO, DAVID | B23: Electrician | C23: =VLOOKUP('6001 1st'!$B23,Table6[],2,FALSE) -> 150 | L23: =(IF(E23>0,MIN(8,E23),"")) | M23: =IF((E23)>8,SUM(E23-L23),"") | N23: =(IF(F23>0,MIN(8,F23),"")) | O23: =IF((F23)>8,SUM(F23-N23),"") | P23: =(IF(G23>0,MIN(8,G23),"")) | Q23: =IF((G23)>8,SUM(G23-P23),"") | R23: =(IF(H23>0,MIN(8,H23),"")) | S23: =IF((H23)>8,SUM(H23-R23),"") | T23: =(IF(I23>0,MIN(8,I23),"")) | U23: =IF((I23)>8,SUM(I23-T23),"") | V23: =(IF(J23>0,MIN(8,J23),"")) | W23: =IF((J23)>8,SUM(J23-V23),"") | X23: =(IF(K23>0,MIN(8,K23),"")) | Y23: =IF((K23)>8,SUM(K23-X23),"") | Z23: =VLOOKUP(A23,#REF!,5,FALSE) -> #REF! | AA23: =VLOOKUP(A23,#REF!,6,FALSE) -> #REF! | AB23: =IFERROR(VLOOKUP(A23,Table13[[#Headers],[#Data]],7,FALSE),0) -> 0 | AC23: =SUM(Z23:AB23) -> #REF! | AD23: =Z23*C23 -> #REF! | AE23: =AA23*C23*1.5 -> #REF! | AF23: =AB23*C23*2 -> 0 | AG23: =AD23+AE23+AF23 -> #REF!
A24: CASANOVA, HUMBERTO FUENMAYOR | B24: Electrician | C24: =VLOOKUP('6001 1st'!$B24,Table6[],2,FALSE) -> 150 | L24: =(IF(E24>0,MIN(8,E24),"")) | M24: =IF((E24)>8,SUM(E24-L24),"") | N24: =(IF(F24>0,MIN(8,F24),"")) | O24: =IF((F24)>8,SUM(F24-N24),"") | P24: =(IF(G24>0,MIN(8,G24),"")) | Q24: =IF((G24)>8,SUM(G24-P24),"") | R24: =(IF(H24>0,MIN(8,H24),"")) | S24: =IF((H24)>8,SUM(H24-R24),"") | T24: =(IF(I24>0,MIN(8,I24),"")) | U24: =IF((I24)>8,SUM(I24-T24),"") | V24: =(IF(J24>0,MIN(8,J24),"")) | W24: =IF((J24)>8,SUM(J24-V24),"") | X24: =(IF(K24>0,MIN(8,K24),"")) | Y24: =IF((K24)>8,SUM(K24-X24),"") | Z24: =VLOOKUP(A24,#REF!,5,FALSE) -> #REF! | AA24: =VLOOKUP(A24,#REF!,6,FALSE) -> #REF! | AB24: =IFERROR(VLOOKUP(A24,Table13[[#Headers],[#Data]],7,FALSE),0) -> 0 | AC24: =SUM(Z24:AB24) -> #REF! | AD24: =Z24*C24 -> #REF! | AE24: =AA24*C24*1.5 -> #REF! | AF24: =AB24*C24*2 -> 0 | AG24: =AD24+AE24+AF24 -> #REF!
A25: CASTILLO, DERBYS URDANETA | B25: Electrician | C25: =VLOOKUP('6001 1st'!$B25,Table6[],2,FALSE) -> 150 | L25: =(IF(E25>0,MIN(8,E25),"")) | M25: =IF((E25)>8,SUM(E25-L25),"") | N25: =(IF(F25>0,MIN(8,F25),"")) | O25: =IF((F25)>8,SUM(F25-N25),"") | P25: =(IF(G25>0,MIN(8,G25),"")) | Q25: =IF((G25)>8,SUM(G25-P25),"") | R25: =(IF(H25>0,MIN(8,H25),"")) | S25: =IF((H25)>8,SUM(H25-R25),"") | T25: =(IF(I25>0,MIN(8,I25),"")) | U25: =IF((I25)>8,SUM(I25-T25),"") | V25: =(IF(J25>0,MIN(8,J25),"")) | W25: =IF((J25)>8,SUM(J25-V25),"") | X25: =(IF(K25>0,MIN(8,K25),"")) | Y25: =IF((K25)>8,SUM(K25-X25),"") | Z25: =VLOOKUP(A25,#REF!,5,FALSE) -> #REF! | AA25: =VLOOKUP(A25,#REF!,6,FALSE) -> #REF! | AB25: =IFERROR(VLOOKUP(A25,Table13[[#Headers],[#Data]],7,FALSE),0) -> 0 | AC25: =SUM(Z25:AB25) -> #REF! | AD25: =Z25*C25 -> #REF! | AE25: =AA25*C25*1.5 -> #REF! | AF25: =AB25*C25*2 -> 0 | AG25: =AD25+AE25+AF25 -> #REF!
A26: CASTILLO, JUAN SALAZAR DEL | B26: Electrician | C26: =VLOOKUP('6001 1st'!$B26,Table6[],2,FALSE) -> 150 | L26: =(IF(E26>0,MIN(8,E26),"")) | M26: =IF((E26)>8,SUM(E26-L26),"") | N26: =(IF(F26>0,MIN(8,F26),"")) | O26: =IF((F26)>8,SUM(F26-N26),"") | P26: =(IF(G26>0,MIN(8,G26),"")) | Q26: =IF((G26)>8,SUM(G26-P26),"") | R26: =(IF(H26>0,MIN(8,H26),"")) | S26: =IF((H26)>8,SUM(H26-R26),"") | T26: =(IF(I26>0,MIN(8,I26),"")) | U26: =IF((I26)>8,SUM(I26-T26),"") | V26: =(IF(J26>0,MIN(8,J26),"")) | W26: =IF((J26)>8,SUM(J26-V26),"") | X26: =(IF(K26>0,MIN(8,K26),"")) | Y26: =IF((K26)>8,SUM(K26-X26),"") | Z26: =VLOOKUP(A26,#REF!,5,FALSE) -> #REF! | AA26: =VLOOKUP(A26,#REF!,6,FALSE) -> #REF! | AB26: =IFERROR(VLOOKUP(A26,Table13[[#Headers],[#Data]],7,FALSE),0) -> 0 | AC26: =SUM(Z26:AB26) -> #REF! | AD26: =Z26*C26 -> #REF! | AE26: =AA26*C26*1.5 -> #REF! | AF26: =AB26*C26*2 -> 0 | AG26: =AD26+AE26+AF26 -> #REF!
A27: CASTILLO, LUIS YUNES | B27: Electrician | C27: =VLOOKUP('6001 1st'!$B27,Table6[],2,FALSE) -> 150 | L27: =(IF(E27>0,MIN(8,E27),"")) | M27: =IF((E27)>8,SUM(E27-L27),"") | N27: =(IF(F27>0,MIN(8,F27),"")) | O27: =IF((F27)>8,SUM(F27-N27),"") | P27: =(IF(G27>0,MIN(8,G27),"")) | Q27: =IF((G27)>8,SUM(G27-P27),"") | R27: =(IF(H27>0,MIN(8,H27),"")) | S27: =IF((H27)>8,SUM(H27-R27),"") | T27: =(IF(I27>0,MIN(8,I27),"")) | U27: =IF((I27)>8,SUM(I27-T27),"") | V27: =(IF(J27>0,MIN(8,J27),"")) | W27: =IF((J27)>8,SUM(J27-V27),"") | X27: =(IF(K27>0,MIN(8,K27),"")) | Y27: =IF((K27)>8,SUM(K27-X27),"") | Z27: =VLOOKUP(A27,#REF!,5,FALSE) -> #REF! | AA27: =VLOOKUP(A27,#REF!,6,FALSE) -> #REF! | AB27: =IFERROR(VLOOKUP(A27,Table13[[#Headers],[#Data]],7,FALSE),0) -> 0 | AC27: =SUM(Z27:AB27) -> #REF! | AD27: =Z27*C27 -> #REF! | AE27: =AA27*C27*1.5 -> #REF! | AF27: =AB27*C27*2 -> 0 | AG27: =AD27+AE27+AF27 -> #REF!
A28: CASTRILLON, DERWIN ZABALA | B28: Electrician | C28: =VLOOKUP('6001 1st'!$B28,Table6[],2,FALSE) -> 150 | L28: =(IF(E28>0,MIN(8,E28),"")) | M28: =IF((E28)>8,SUM(E28-L28),"") | N28: =(IF(F28>0,MIN(8,F28),"")) | O28: =IF((F28)>8,SUM(F28-N28),"") | P28: =(IF(G28>0,MIN(8,G28),"")) | Q28: =IF((G28)>8,SUM(G28-P28),"") | R28: =(IF(H28>0,MIN(8,H28),"")) | S28: =IF((H28)>8,SUM(H28-R28),"") | T28: =(IF(I28>0,MIN(8,I28),"")) | U28: =IF((I28)>8,SUM(I28-T28),"") | V28: =(IF(J28>0,MIN(8,J28),"")) | W28: =IF((J28)>8,SUM(J28-V28),"") | X28: =(IF(K28>0,MIN(8,K28),"")) | Y28: =IF((K28)>8,SUM(K28-X28),"") | Z28: =VLOOKUP(A28,#REF!,5,FALSE) -> #REF! | AA28: =VLOOKUP(A28,#REF!,6,FALSE) -> #REF! | AB28: =IFERROR(VLOOKUP(A28,Table13[[#Headers],[#Data]],7,FALSE),0) -> 0 | AC28: =SUM(Z28:AB28) -> #REF! | AD28: =Z28*C28 -> #REF! | AE28: =AA28*C28*1.5 -> #REF! | AF28: =AB28*C28*2 -> 0 | AG28: =AD28+AE28+AF28 -> #REF!
A29: CASTRO, DANIEL | B29: Electrician | C29: =VLOOKUP('6001 1st'!$B29,Table6[],2,FALSE) -> 150 | L29: =(IF(E29>0,MIN(8,E29),"")) | M29: =IF((E29)>8,SUM(E29-L29),"") | N29: =(IF(F29>0,MIN(8,F29),"")) | O29: =IF((F29)>8,SUM(F29-N29),"") | P29: =(IF(G29>0,MIN(8,G29),"")) | Q29: =IF((G29)>8,SUM(G29-P29),"") | R29: =(IF(H29>0,MIN(8,H29),"")) | S29: =IF((H29)>8,SUM(H29-R29),"") | T29: =(IF(I29>0,MIN(8,I29),"")) | U29: =IF((I29)>8,SUM(I29-T29),"") | V29: =(IF(J29>0,MIN(8,J29),"")) | W29: =IF((J29)>8,SUM(J29-V29),"") | X29: =(IF(K29>0,MIN(8,K29),"")) | Y29: =IF((K29)>8,SUM(K29-X29),"") | Z29: =VLOOKUP(A29,#REF!,5,FALSE) -> #REF! | AA29: =VLOOKUP(A29,#REF!,6,FALSE) -> #REF! | AB29: =IFERROR(VLOOKUP(A29,Table13[[#Headers],[#Data]],7,FALSE),0) -> 0 | AC29: =SUM(Z29:AB29) -> #REF! | AD29: =Z29*C29 -> #REF! | AE29: =AA29*C29*1.5 -> #REF! | AF29: =AB29*C29*2 -> 0 | AG29: =AD29+AE29+AF29 -> #REF!
A30: CHASE, SHANE | B30: Electrician | C30: =VLOOKUP('6001 1st'!$B30,Table6[],2,FALSE) -> 150 | L30: =(IF(E30>0,MIN(8,E30),"")) | M30: =IF((E30)>8,SUM(E30-L30),"") | N30: =(IF(F30>0,MIN(8,F30),"")) | O30: =IF((F30)>8,SUM(F30-N30),"") | P30: =(IF(G30>0,MIN(8,G30),"")) | Q30: =IF((G30)>8,SUM(G30-P30),"") | R30: =(IF(H30>0,MIN(8,H30),"")) | S30: =IF((H30)>8,SUM(H30-R30),"") | T30: =(IF(I30>0,MIN(8,I30),"")) | U30: =IF((I30)>8,SUM(I30-T30),"") | V30: =(IF(J30>0,MIN(8,J30),"")) | W30: =IF((J30)>8,SUM(J30-V30),"") | X30: =(IF(K30>0,MIN(8,K30),"")) | Y30: =IF((K30)>8,SUM(K30-X30),"") | Z30: =VLOOKUP(A30,#REF!,5,FALSE) -> #REF! | AA30: =VLOOKUP(A30,#REF!,6,FALSE) -> #REF! | AB30: =IFERROR(VLOOKUP(A30,Table13[[#Headers],[#Data]],7,FALSE),0) -> 0 | AC30: =SUM(Z30:AB30) -> #REF! | AD30: =Z30*C30 -> #REF! | AE30: =AA30*C30*1.5 -> #REF! | AF30: =AB30*C30*2 -> 0 | AG30: =AD30+AE30+AF30 -> #REF!
A31: CHAVARRIA, GLORIA CRISTINA TORREZ | B31: Electrician | C31: =VLOOKUP('6001 1st'!$B31,Table6[],2,FALSE) -> 150 | L31: =(IF(E31>0,MIN(8,E31),"")) | M31: =IF((E31)>8,SUM(E31-L31),"") | N31: =(IF(F31>0,MIN(8,F31),"")) | O31: =IF((F31)>8,SUM(F31-N31),"") | P31: =(IF(G31>0,MIN(8,G31),"")) | Q31: =IF((G31)>8,SUM(G31-P31),"") | R31: =(IF(H31>0,MIN(8,H31),"")) | S31: =IF((H31)>8,SUM(H31-R31),"") | T31: =(IF(I31>0,MIN(8,I31),"")) | U31: =IF((I31)>8,SUM(I31-T31),"") | V31: =(IF(J31>0,MIN(8,J31),"")) | W31: =IF((J31)>8,SUM(J31-V31),"") | X31: =(IF(K31>0,MIN(8,K31),"")) | Y31: =IF((K31)>8,SUM(K31-X31),"") | Z31: =VLOOKUP(A31,#REF!,5,FALSE) -> #REF! | AA31: =VLOOKUP(A31,#REF!,6,FALSE) -> #REF! | AB31: =IFERROR(VLOOKUP(A31,Table13[[#Headers],[#Data]],7,FALSE),0) -> 0 | AC31: =SUM(Z31:AB31) -> #REF! | AD31: =Z31*C31 -> #REF! | AE31: =AA31*C31*1.5 -> #REF! | AF31: =AB31*C31*2 -> 0 | AG31: =AD31+AE31+AF31 -> #REF!
A32: CHAVEZ ABELARDO, JANDIEL | B32: Electrician | C32: =VLOOKUP('6001 1st'!$B32,Table6[],2,FALSE) -> 150 | L32: =(IF(E32>0,MIN(8,E32),"")) | M32: =IF((E32)>8,SUM(E32-L32),"") | N32: =(IF(F32>0,MIN(8,F32),"")) | O32: =IF((F32)>8,SUM(F32-N32),"") | P32: =(IF(G32>0,MIN(8,G32),"")) | Q32: =IF((G32)>8,SUM(G32-P32),"") | R32: =(IF(H32>0,MIN(8,H32),"")) | S32: =IF((H32)>8,SUM(H32-R32),"") | T32: =(IF(I32>0,MIN(8,I32),"")) | U32: =IF((I32)>8,SUM(I32-T32),"") | V32: =(IF(J32>0,MIN(8,J32),"")) | W32: =IF((J32)>8,SUM(J32-V32),"") | X32: =(IF(K32>0,MIN(8,K32),"")) | Y32: =IF((K32)>8,SUM(K32-X32),"") | Z32: =VLOOKUP(A32,#REF!,5,FALSE) -> #REF! | AA32: =VLOOKUP(A32,#REF!,6,FALSE) -> #REF! | AB32: =IFERROR(VLOOKUP(A32,Table13[[#Headers],[#Data]],7,FALSE),0) -> 0 | AC32: =SUM(Z32:AB32) -> #REF! | AD32: =Z32*C32 -> #REF! | AE32: =AA32*C32*1.5 -> #REF! | AF32: =AB32*C32*2 -> 0 | AG32: =AD32+AE32+AF32 -> #REF!
A33: CHIRINOS, DANNY | B33: Electrician | C33: =VLOOKUP('6001 1st'!$B33,Table6[],2,FALSE) -> 150 | L33: =(IF(E33>0,MIN(8,E33),"")) | M33: =IF((E33)>8,SUM(E33-L33),"") | N33: =(IF(F33>0,MIN(8,F33),"")) | O33: =IF((F33)>8,SUM(F33-N33),"") | P33: =(IF(G33>0,MIN(8,G33),"")) | Q33: =IF((G33)>8,SUM(G33-P33),"") | R33: =(IF(H33>0,MIN(8,H33),"")) | S33: =IF((H33)>8,SUM(H33-R33),"") | T33: =(IF(I33>0,MIN(8,I33),"")) | U33: =IF((I33)>8,SUM(I33-T33),"") | V33: =(IF(J33>0,MIN(8,J33),"")) | W33: =IF((J33)>8,SUM(J33-V33),"") | X33: =(IF(K33>0,MIN(8,K33),"")) | Y33: =IF((K33)>8,SUM(K33-X33),"") | Z33: =VLOOKUP(A33,#REF!,5,FALSE) -> #REF! | AA33: =VLOOKUP(A33,#REF!,6,FALSE) -> #REF! | AB33: =IFERROR(VLOOKUP(A33,Table13[[#Headers],[#Data]],7,FALSE),0) -> 0 | AC33: =SUM(Z33:AB33) -> #REF! | AD33: =Z33*C33 -> #REF! | AE33: =AA33*C33*1.5 -> #REF! | AF33: =AB33*C33*2 -> 0 | AG33: =AD33+AE33+AF33 -> #REF!
A34: CHOC, ALEJANDRO | B34: Electrician | C34: =VLOOKUP('6001 1st'!$B34,Table6[],2,FALSE) -> 150 | L34: =(IF(E34>0,MIN(8,E34),"")) | M34: =IF((E34)>8,SUM(E34-L34),"") | N34: =(IF(F34>0,MIN(8,F34),"")) | O34: =IF((F34)>8,SUM(F34-N34),"") | P34: =(IF(G34>0,MIN(8,G34),"")) | Q34: =IF((G34)>8,SUM(G34-P34),"") | R34: =(IF(H34>0,MIN(8,H34),"")) | S34: =IF((H34)>8,SUM(H34-R34),"") | T34: =(IF(I34>0,MIN(8,I34),"")) | U34: =IF((I34)>8,SUM(I34-T34),"") | V34: =(IF(J34>0,MIN(8,J34),"")) | W34: =IF((J34)>8,SUM(J34-V34),"") | X34: =(IF(K34>0,MIN(8,K34),"")) | Y34: =IF((K34)>8,SUM(K34-X34),"") | Z34: =VLOOKUP(A34,#REF!,5,FALSE) -> #REF! | AA34: =VLOOKUP(A34,#REF!,6,FALSE) -> #REF! | AB34: =IFERROR(VLOOKUP(A34,Table13[[#Headers],[#Data]],7,FALSE),0) -> 0 | AC34: =SUM(Z34:AB34) -> #REF! | AD34: =Z34*C34 -> #REF! | AE34: =AA34*C34*1.5 -> #REF! | AF34: =AB34*C34*2 -> 0 | AG34: =AD34+AE34+AF34 -> #REF!
A35: COLMENAREZ, JONATHAN | B35: Electrician | C35: =VLOOKUP('6001 1st'!$B35,Table6[],2,FALSE) -> 150 | Z35: =VLOOKUP(A35,#REF!,5,FALSE) -> #REF! | AA35: =VLOOKUP(A35,#REF!,6,FALSE) -> #REF! | AB35: =IFERROR(VLOOKUP(A35,Table13[[#Headers],[#Data]],7,FALSE),0) -> 0 | AC35: =SUM(Z35:AB35) -> #REF! | AD35: =Z35*C35 -> #REF! | AE35: =AA35*C35*1.5 -> #REF! | AF35: =AB35*C35*2 -> 0 | AG35: =AD35+AE35+AF35 -> #REF!
A36: CONCHA, RUBEN | B36: Electrician | C36: =VLOOKUP('6001 1st'!$B36,Table6[],2,FALSE) -> 150 | Z36: =VLOOKUP(A36,#REF!,5,FALSE) -> #REF! | AA36: =VLOOKUP(A36,#REF!,6,FALSE) -> #REF! | AB36: =IFERROR(VLOOKUP(A36,Table13[[#Headers],[#Data]],7,FALSE),0) -> 0 | AC36: =SUM(Z36:AB36) -> #REF! | AD36: =Z36*C36 -> #REF! | AE36: =AA36*C36*1.5 -> #REF! | AF36: =AB36*C36*2 -> 0 | AG36: =AD36+AE36+AF36 -> #REF!
A37: CONSTAZA, NELSON G | B37: Electrician | C37: =VLOOKUP('6001 1st'!$B37,Table6[],2,FALSE) -> 150 | L37: =(IF(E37>0,MIN(8,E37),"")) | M37: =IF((E37)>8,SUM(E37-L37),"") | N37: =(IF(F37>0,MIN(8,F37),"")) | O37: =IF((F37)>8,SUM(F37-N37),"") | P37: =(IF(G37>0,MIN(8,G37),"")) | Q37: =IF((G37)>8,SUM(G37-P37),"") | R37: =(IF(H37>0,MIN(8,H37),"")) | S37: =IF((H37)>8,SUM(H37-R37),"") | T37: =(IF(I37>0,MIN(8,I37),"")) | U37: =IF((I37)>8,SUM(I37-T37),"") | V37: =(IF(J37>0,MIN(8,J37),"")) | W37: =IF((J37)>8,SUM(J37-V37),"") | X37: =(IF(K37>0,MIN(8,K37),"")) | Y37: =IF((K37)>8,SUM(K37-X37),"") | Z37: =VLOOKUP(A37,#REF!,5,FALSE) -> #REF! | AA37: =VLOOKUP(A37,#REF!,6,FALSE) -> #REF! | AB37: =IFERROR(VLOOKUP(A37,Table13[[#Headers],[#Data]],7,FALSE),0) -> 0 | AC37: =SUM(Z37:AB37) -> #REF! | AD37: =Z37*C37 -> #REF! | AE37: =AA37*C37*1.5 -> #REF! | AF37: =AB37*C37*2 -> 0 | AG37: =AD37+AE37+AF37 -> #REF!
A38: CORREO, RUBEN PEREIRA | B38: Electrician | C38: =VLOOKUP('6001 1st'!$B38,Table6[],2,FALSE) -> 150 | L38: =(IF(E38>0,MIN(8,E38),"")) | M38: =IF((E38)>8,SUM(E38-L38),"") | N38: =(IF(F38>0,MIN(8,F38),"")) | O38: =IF((F38)>8,SUM(F38-N38),"") | P38: =(IF(G38>0,MIN(8,G38),"")) | Q38: =IF((G38)>8,SUM(G38-P38),"") | R38: =(IF(H38>0,MIN(8,H38),"")) | S38: =IF((H38)>8,SUM(H38-R38),"") | T38: =(IF(I38>0,MIN(8,I38),"")) | U38: =IF((I38)>8,SUM(I38-T38),"") | V38: =(IF(J38>0,MIN(8,J38),"")) | W38: =IF((J38)>8,SUM(J38-V38),"") | X38: =(IF(K38>0,MIN(8,K38),"")) | Y38: =IF((K38)>8,SUM(K38-X38),"") | Z38: =VLOOKUP(A38,#REF!,5,FALSE) -> #REF! | AA38: =VLOOKUP(A38,#REF!,6,FALSE) -> #REF! | AB38: =IFERROR(VLOOKUP(A38,Table13[[#Headers],[#Data]],7,FALSE),0) -> 0 | AC38: =SUM(Z38:AB38) -> #REF! | AD38: =Z38*C38 -> #REF! | AE38: =AA38*C38*1.5 -> #REF! | AF38: =AB38*C38*2 -> 0 | AG38: =AD38+AE38+AF38 -> #REF!
A39: CRUZ, ADOLFO MANUEL ROSAS | B39: Electrician | C39: =VLOOKUP('6001 1st'!$B39,Table6[],2,FALSE) -> 150 | Z39: =VLOOKUP(A39,#REF!,5,FALSE) -> #REF! | AA39: =VLOOKUP(A39,#REF!,6,FALSE) -> #REF! | AB39: =IFERROR(VLOOKUP(A39,Table13[[#Headers],[#Data]],7,FALSE),0) -> 0 | AC39: =SUM(Z39:AB39) -> #REF! | AD39: =Z39*C39 -> #REF! | AE39: =AA39*C39*1.5 -> #REF! | AF39: =AB39*C39*2 -> 0 | AG39: =AD39+AE39+AF39 -> #REF!
A40: DAGURROLA, DARWIN REYES | B40: Electrician | C40: =VLOOKUP('6001 1st'!$B40,Table6[],2,FALSE) -> 150 | L40: =(IF(E40>0,MIN(8,E40),"")) | M40: =IF((E40)>8,SUM(E40-L40),"") | N40: =(IF(F40>0,MIN(8,F40),"")) | O40: =IF((F40)>8,SUM(F40-N40),"") | P40: =(IF(G40>0,MIN(8,G40),"")) | Q40: =IF((G40)>8,SUM(G40-P40),"") | R40: =(IF(H40>0,MIN(8,H40),"")) | S40: =IF((H40)>8,SUM(H40-R40),"") | T40: =(IF(I40>0,MIN(8,I40),"")) | U40: =IF((I40)>8,SUM(I40-T40),"") | V40: =(IF(J40>0,MIN(8,J40),"")) | W40: =IF((J40)>8,SUM(J40-V40),"") | X40: =(IF(K40>0,MIN(8,K40),"")) | Y40: =IF((K40)>8,SUM(K40-X40),"") | Z40: =VLOOKUP(A40,#REF!,5,FALSE) -> #REF! | AA40: =VLOOKUP(A40,#REF!,6,FALSE) -> #REF! | AB40: =IFERROR(VLOOKUP(A40,Table13[[#Headers],[#Data]],7,FALSE),0) -> 0 | AC40: =SUM(Z40:AB40) -> #REF! | AD40: =Z40*C40 -> #REF! | AE40: =AA40*C40*1.5 -> #REF! | AF40: =AB40*C40*2 -> 0 | AG40: =AD40+AE40+AF40 -> #REF!
A41: DEJAC, TYLER | B41: Electrician | C41: =VLOOKUP('6001 1st'!$B41,Table6[],2,FALSE) -> 150 | L41: =(IF(E41>0,MIN(8,E41),"")) | M41: =IF((E41)>8,SUM(E41-L41),"") | N41: =(IF(F41>0,MIN(8,F41),"")) | O41: =IF((F41)>8,SUM(F41-N41),"") | P41: =(IF(G41>0,MIN(8,G41),"")) | Q41: =IF((G41)>8,SUM(G41-P41),"") | R41: =(IF(H41>0,MIN(8,H41),"")) | S41: =IF((H41)>8,SUM(H41-R41),"") | T41: =(IF(I41>0,MIN(8,I41),"")) | U41: =IF((I41)>8,SUM(I41-T41),"") | V41: =(IF(J41>0,MIN(8,J41),"")) | W41: =IF((J41)>8,SUM(J41-V41),"") | X41: =(IF(K41>0,MIN(8,K41),"")) | Y41: =IF((K41)>8,SUM(K41-X41),"") | Z41: =VLOOKUP(A41,#REF!,5,FALSE) -> #REF! | AA41: =VLOOKUP(A41,#REF!,6,FALSE) -> #REF! | AB41: =IFERROR(VLOOKUP(A41,Table13[[#Headers],[#Data]],7,FALSE),0) -> 0 | AC41: =SUM(Z41:AB41) -> #REF! | AD41: =Z41*C41 -> #REF! | AE41: =AA41*C41*1.5 -> #REF! | AF41: =AB41*C41*2 -> 0 | AG41: =AD41+AE41+AF41 -> #REF!
A42: DIAZ, JOANNA | B42: Electrician | C42: =VLOOKUP('6001 1st'!$B42,Table6[],2,FALSE) -> 150 | L42: =(IF(E42>0,MIN(8,E42),"")) | M42: =IF((E42)>8,SUM(E42-L42),"") | N42: =(IF(F42>0,MIN(8,F42),"")) | O42: =IF((F42)>8,SUM(F42-N42),"") | P42: =(IF(G42>0,MIN(8,G42),"")) | Q42: =IF((G42)>8,SUM(G42-P42),"") | R42: =(IF(H42>0,MIN(8,H42),"")) | S42: =IF((H42)>8,SUM(H42-R42),"") | T42: =(IF(I42>0,MIN(8,I42),"")) | U42: =IF((I42)>8,SUM(I42-T42),"") | V42: =(IF(J42>0,MIN(8,J42),"")) | W42: =IF((J42)>8,SUM(J42-V42),"") | X42: =(IF(K42>0,MIN(8,K42),"")) | Y42: =IF((K42)>8,SUM(K42-X42),"") | Z42: =VLOOKUP(A42,#REF!,5,FALSE) -> #REF! | AA42: =VLOOKUP(A42,#REF!,6,FALSE) -> #REF! | AB42: =IFERROR(VLOOKUP(A42,Table13[[#Headers],[#Data]],7,FALSE),0) -> 0 | AC42: =SUM(Z42:AB42) -> #REF! | AD42: =Z42*C42 -> #REF! | AE42: =AA42*C42*1.5 -> #REF! | AF42: =AB42*C42*2 -> 0 | AG42: =AD42+AE42+AF42 -> #REF!
A43: DIOSDADO MIRANDA, SAMUEL | B43: Electrician | C43: =VLOOKUP('6001 1st'!$B43,Table6[],2,FALSE) -> 150 | L43: =(IF(E43>0,MIN(8,E43),"")) | M43: =IF((E43)>8,SUM(E43-L43),"") | N43: =(IF(F43>0,MIN(8,F43),"")) | O43: =IF((F43)>8,SUM(F43-N43),"") | P43: =(IF(G43>0,MIN(8,G43),"")) | Q43: =IF((G43)>8,SUM(G43-P43),"") | R43: =(IF(H43>0,MIN(8,H43),"")) | S43: =IF((H43)>8,SUM(H43-R43),"") | T43: =(IF(I43>0,MIN(8,I43),"")) | U43: =IF((I43)>8,SUM(I43-T43),"") | V43: =(IF(J43>0,MIN(8,J43),"")) | W43: =IF((J43)>8,SUM(J43-V43),"") | X43: =(IF(K43>0,MIN(8,K43),"")) | Y43: =IF((K43)>8,SUM(K43-X43),"") | Z43: =VLOOKUP(A43,#REF!,5,FALSE) -> #REF! | AA43: =VLOOKUP(A43,#REF!,6,FALSE) -> #REF! | AB43: =IFERROR(VLOOKUP(A43,Table13[[#Headers],[#Data]],7,FALSE),0) -> 0 | AC43: =SUM(Z43:AB43) -> #REF! | AD43: =Z43*C43 -> #REF! | AE43: =AA43*C43*1.5 -> #REF! | AF43: =AB43*C43*2 -> 0 | AG43: =AD43+AE43+AF43 -> #REF!
A44: DURAN, OSMAN PERDOMO | B44: Electrician | C44: =VLOOKUP('6001 1st'!$B44,Table6[],2,FALSE) -> 150 | L44: =(IF(E44>0,MIN(8,E44),"")) | M44: =IF((E44)>8,SUM(E44-L44),"") | N44: =(IF(F44>0,MIN(8,F44),"")) | O44: =IF((F44)>8,SUM(F44-N44),"") | P44: =(IF(G44>0,MIN(8,G44),"")) | Q44: =IF((G44)>8,SUM(G44-P44),"") | R44: =(IF(H44>0,MIN(8,H44),"")) | S44: =IF((H44)>8,SUM(H44-R44),"") | T44: =(IF(I44>0,MIN(8,I44),"")) | U44: =IF((I44)>8,SUM(I44-T44),"") | V44: =(IF(J44>0,MIN(8,J44),"")) | W44: =IF((J44)>8,SUM(J44-V44),"") | X44: =(IF(K44>0,MIN(8,K44),"")) | Y44: =IF((K44)>8,SUM(K44-X44),"") | Z44: =VLOOKUP(A44,#REF!,5,FALSE) -> #REF! | AA44: =VLOOKUP(A44,#REF!,6,FALSE) -> #REF! | AB44: =IFERROR(VLOOKUP(A44,Table13[[#Headers],[#Data]],7,FALSE),0) -> 0 | AC44: =SUM(Z44:AB44) -> #REF! | AD44: =Z44*C44 -> #REF! | AE44: =AA44*C44*1.5 -> #REF! | AF44: =AB44*C44*2 -> 0 | AG44: =AD44+AE44+AF44 -> #REF!
A45: ECHEVARRIA, EDWIN GONZALEZ | B45: Electrician | C45: =VLOOKUP('6001 1st'!$B45,Table6[],2,FALSE) -> 150 | L45: =(IF(E45>0,MIN(8,E45),"")) | M45: =IF((E45)>8,SUM(E45-L45),"") | N45: =(IF(F45>0,MIN(8,F45),"")) | O45: =IF((F45)>8,SUM(F45-N45),"") | P45: =(IF(G45>0,MIN(8,G45),"")) | Q45: =IF((G45)>8,SUM(G45-P45),"") | R45: =(IF(H45>0,MIN(8,H45),"")) | S45: =IF((H45)>8,SUM(H45-R45),"") | T45: =(IF(I45>0,MIN(8,I45),"")) | U45: =IF((I45)>8,SUM(I45-T45),"") | V45: =(IF(J45>0,MIN(8,J45),"")) | W45: =IF((J45)>8,SUM(J45-V45),"") | X45: =(IF(K45>0,MIN(8,K45),"")) | Y45: =IF((K45)>8,SUM(K45-X45),"") | Z45: =VLOOKUP(A45,#REF!,5,FALSE) -> #REF! | AA45: =VLOOKUP(A45,#REF!,6,FALSE) -> #REF! | AB45: =IFERROR(VLOOKUP(A45,Table13[[#Headers],[#Data]],7,FALSE),0) -> 0 | AC45: =SUM(Z45:AB45) -> #REF! | AD45: =Z45*C45 -> #REF! | AE45: =AA45*C45*1.5 -> #REF! | AF45: =AB45*C45*2 -> 0 | AG45: =AD45+AE45+AF45 -> #REF!
A46: ERIVES, ROBERTO RAFAEL | B46: Electrician | C46: =VLOOKUP('6001 1st'!$B46,Table6[],2,FALSE) -> 150 | Z46: =VLOOKUP(A46,#REF!,5,FALSE) -> #REF! | AA46: =VLOOKUP(A46,#REF!,6,FALSE) -> #REF! | AB46: =IFERROR(VLOOKUP(A46,Table13[[#Headers],[#Data]],7,FALSE),0) -> 0 | AC46: =SUM(Z46:AB46) -> #REF! | AD46: =Z46*C46 -> #REF! | AE46: =AA46*C46*1.5 -> #REF! | AF46: =AB46*C46*2 -> 0 | AG46: =AD46+AE46+AF46 -> #REF!
A47: ESTUDILLO GONZALES, JONATHAN GIOVANI | B47: Electrician | C47: =VLOOKUP('6001 1st'!$B47,Table6[],2,FALSE) -> 150 | L47: =(IF(E47>0,MIN(8,E47),"")) | M47: =IF((E47)>8,SUM(E47-L47),"") | N47: =(IF(F47>0,MIN(8,F47),"")) | O47: =IF((F47)>8,SUM(F47-N47),"") | P47: =(IF(G47>0,MIN(8,G47),"")) | Q47: =IF((G47)>8,SUM(G47-P47),"") | R47: =(IF(H47>0,MIN(8,H47),"")) | S47: =IF((H47)>8,SUM(H47-R47),"") | T47: =(IF(I47>0,MIN(8,I47),"")) | U47: =IF((I47)>8,SUM(I47-T47),"") | V47: =(IF(J47>0,MIN(8,J47),"")) | W47: =IF((J47)>8,SUM(J47-V47),"") | X47: =(IF(K47>0,MIN(8,K47),"")) | Y47: =IF((K47)>8,SUM(K47-X47),"") | Z47: =VLOOKUP(A47,#REF!,5,FALSE) -> #REF! | AA47: =VLOOKUP(A47,#REF!,6,FALSE) -> #REF! | AB47: =IFERROR(VLOOKUP(A47,Table13[[#Headers],[#Data]],7,FALSE),0) -> 0 | AC47: =SUM(Z47:AB47) -> #REF! | AD47: =Z47*C47 -> #REF! | AE47: =AA47*C47*1.5 -> #REF! | AF47: =AB47*C47*2 -> 0 | AG47: =AD47+AE47+AF47 -> #REF!
A48: ESTUDILLO GONZALES, JOSE IVAN | B48: Electrician | C48: =VLOOKUP('6001 1st'!$B48,Table6[],2,FALSE) -> 150 | L48: =(IF(E48>0,MIN(8,E48),"")) | M48: =IF((E48)>8,SUM(E48-L48),"") | N48: =(IF(F48>0,MIN(8,F48),"")) | O48: =IF((F48)>8,SUM(F48-N48),"") | P48: =(IF(G48>0,MIN(8,G48),"")) | Q48: =IF((G48)>8,SUM(G48-P48),"") | R48: =(IF(H48>0,MIN(8,H48),"")) | S48: =IF((H48)>8,SUM(H48-R48),"") | T48: =(IF(I48>0,MIN(8,I48),"")) | U48: =IF((I48)>8,SUM(I48-T48),"") | V48: =(IF(J48>0,MIN(8,J48),"")) | W48: =IF((J48)>8,SUM(J48-V48),"") | X48: =(IF(K48>0,MIN(8,K48),"")) | Y48: =IF((K48)>8,SUM(K48-X48),"") | Z48: =VLOOKUP(A48,#REF!,5,FALSE) -> #REF! | AA48: =VLOOKUP(A48,#REF!,6,FALSE) -> #REF! | AB48: =IFERROR(VLOOKUP(A48,Table13[[#Headers],[#Data]],7,FALSE),0) -> 0 | AC48: =SUM(Z48:AB48) -> #REF! | AD48: =Z48*C48 -> #REF! | AE48: =AA48*C48*1.5 -> #REF! | AF48: =AB48*C48*2 -> 0 | AG48: =AD48+AE48+AF48 -> #REF!
A49: FERNANDEZ, JOSEP ROJAS | B49: Electrician | C49: =VLOOKUP('6001 1st'!$B49,Table6[],2,FALSE) -> 150 | L49: =(IF(E49>0,MIN(8,E49),"")) | M49: =IF((E49)>8,SUM(E49-L49),"") | N49: =(IF(F49>0,MIN(8,F49),"")) | O49: =IF((F49)>8,SUM(F49-N49),"") | P49: =(IF(G49>0,MIN(8,G49),"")) | Q49: =IF((G49)>8,SUM(G49-P49),"") | R49: =(IF(H49>0,MIN(8,H49),"")) | S49: =IF((H49)>8,SUM(H49-R49),"") | T49: =(IF(I49>0,MIN(8,I49),"")) | U49: =IF((I49)>8,SUM(I49-T49),"") | V49: =(IF(J49>0,MIN(8,J49),"")) | W49: =IF((J49)>8,SUM(J49-V49),"") | X49: =(IF(K49>0,MIN(8,K49),"")) | Y49: =IF((K49)>8,SUM(K49-X49),"") | Z49: =VLOOKUP(A49,#REF!,5,FALSE) -> #REF! | AA49: =VLOOKUP(A49,#REF!,6,FALSE) -> #REF! | AB49: =IFERROR(VLOOKUP(A49,Table13[[#Headers],[#Data]],7,FALSE),0) -> 0 | AC49: =SUM(Z49:AB49) -> #REF! | AD49: =Z49*C49 -> #REF! | AE49: =AA49*C49*1.5 -> #REF! | AF49: =AB49*C49*2 -> 0 | AG49: =AD49+AE49+AF49 -> #REF!
A50: FERNANDEZ, MARIA V ROJAS | B50: Electrician | C50: =VLOOKUP('6001 1st'!$B50,Table6[],2,FALSE) -> 150 | L50: =(IF(E50>0,MIN(8,E50),"")) | M50: =IF((E50)>8,SUM(E50-L50),"") | N50: =(IF(F50>0,MIN(8,F50),"")) | O50: =IF((F50)>8,SUM(F50-N50),"") | P50: =(IF(G50>0,MIN(8,G50),"")) | Q50: =IF((G50)>8,SUM(G50-P50),"") | R50: =(IF(H50>0,MIN(8,H50),"")) | S50: =IF((H50)>8,SUM(H50-R50),"") | T50: =(IF(I50>0,MIN(8,I50),"")) | U50: =IF((I50)>8,SUM(I50-T50),"") | V50: =(IF(J50>0,MIN(8,J50),"")) | W50: =IF((J50)>8,SUM(J50-V50),"") | X50: =(IF(K50>0,MIN(8,K50),"")) | Y50: =IF((K50)>8,SUM(K50-X50),"") | Z50: =VLOOKUP(A50,#REF!,5,FALSE) -> #REF! | AA50: =VLOOKUP(A50,#REF!,6,FALSE) -> #REF! | AB50: =IFERROR(VLOOKUP(A50,Table13[[#Headers],[#Data]],7,FALSE),0) -> 0 | AC50: =SUM(Z50:AB50) -> #REF! | AD50: =Z50*C50 -> #REF! | AE50: =AA50*C50*1.5 -> #REF! | AF50: =AB50*C50*2 -> 0 | AG50: =AD50+AE50+AF50 -> #REF!
A51: FALCON ORDOGOITIA, ARNALDO | B51: Electrician | C51: =VLOOKUP('6001 1st'!$B51,Table6[],2,FALSE) -> 150 | L51: =(IF(E51>0,MIN(8,E51),"")) | M51: =IF((E51)>8,SUM(E51-L51),"") | N51: =(IF(F51>0,MIN(8,F51),"")) | O51: =IF((F51)>8,SUM(F51-N51),"") | P51: =(IF(G51>0,MIN(8,G51),"")) | Q51: =IF((G51)>8,SUM(G51-P51),"") | R51: =(IF(H51>0,MIN(8,H51),"")) | S51: =IF((H51)>8,SUM(H51-R51),"") | T51: =(IF(I51>0,MIN(8,I51),"")) | U51: =IF((I51)>8,SUM(I51-T51),"") | V51: =(IF(J51>0,MIN(8,J51),"")) | W51: =IF((J51)>8,SUM(J51-V51),"") | X51: =(IF(K51>0,MIN(8,K51),"")) | Y51: =IF((K51)>8,SUM(K51-X51),"") | Z51: =VLOOKUP(A51,#REF!,5,FALSE) -> #REF! | AA51: =VLOOKUP(A51,#REF!,6,FALSE) -> #REF! | AB51: =IFERROR(VLOOKUP(A51,Table13[[#Headers],[#Data]],7,FALSE),0) -> 0 | AC51: =SUM(Z51:AB51) -> #REF! | AD51: =Z51*C51 -> #REF! | AE51: =AA51*C51*1.5 -> #REF! | AF51: =AB51*C51*2 -> 0 | AG51: =AD51+AE51+AF51 -> #REF!
A52: FLORES, BRYAN JAVIER RIVERA | B52: Electrician | C52: =VLOOKUP('6001 1st'!$B52,Table6[],2,FALSE) -> 150 | L52: =(IF(E52>0,MIN(8,E52),"")) | M52: =IF((E52)>8,SUM(E52-L52),"") | N52: =(IF(F52>0,MIN(8,F52),"")) | O52: =IF((F52)>8,SUM(F52-N52),"") | P52: =(IF(G52>0,MIN(8,G52),"")) | Q52: =IF((G52)>8,SUM(G52-P52),"") | R52: =(IF(H52>0,MIN(8,H52),"")) | S52: =IF((H52)>8,SUM(H52-R52),"") | T52: =(IF(I52>0,MIN(8,I52),"")) | U52: =IF((I52)>8,SUM(I52-T52),"") | V52: =(IF(J52>0,MIN(8,J52),"")) | W52: =IF((J52)>8,SUM(J52-V52),"") | X52: =(IF(K52>0,MIN(8,K52),"")) | Y52: =IF((K52)>8,SUM(K52-X52),"") | Z52: =VLOOKUP(A52,#REF!,5,FALSE) -> #REF! | AA52: =VLOOKUP(A52,#REF!,6,FALSE) -> #REF! | AB52: =IFERROR(VLOOKUP(A52,Table13[[#Headers],[#Data]],7,FALSE),0) -> 0 | AC52: =SUM(Z52:AB52) -> #REF! | AD52: =Z52*C52 -> #REF! | AE52: =AA52*C52*1.5 -> #REF! | AF52: =AB52*C52*2 -> 0 | AG52: =AD52+AE52+AF52 -> #REF!
A53: FLORES, EDEL | B53: Electrician | C53: =VLOOKUP('6001 1st'!$B53,Table6[],2,FALSE) -> 150 | L53: =(IF(E53>0,MIN(8,E53),"")) | M53: =IF((E53)>8,SUM(E53-L53),"") | N53: =(IF(F53>0,MIN(8,F53),"")) | O53: =IF((F53)>8,SUM(F53-N53),"") | P53: =(IF(G53>0,MIN(8,G53),"")) | Q53: =IF((G53)>8,SUM(G53-P53),"") | R53: =(IF(H53>0,MIN(8,H53),"")) | S53: =IF((H53)>8,SUM(H53-R53),"") | T53: =(IF(I53>0,MIN(8,I53),"")) | U53: =IF((I53)>8,SUM(I53-T53),"") | V53: =(IF(J53>0,MIN(8,J53),"")) | W53: =IF((J53)>8,SUM(J53-V53),"") | X53: =(IF(K53>0,MIN(8,K53),"")) | Y53: =IF((K53)>8,SUM(K53-X53),"") | Z53: =VLOOKUP(A53,#REF!,5,FALSE) -> #REF! | AA53: =VLOOKUP(A53,#REF!,6,FALSE) -> #REF! | AB53: =IFERROR(VLOOKUP(A53,Table13[[#Headers],[#Data]],7,FALSE),0) -> 0 | AC53: =SUM(Z53:AB53) -> #REF! | AD53: =Z53*C53 -> #REF! | AE53: =AA53*C53*1.5 -> #REF! | AF53: =AB53*C53*2 -> 0 | AG53: =AD53+AE53+AF53 -> #REF!
A54: FLORES, RIGOBERTO BEBRAUT | B54: Electrician | C54: =VLOOKUP('6001 1st'!$B54,Table6[],2,FALSE) -> 150 | L54: =(IF(E54>0,MIN(8,E54),"")) | M54: =IF((E54)>8,SUM(E54-L54),"") | N54: =(IF(F54>0,MIN(8,F54),"")) | O54: =IF((F54)>8,SUM(F54-N54),"") | P54: =(IF(G54>0,MIN(8,G54),"")) | Q54: =IF((G54)>8,SUM(G54-P54),"") | R54: =(IF(H54>0,MIN(8,H54),"")) | S54: =IF((H54)>8,SUM(H54-R54),"") | T54: =(IF(I54>0,MIN(8,I54),"")) | U54: =IF((I54)>8,SUM(I54-T54),"") | V54: =(IF(J54>0,MIN(8,J54),"")) | W54: =IF((J54)>8,SUM(J54-V54),"") | X54: =(IF(K54>0,MIN(8,K54),"")) | Y54: =IF((K54)>8,SUM(K54-X54),"") | Z54: =VLOOKUP(A54,#REF!,5,FALSE) -> #REF! | AA54: =VLOOKUP(A54,#REF!,6,FALSE) -> #REF! | AB54: =IFERROR(VLOOKUP(A54,Table13[[#Headers],[#Data]],7,FALSE),0) -> 0 | AC54: =SUM(Z54:AB54) -> #REF! | AD54: =Z54*C54 -> #REF! | AE54: =AA54*C54*1.5 -> #REF! | AF54: =AB54*C54*2 -> 0 | AG54: =AD54+AE54+AF54 -> #REF!
A55: FOLLA, MATIAS LAIN | B55: Electrician | C55: =VLOOKUP('6001 1st'!$B55,Table6[],2,FALSE) -> 150 | L55: =(IF(E55>0,MIN(8,E55),"")) | M55: =IF((E55)>8,SUM(E55-L55),"") | N55: =(IF(F55>0,MIN(8,F55),"")) | O55: =IF((F55)>8,SUM(F55-N55),"") | P55: =(IF(G55>0,MIN(8,G55),"")) | Q55: =IF((G55)>8,SUM(G55-P55),"") | R55: =(IF(H55>0,MIN(8,H55),"")) | S55: =IF((H55)>8,SUM(H55-R55),"") | T55: =(IF(I55>0,MIN(8,I55),"")) | U55: =IF((I55)>8,SUM(I55-T55),"") | V55: =(IF(J55>0,MIN(8,J55),"")) | W55: =IF((J55)>8,SUM(J55-V55),"") | X55: =(IF(K55>0,MIN(8,K55),"")) | Y55: =IF((K55)>8,SUM(K55-X55),"") | Z55: =VLOOKUP(A55,#REF!,5,FALSE) -> #REF! | AA55: =VLOOKUP(A55,#REF!,6,FALSE) -> #REF! | AB55: =IFERROR(VLOOKUP(A55,Table13[[#Headers],[#Data]],7,FALSE),0) -> 0 | AC55: =SUM(Z55:AB55) -> #REF! | AD55: =Z55*C55 -> #REF! | AE55: =AA55*C55*1.5 -> #REF! | AF55: =AB55*C55*2 -> 0 | AG55: =AD55+AE55+AF55 -> #REF!
A56: FORTES, NELSON | B56: Safety | C56: =VLOOKUP('6001 1st'!$B56,Table6[],2,FALSE) -> 135 | L56: =(IF(E56>0,MIN(8,E56),"")) | M56: =IF((E56)>8,SUM(E56-L56),"") | N56: =(IF(F56>0,MIN(8,F56),"")) | O56: =IF((F56)>8,SUM(F56-N56),"") | P56: =(IF(G56>0,MIN(8,G56),"")) | Q56: =IF((G56)>8,SUM(G56-P56),"") | R56: =(IF(H56>0,MIN(8,H56),"")) | S56: =IF((H56)>8,SUM(H56-R56),"") | T56: =(IF(I56>0,MIN(8,I56),"")) | U56: =IF((I56)>8,SUM(I56-T56),"") | V56: =(IF(J56>0,MIN(8,J56),"")) | W56: =IF((J56)>8,SUM(J56-V56),"") | X56: =(IF(K56>0,MIN(8,K56),"")) | Y56: =IF((K56)>8,SUM(K56-X56),"") | Z56: =VLOOKUP(A56,#REF!,5,FALSE) -> #REF! | AA56: =VLOOKUP(A56,#REF!,6,FALSE) -> #REF! | AB56: =IFERROR(VLOOKUP(A56,Table13[[#Headers],[#Data]],7,FALSE),0) -> 0 | AC56: =SUM(Z56:AB56) -> #REF! | AD56: =Z56*C56 -> #REF! | AE56: =AA56*C56*1.5 -> #REF! | AF56: =AB56*C56*2 -> 0 | AG56: =AD56+AE56+AF56 -> #REF!
A57: GALVEZ, EDGAR TUN | B57: Electrician | C57: =VLOOKUP('6001 1st'!$B57,Table6[],2,FALSE) -> 150 | L57: =(IF(E57>0,MIN(8,E57),"")) | M57: =IF((E57)>8,SUM(E57-L57),"") | N57: =(IF(F57>0,MIN(8,F57),"")) | O57: =IF((F57)>8,SUM(F57-N57),"") | P57: =(IF(G57>0,MIN(8,G57),"")) | Q57: =IF((G57)>8,SUM(G57-P57),"") | R57: =(IF(H57>0,MIN(8,H57),"")) | S57: =IF((H57)>8,SUM(H57-R57),"") | T57: =(IF(I57>0,MIN(8,I57),"")) | U57: =IF((I57)>8,SUM(I57-T57),"") | V57: =(IF(J57>0,MIN(8,J57),"")) | W57: =IF((J57)>8,SUM(J57-V57),"") | X57: =(IF(K57>0,MIN(8,K57),"")) | Y57: =IF((K57)>8,SUM(K57-X57),"") | Z57: =VLOOKUP(A57,#REF!,5,FALSE) -> #REF! | AA57: =VLOOKUP(A57,#REF!,6,FALSE) -> #REF! | AB57: =IFERROR(VLOOKUP(A57,Table13[[#Headers],[#Data]],7,FALSE),0) -> 0 | AC57: =SUM(Z57:AB57) -> #REF! | AD57: =Z57*C57 -> #REF! | AE57: =AA57*C57*1.5 -> #REF! | AF57: =AB57*C57*2 -> 0 | AG57: =AD57+AE57+AF57 -> #REF!
A58: GOMEZ, ISMAEL | B58: Electrician | C58: =VLOOKUP('6001 1st'!$B58,Table6[],2,FALSE) -> 150 | Z58: =VLOOKUP(A58,#REF!,5,FALSE) -> #REF! | AA58: =VLOOKUP(A58,#REF!,6,FALSE) -> #REF! | AB58: =IFERROR(VLOOKUP(A58,Table13[[#Headers],[#Data]],7,FALSE),0) -> 0 | AC58: =SUM(Z58:AB58) -> #REF! | AD58: =Z58*C58 -> #REF! | AE58: =AA58*C58*1.5 -> #REF! | AF58: =AB58*C58*2 -> 0 | AG58: =AD58+AE58+AF58 -> #REF!
A59: GALVEZ, OSCAR TUN | B59: Electrician | C59: =VLOOKUP('6001 1st'!$B59,Table6[],2,FALSE) -> 150 | L59: =(IF(E59>0,MIN(8,E59),"")) | M59: =IF((E59)>8,SUM(E59-L59),"") | N59: =(IF(F59>0,MIN(8,F59),"")) | O59: =IF((F59)>8,SUM(F59-N59),"") | P59: =(IF(G59>0,MIN(8,G59),"")) | Q59: =IF((G59)>8,SUM(G59-P59),"") | R59: =(IF(H59>0,MIN(8,H59),"")) | S59: =IF((H59)>8,SUM(H59-R59),"") | T59: =(IF(I59>0,MIN(8,I59),"")) | U59: =IF((I59)>8,SUM(I59-T59),"") | V59: =(IF(J59>0,MIN(8,J59),"")) | W59: =IF((J59)>8,SUM(J59-V59),"") | X59: =(IF(K59>0,MIN(8,K59),"")) | Y59: =IF((K59)>8,SUM(K59-X59),"") | Z59: =VLOOKUP(A59,#REF!,5,FALSE) -> #REF! | AA59: =VLOOKUP(A59,#REF!,6,FALSE) -> #REF! | AB59: =IFERROR(VLOOKUP(A59,Table13[[#Headers],[#Data]],7,FALSE),0) -> 0 | AC59: =SUM(Z59:AB59) -> #REF! | AD59: =Z59*C59 -> #REF! | AE59: =AA59*C59*1.5 -> #REF! | AF59: =AB59*C59*2 -> 0 | AG59: =AD59+AE59+AF59 -> #REF!
A60: GOMEZ, LUIS | B60: Electrician | C60: =VLOOKUP('6001 1st'!$B60,Table6[],2,FALSE) -> 150 | L60: =(IF(E60>0,MIN(8,E60),"")) | M60: =IF((E60)>8,SUM(E60-L60),"") | N60: =(IF(F60>0,MIN(8,F60),"")) | O60: =IF((F60)>8,SUM(F60-N60),"") | P60: =(IF(G60>0,MIN(8,G60),"")) | Q60: =IF((G60)>8,SUM(G60-P60),"") | R60: =(IF(H60>0,MIN(8,H60),"")) | S60: =IF((H60)>8,SUM(H60-R60),"") | T60: =(IF(I60>0,MIN(8,I60),"")) | U60: =IF((I60)>8,SUM(I60-T60),"") | V60: =(IF(J60>0,MIN(8,J60),"")) | W60: =IF((J60)>8,SUM(J60-V60),"") | X60: =(IF(K60>0,MIN(8,K60),"")) | Y60: =IF((K60)>8,SUM(K60-X60),"") | Z60: =VLOOKUP(A60,#REF!,5,FALSE) -> #REF! | AA60: =VLOOKUP(A60,#REF!,6,FALSE) -> #REF! | AB60: =IFERROR(VLOOKUP(A60,Table13[[#Headers],[#Data]],7,FALSE),0) -> 0 | AC60: =SUM(Z60:AB60) -> #REF! | AD60: =Z60*C60 -> #REF! | AE60: =AA60*C60*1.5 -> #REF! | AF60: =AB60*C60*2 -> 0 | AG60: =AD60+AE60+AF60 -> #REF!
A61: GOMEZ, RODOLFO RUEDA | B61: Electrician | C61: =VLOOKUP('6001 1st'!$B61,Table6[],2,FALSE) -> 150 | L61: =(IF(E61>0,MIN(8,E61),"")) | M61: =IF((E61)>8,SUM(E61-L61),"") | N61: =(IF(F61>0,MIN(8,F61),"")) | O61: =IF((F61)>8,SUM(F61-N61),"") | P61: =(IF(G61>0,MIN(8,G61),"")) | Q61: =IF((G61)>8,SUM(G61-P61),"") | R61: =(IF(H61>0,MIN(8,H61),"")) | S61: =IF((H61)>8,SUM(H61-R61),"") | T61: =(IF(I61>0,MIN(8,I61),"")) | U61: =IF((I61)>8,SUM(I61-T61),"") | V61: =(IF(J61>0,MIN(8,J61),"")) | W61: =IF((J61)>8,SUM(J61-V61),"") | X61: =(IF(K61>0,MIN(8,K61),"")) | Y61: =IF((K61)>8,SUM(K61-X61),"") | Z61: =VLOOKUP(A61,#REF!,5,FALSE) -> #REF! | AA61: =VLOOKUP(A61,#REF!,6,FALSE) -> #REF! | AB61: =IFERROR(VLOOKUP(A61,Table13[[#Headers],[#Data]],7,FALSE),0) -> 0 | AC61: =SUM(Z61:AB61) -> #REF! | AD61: =Z61*C61 -> #REF! | AE61: =AA61*C61*1.5 -> #REF! | AF61: =AB61*C61*2 -> 0 | AG61: =AD61+AE61+AF61 -> #REF!
A62: GONZALEZ, ELDER | B62: Electrician | C62: =VLOOKUP('6001 1st'!$B62,Table6[],2,FALSE) -> 150 | L62: =(IF(E62>0,MIN(8,E62),"")) | M62: =IF((E62)>8,SUM(E62-L62),"") | N62: =(IF(F62>0,MIN(8,F62),"")) | O62: =IF((F62)>8,SUM(F62-N62),"") | P62: =(IF(G62>0,MIN(8,G62),"")) | Q62: =IF((G62)>8,SUM(G62-P62),"") | R62: =(IF(H62>0,MIN(8,H62),"")) | S62: =IF((H62)>8,SUM(H62-R62),"") | T62: =(IF(I62>0,MIN(8,I62),"")) | U62: =IF((I62)>8,SUM(I62-T62),"") | V62: =(IF(J62>0,MIN(8,J62),"")) | W62: =IF((J62)>8,SUM(J62-V62),"") | X62: =(IF(K62>0,MIN(8,K62),"")) | Y62: =IF((K62)>8,SUM(K62-X62),"") | Z62: =VLOOKUP(A62,#REF!,5,FALSE) -> #REF! | AA62: =VLOOKUP(A62,#REF!,6,FALSE) -> #REF! | AB62: =IFERROR(VLOOKUP(A62,Table13[[#Headers],[#Data]],7,FALSE),0) -> 0 | AC62: =SUM(Z62:AB62) -> #REF! | AD62: =Z62*C62 -> #REF! | AE62: =AA62*C62*1.5 -> #REF! | AF62: =AB62*C62*2 -> 0 | AG62: =AD62+AE62+AF62 -> #REF!
A63: GONZALES, LUIS ANGEL | B63: Electrician | C63: =VLOOKUP('6001 1st'!$B63,Table6[],2,FALSE) -> 150 | L63: =(IF(E63>0,MIN(8,E63),"")) | M63: =IF((E63)>8,SUM(E63-L63),"") | N63: =(IF(F63>0,MIN(8,F63),"")) | O63: =IF((F63)>8,SUM(F63-N63),"") | P63: =(IF(G63>0,MIN(8,G63),"")) | Q63: =IF((G63)>8,SUM(G63-P63),"") | R63: =(IF(H63>0,MIN(8,H63),"")) | S63: =IF((H63)>8,SUM(H63-R63),"") | T63: =(IF(I63>0,MIN(8,I63),"")) | U63: =IF((I63)>8,SUM(I63-T63),"") | V63: =(IF(J63>0,MIN(8,J63),"")) | W63: =IF((J63)>8,SUM(J63-V63),"") | X63: =(IF(K63>0,MIN(8,K63),"")) | Y63: =IF((K63)>8,SUM(K63-X63),"") | Z63: =VLOOKUP(A63,#REF!,5,FALSE) -> #REF! | AA63: =VLOOKUP(A63,#REF!,6,FALSE) -> #REF! | AB63: =IFERROR(VLOOKUP(A63,Table13[[#Headers],[#Data]],7,FALSE),0) -> 0 | AC63: =SUM(Z63:AB63) -> #REF! | AD63: =Z63*C63 -> #REF! | AE63: =AA63*C63*1.5 -> #REF! | AF63: =AB63*C63*2 -> 0 | AG63: =AD63+AE63+AF63 -> #REF!
A64: GONZALEZ, MIGUELANGEL | B64: Electrician | C64: =VLOOKUP('6001 1st'!$B64,Table6[],2,FALSE) -> 150 | L64: =(IF(E64>0,MIN(8,E64),"")) | M64: =IF((E64)>8,SUM(E64-L64),"") | N64: =(IF(F64>0,MIN(8,F64),"")) | O64: =IF((F64)>8,SUM(F64-N64),"") | P64: =(IF(G64>0,MIN(8,G64),"")) | Q64: =IF((G64)>8,SUM(G64-P64),"") | R64: =(IF(H64>0,MIN(8,H64),"")) | S64: =IF((H64)>8,SUM(H64-R64),"") | T64: =(IF(I64>0,MIN(8,I64),"")) | U64: =IF((I64)>8,SUM(I64-T64),"") | V64: =(IF(J64>0,MIN(8,J64),"")) | W64: =IF((J64)>8,SUM(J64-V64),"") | X64: =(IF(K64>0,MIN(8,K64),"")) | Y64: =IF((K64)>8,SUM(K64-X64),"") | Z64: =VLOOKUP(A64,#REF!,5,FALSE) -> #REF! | AA64: =VLOOKUP(A64,#REF!,6,FALSE) -> #REF! | AB64: =IFERROR(VLOOKUP(A64,Table13[[#Headers],[#Data]],7,FALSE),0) -> 0 | AC64: =SUM(Z64:AB64) -> #REF! | AD64: =Z64*C64 -> #REF! | AE64: =AA64*C64*1.5 -> #REF! | AF64: =AB64*C64*2 -> 0 | AG64: =AD64+AE64+AF64 -> #REF!
A65: GRAJEDA, HECTOR | B65: Electrician | C65: =VLOOKUP('6001 1st'!$B65,Table6[],2,FALSE) -> 150 | L65: =(IF(E65>0,MIN(8,E65),"")) | M65: =IF((E65)>8,SUM(E65-L65),"") | N65: =(IF(F65>0,MIN(8,F65),"")) | O65: =IF((F65)>8,SUM(F65-N65),"") | P65: =(IF(G65>0,MIN(8,G65),"")) | Q65: =IF((G65)>8,SUM(G65-P65),"") | R65: =(IF(H65>0,MIN(8,H65),"")) | S65: =IF((H65)>8,SUM(H65-R65),"") | T65: =(IF(I65>0,MIN(8,I65),"")) | U65: =IF((I65)>8,SUM(I65-T65),"") | V65: =(IF(J65>0,MIN(8,J65),"")) | W65: =IF((J65)>8,SUM(J65-V65),"") | X65: =(IF(K65>0,MIN(8,K65),"")) | Y65: =IF((K65)>8,SUM(K65-X65),"") | Z65: =VLOOKUP(A65,#REF!,5,FALSE) -> #REF! | AA65: =VLOOKUP(A65,#REF!,6,FALSE) -> #REF! | AB65: =IFERROR(VLOOKUP(A65,Table13[[#Headers],[#Data]],7,FALSE),0) -> 0 | AC65: =SUM(Z65:AB65) -> #REF! | AD65: =Z65*C65 -> #REF! | AE65: =AA65*C65*1.5 -> #REF! | AF65: =AB65*C65*2 -> 0 | AG65: =AD65+AE65+AF65 -> #REF!
A66: GRATEROL, ELIANA | B66: Electrician | C66: =VLOOKUP('6001 1st'!$B66,Table6[],2,FALSE) -> 150 | L66: =(IF(E66>0,MIN(8,E66),"")) | M66: =IF((E66)>8,SUM(E66-L66),"") | N66: =(IF(F66>0,MIN(8,F66),"")) | O66: =IF((F66)>8,SUM(F66-N66),"") | P66: =(IF(G66>0,MIN(8,G66),"")) | Q66: =IF((G66)>8,SUM(G66-P66),"") | R66: =(IF(H66>0,MIN(8,H66),"")) | S66: =IF((H66)>8,SUM(H66-R66),"") | T66: =(IF(I66>0,MIN(8,I66),"")) | U66: =IF((I66)>8,SUM(I66-T66),"") | V66: =(IF(J66>0,MIN(8,J66),"")) | W66: =IF((J66)>8,SUM(J66-V66),"") | X66: =(IF(K66>0,MIN(8,K66),"")) | Y66: =IF((K66)>8,SUM(K66-X66),"") | Z66: =VLOOKUP(A66,#REF!,5,FALSE) -> #REF! | AA66: =VLOOKUP(A66,#REF!,6,FALSE) -> #REF! | AB66: =IFERROR(VLOOKUP(A66,Table13[[#Headers],[#Data]],7,FALSE),0) -> 0 | AC66: =SUM(Z66:AB66) -> #REF! | AD66: =Z66*C66 -> #REF! | AE66: =AA66*C66*1.5 -> #REF! | AF66: =AB66*C66*2 -> 0 | AG66: =AD66+AE66+AF66 -> #REF!
A67: GREENE, STEVIE | B67: Safety | C67: =VLOOKUP('6001 1st'!$B67,Table6[],2,FALSE) -> 135 | L67: =(IF(E67>0,MIN(8,E67),"")) | M67: =IF((E67)>8,SUM(E67-L67),"") | N67: =(IF(F67>0,MIN(8,F67),"")) | O67: =IF((F67)>8,SUM(F67-N67),"") | P67: =(IF(G67>0,MIN(8,G67),"")) | Q67: =IF((G67)>8,SUM(G67-P67),"") | R67: =(IF(H67>0,MIN(8,H67),"")) | S67: =IF((H67)>8,SUM(H67-R67),"") | T67: =(IF(I67>0,MIN(8,I67),"")) | U67: =IF((I67)>8,SUM(I67-T67),"") | V67: =(IF(J67>0,MIN(8,J67),"")) | W67: =IF((J67)>8,SUM(J67-V67),"") | X67: =(IF(K67>0,MIN(8,K67),"")) | Y67: =IF((K67)>8,SUM(K67-X67),"") | Z67: =VLOOKUP(A67,#REF!,5,FALSE) -> #REF! | AA67: =VLOOKUP(A67,#REF!,6,FALSE) -> #REF! | AB67: =IFERROR(VLOOKUP(A67,Table13[[#Headers],[#Data]],7,FALSE),0) -> 0 | AC67: =SUM(Z67:AB67) -> #REF! | AD67: =Z67*C67 -> #REF! | AE67: =AA67*C67*1.5 -> #REF! | AF67: =AB67*C67*2 -> 0 | AG67: =AD67+AE67+AF67 -> #REF!
A68: HERNANDEZ, ANTONIO | B68: Electrician | C68: =VLOOKUP('6001 1st'!$B68,Table6[],2,FALSE) -> 150 | L68: =(IF(E68>0,MIN(8,E68),"")) | M68: =IF((E68)>8,SUM(E68-L68),"") | N68: =(IF(F68>0,MIN(8,F68),"")) | O68: =IF((F68)>8,SUM(F68-N68),"") | P68: =(IF(G68>0,MIN(8,G68),"")) | Q68: =IF((G68)>8,SUM(G68-P68),"") | R68: =(IF(H68>0,MIN(8,H68),"")) | S68: =IF((H68)>8,SUM(H68-R68),"") | T68: =(IF(I68>0,MIN(8,I68),"")) | U68: =IF((I68)>8,SUM(I68-T68),"") | V68: =(IF(J68>0,MIN(8,J68),"")) | W68: =IF((J68)>8,SUM(J68-V68),"") | X68: =(IF(K68>0,MIN(8,K68),"")) | Y68: =IF((K68)>8,SUM(K68-X68),"") | Z68: =VLOOKUP(A68,#REF!,5,FALSE) -> #REF! | AA68: =VLOOKUP(A68,#REF!,6,FALSE) -> #REF! | AB68: =IFERROR(VLOOKUP(A68,Table13[[#Headers],[#Data]],7,FALSE),0) -> 0 | AC68: =SUM(Z68:AB68) -> #REF! | AD68: =Z68*C68 -> #REF! | AE68: =AA68*C68*1.5 -> #REF! | AF68: =AB68*C68*2 -> 0 | AG68: =AD68+AE68+AF68 -> #REF!
A69: HERNANDEZ, ARMANDO LEZAMA | B69: Electrician | C69: =VLOOKUP('6001 1st'!$B69,Table6[],2,FALSE) -> 150 | L69: =(IF(E69>0,MIN(8,E69),"")) | M69: =IF((E69)>8,SUM(E69-L69),"") | N69: =(IF(F69>0,MIN(8,F69),"")) | O69: =IF((F69)>8,SUM(F69-N69),"") | P69: =(IF(G69>0,MIN(8,G69),"")) | Q69: =IF((G69)>8,SUM(G69-P69),"") | R69: =(IF(H69>0,MIN(8,H69),"")) | S69: =IF((H69)>8,SUM(H69-R69),"") | T69: =(IF(I69>0,MIN(8,I69),"")) | U69: =IF((I69)>8,SUM(I69-T69),"") | V69: =(IF(J69>0,MIN(8,J69),"")) | W69: =IF((J69)>8,SUM(J69-V69),"") | X69: =(IF(K69>0,MIN(8,K69),"")) | Y69: =IF((K69)>8,SUM(K69-X69),"") | Z69: =VLOOKUP(A69,#REF!,5,FALSE) -> #REF! | AA69: =VLOOKUP(A69,#REF!,6,FALSE) -> #REF! | AB69: =IFERROR(VLOOKUP(A69,Table13[[#Headers],[#Data]],7,FALSE),0) -> 0 | AC69: =SUM(Z69:AB69) -> #REF! | AD69: =Z69*C69 -> #REF! | AE69: =AA69*C69*1.5 -> #REF! | AF69: =AB69*C69*2 -> 0 | AG69: =AD69+AE69+AF69 -> #REF!
A70: HERNANDEZ, DANIELA | B70: Electrician | C70: =VLOOKUP('6001 1st'!$B70,Table6[],2,FALSE) -> 150 | L70: =(IF(E70>0,MIN(8,E70),"")) | M70: =IF((E70)>8,SUM(E70-L70),"") | N70: =(IF(F70>0,MIN(8,F70),"")) | O70: =IF((F70)>8,SUM(F70-N70),"") | P70: =(IF(G70>0,MIN(8,G70),"")) | Q70: =IF((G70)>8,SUM(G70-P70),"") | R70: =(IF(H70>0,MIN(8,H70),"")) | S70: =IF((H70)>8,SUM(H70-R70),"") | T70: =(IF(I70>0,MIN(8,I70),"")) | U70: =IF((I70)>8,SUM(I70-T70),"") | V70: =(IF(J70>0,MIN(8,J70),"")) | W70: =IF((J70)>8,SUM(J70-V70),"") | X70: =(IF(K70>0,MIN(8,K70),"")) | Y70: =IF((K70)>8,SUM(K70-X70),"") | Z70: =VLOOKUP(A70,#REF!,5,FALSE) -> #REF! | AA70: =VLOOKUP(A70,#REF!,6,FALSE) -> #REF! | AB70: =IFERROR(VLOOKUP(A70,Table13[[#Headers],[#Data]],7,FALSE),0) -> 0 | AC70: =SUM(Z70:AB70) -> #REF! | AD70: =Z70*C70 -> #REF! | AE70: =AA70*C70*1.5 -> #REF! | AF70: =AB70*C70*2 -> 0 | AG70: =AD70+AE70+AF70 -> #REF!
... A89: LUERA, JOSUE SILVA DE | B89: Electrician | C89: =VLOOKUP('6001 1st'!$B89,Table6[],2,FALSE) -> 150 | L89: =(IF(E89>0,MIN(8,E89),"")) | M89: =IF((E89)>8,SUM(E89-L89),"") | N89: =(IF(F89>0,MIN(8,F89),"")) | O89: =IF((F89)>8,SUM(F89-N89),"") | P89: =(IF(G89>0,MIN(8,G89),"")) | Q89: =IF((G89)>8,SUM(G89-P89),"") | R89: =(IF(H89>0,MIN(8,H89),"")) | S89: =IF((H89)>8,SUM(H89-R89),"") | T89: =(IF(I89>0,MIN(8,I89),"")) | U89: =IF((I89)>8,SUM(I89-T89),"") | V89: =(IF(J89>0,MIN(8,J89),"")) | W89: =IF((J89)>8,SUM(J89-V89),"") | X89: =(IF(K89>0,MIN(8,K89),"")) | Y89: =IF((K89)>8,SUM(K89-X89),"") | Z89: =VLOOKUP(A89,#REF!,5,FALSE) -> #REF! | AA89: =VLOOKUP(A89,#REF!,6,FALSE) -> #REF! | AB89: =IFERROR(VLOOKUP(A89,Table13[[#Headers],[#Data]],7,FALSE),0) -> 0 | AC89: =SUM(Z89:AB89) -> #REF! | AD89: =Z89*C89 -> #REF! | AE89: =AA89*C89*1.5 -> #REF! | AF89: =AB89*C89*2 -> 0 | AG89: =AD89+AE89+AF89 -> #REF!
A90: LUGARDO, CARLOS | B90: QA/QC Director | C90: 175 | Z90: =VLOOKUP(A90,#REF!,5,FALSE) -> #REF! | AA90: =VLOOKUP(A90,#REF!,6,FALSE) -> #REF! | AB90: =IFERROR(VLOOKUP(A90,Table13[[#Headers],[#Data]],7,FALSE),0) -> 0 | AC90: =SUM(Z90:AB90) -> #REF! | AD90: =Z90*C90 -> #REF! | AE90: =AA90*C90*1.5 -> #REF! | AF90: =AB90*C90*2 -> 0 | AG90: =AD90+AE90+AF90 -> #REF! | AP90: 8 | AS90: 8
A91: MACIAS, LEONARDO | B91: Electrician | C91: =VLOOKUP('6001 1st'!$B91,Table6[],2,FALSE) -> 150 | L91: =(IF(E91>0,MIN(8,E91),"")) | M91: =IF((E91)>8,SUM(E91-L91),"") | N91: =(IF(F91>0,MIN(8,F91),"")) | O91: =IF((F91)>8,SUM(F91-N91),"") | P91: =(IF(G91>0,MIN(8,G91),"")) | Q91: =IF((G91)>8,SUM(G91-P91),"") | R91: =(IF(H91>0,MIN(8,H91),"")) | S91: =IF((H91)>8,SUM(H91-R91),"") | T91: =(IF(I91>0,MIN(8,I91),"")) | U91: =IF((I91)>8,SUM(I91-T91),"") | V91: =(IF(J91>0,MIN(8,J91),"")) | W91: =IF((J91)>8,SUM(J91-V91),"") | X91: =(IF(K91>0,MIN(8,K91),"")) | Y91: =IF((K91)>8,SUM(K91-X91),"") | Z91: =VLOOKUP(A91,#REF!,5,FALSE) -> #REF! | AA91: =VLOOKUP(A91,#REF!,6,FALSE) -> #REF! | AB91: =IFERROR(VLOOKUP(A91,Table13[[#Headers],[#Data]],7,FALSE),0) -> 0 | AC91: =SUM(Z91:AB91) -> #REF! | AD91: =Z91*C91 -> #REF! | AE91: =AA91*C91*1.5 -> #REF! | AF91: =AB91*C91*2 -> 0 | AG91: =AD91+AE91+AF91 -> #REF! | AQ91: =AO91+AC91-AP91 -> #REF!
A92: LUQUE, WILLIAM | B92: Electrician | C92: =VLOOKUP('6001 1st'!$B92,Table6[],2,FALSE) -> 150 | L92: =(IF(E92>0,MIN(8,E92),"")) | M92: =IF((E92)>8,SUM(E92-L92),"") | N92: =(IF(F92>0,MIN(8,F92),"")) | O92: =IF((F92)>8,SUM(F92-N92),"") | P92: =(IF(G92>0,MIN(8,G92),"")) | Q92: =IF((G92)>8,SUM(G92-P92),"") | R92: =(IF(H92>0,MIN(8,H92),"")) | S92: =IF((H92)>8,SUM(H92-R92),"") | T92: =(IF(I92>0,MIN(8,I92),"")) | U92: =IF((I92)>8,SUM(I92-T92),"") | V92: =(IF(J92>0,MIN(8,J92),"")) | W92: =IF((J92)>8,SUM(J92-V92),"") | X92: =(IF(K92>0,MIN(8,K92),"")) | Y92: =IF((K92)>8,SUM(K92-X92),"") | Z92: =VLOOKUP(A92,#REF!,5,FALSE) -> #REF! | AA92: =VLOOKUP(A92,#REF!,6,FALSE) -> #REF! | AB92: =IFERROR(VLOOKUP(A92,Table13[[#Headers],[#Data]],7,FALSE),0) -> 0 | AC92: =SUM(Z92:AB92) -> #REF! | AD92: =Z92*C92 -> #REF! | AE92: =AA92*C92*1.5 -> #REF! | AF92: =AB92*C92*2 -> 0 | AG92: =AD92+AE92+AF92 -> #REF! | AQ92: =AO92+AC92-AP92 -> #REF!
A93: MARQUEZ, CESAR | B93: Electrician | C93: =VLOOKUP('6001 1st'!$B93,Table6[],2,FALSE) -> 150 | L93: =(IF(E93>0,MIN(8,E93),"")) | M93: =IF((E93)>8,SUM(E93-L93),"") | N93: =(IF(F93>0,MIN(8,F93),"")) | O93: =IF((F93)>8,SUM(F93-N93),"") | P93: =(IF(G93>0,MIN(8,G93),"")) | Q93: =IF((G93)>8,SUM(G93-P93),"") | R93: =(IF(H93>0,MIN(8,H93),"")) | S93: =IF((H93)>8,SUM(H93-R93),"") | T93: =(IF(I93>0,MIN(8,I93),"")) | U93: =IF((I93)>8,SUM(I93-T93),"") | V93: =(IF(J93>0,MIN(8,J93),"")) | W93: =IF((J93)>8,SUM(J93-V93),"") | X93: =(IF(K93>0,MIN(8,K93),"")) | Y93: =IF((K93)>8,SUM(K93-X93),"") | Z93: =VLOOKUP(A93,#REF!,5,FALSE) -> #REF! | AA93: =VLOOKUP(A93,#REF!,6,FALSE) -> #REF! | AB93: =IFERROR(VLOOKUP(A93,Table13[[#Headers],[#Data]],7,FALSE),0) -> 0 | AC93: =SUM(Z93:AB93) -> #REF! | AD93: =Z93*C93 -> #REF! | AE93: =AA93*C93*1.5 -> #REF! | AF93: =AB93*C93*2 -> 0 | AG93: =AD93+AE93+AF93 -> #REF! | AQ93: =AO93+AC93-AP93 -> #REF!
A94: MARROQUIN, JUAN | B94: Electrician | C94: =VLOOKUP('6001 1st'!$B94,Table6[],2,FALSE) -> 150 | L94: =(IF(E94>0,MIN(8,E94),"")) | M94: =IF((E94)>8,SUM(E94-L94),"") | N94: =(IF(F94>0,MIN(8,F94),"")) | O94: =IF((F94)>8,SUM(F94-N94),"") | P94: =(IF(G94>0,MIN(8,G94),"")) | Q94: =IF((G94)>8,SUM(G94-P94),"") | R94: =(IF(H94>0,MIN(8,H94),"")) | S94: =IF((H94)>8,SUM(H94-R94),"") | T94: =(IF(I94>0,MIN(8,I94),"")) | U94: =IF((I94)>8,SUM(I94-T94),"") | V94: =(IF(J94>0,MIN(8,J94),"")) | W94: =IF((J94)>8,SUM(J94-V94),"") | X94: =(IF(K94>0,MIN(8,K94),"")) | Y94: =IF((K94)>8,SUM(K94-X94),"") | Z94: =VLOOKUP(A94,#REF!,5,FALSE) -> #REF! | AA94: =VLOOKUP(A94,#REF!,6,FALSE) -> #REF! | AB94: =IFERROR(VLOOKUP(A94,Table13[[#Headers],[#Data]],7,FALSE),0) -> 0 | AC94: =SUM(Z94:AB94) -> #REF! | AD94: =Z94*C94 -> #REF! | AE94: =AA94*C94*1.5 -> #REF! | AF94: =AB94*C94*2 -> 0 | AG94: =AD94+AE94+AF94 -> #REF! | AQ94: =AO94+AC94-AP94 -> #REF!
A95: MARTIN, JUAN JOSE REYNA | B95: Electrician | C95: =VLOOKUP('6001 1st'!$B95,Table6[],2,FALSE) -> 150 | L95: =(IF(E95>0,MIN(8,E95),"")) | M95: =IF((E95)>8,SUM(E95-L95),"") | N95: =(IF(F95>0,MIN(8,F95),"")) | O95: =IF((F95)>8,SUM(F95-N95),"") | P95: =(IF(G95>0,MIN(8,G95),"")) | Q95: =IF((G95)>8,SUM(G95-P95),"") | R95: =(IF(H95>0,MIN(8,H95),"")) | S95: =IF((H95)>8,SUM(H95-R95),"") | T95: =(IF(I95>0,MIN(8,I95),"")) | U95: =IF((I95)>8,SUM(I95-T95),"") | V95: =(IF(J95>0,MIN(8,J95),"")) | W95: =IF((J95)>8,SUM(J95-V95),"") | X95: =(IF(K95>0,MIN(8,K95),"")) | Y95: =IF((K95)>8,SUM(K95-X95),"") | Z95: =VLOOKUP(A95,#REF!,5,FALSE) -> #REF! | AA95: =VLOOKUP(A95,#REF!,6,FALSE) -> #REF! | AB95: =IFERROR(VLOOKUP(A95,Table13[[#Headers],[#Data]],7,FALSE),0) -> 0 | AC95: =SUM(Z95:AB95) -> #REF! | AD95: =Z95*C95 -> #REF! | AE95: =AA95*C95*1.5 -> #REF! | AF95: =AB95*C95*2 -> 0 | AG95: =AD95+AE95+AF95 -> #REF! | AQ95: =AO95+AC95-AP95 -> #REF!
A96: MATURINO, JESUS | B96: Electrician | C96: =VLOOKUP('6001 1st'!$B96,Table6[],2,FALSE) -> 150 | L96: =(IF(E96>0,MIN(8,E96),"")) | M96: =IF((E96)>8,SUM(E96-L96),"") | N96: =(IF(F96>0,MIN(8,F96),"")) | O96: =IF((F96)>8,SUM(F96-N96),"") | P96: =(IF(G96>0,MIN(8,G96),"")) | Q96: =IF((G96)>8,SUM(G96-P96),"") | R96: =(IF(H96>0,MIN(8,H96),"")) | S96: =IF((H96)>8,SUM(H96-R96),"") | T96: =(IF(I96>0,MIN(8,I96),"")) | U96: =IF((I96)>8,SUM(I96-T96),"") | V96: =(IF(J96>0,MIN(8,J96),"")) | W96: =IF((J96)>8,SUM(J96-V96),"") | X96: =(IF(K96>0,MIN(8,K96),"")) | Y96: =IF((K96)>8,SUM(K96-X96),"") | Z96: =VLOOKUP(A96,#REF!,5,FALSE) -> #REF! | AA96: =VLOOKUP(A96,#REF!,6,FALSE) -> #REF! | AB96: =IFERROR(VLOOKUP(A96,Table13[[#Headers],[#Data]],7,FALSE),0) -> 0 | AC96: =SUM(Z96:AB96) -> #REF! | AD96: =Z96*C96 -> #REF! | AE96: =AA96*C96*1.5 -> #REF! | AF96: =AB96*C96*2 -> 0 | AG96: =AD96+AE96+AF96 -> #REF! | AQ96: =AO96+AC96-AP96 -> #REF!
A97: MCDONALD, ROBERT | B97: Electrician | C97: =VLOOKUP('6001 1st'!$B97,Table6[],2,FALSE) -> 150 | L97: =(IF(E97>0,MIN(8,E97),"")) | M97: =IF((E97)>8,SUM(E97-L97),"") | N97: =(IF(F97>0,MIN(8,F97),"")) | O97: =IF((F97)>8,SUM(F97-N97),"") | P97: =(IF(G97>0,MIN(8,G97),"")) | Q97: =IF((G97)>8,SUM(G97-P97),"") | R97: =(IF(H97>0,MIN(8,H97),"")) | S97: =IF((H97)>8,SUM(H97-R97),"") | T97: =(IF(I97>0,MIN(8,I97),"")) | U97: =IF((I97)>8,SUM(I97-T97),"") | V97: =(IF(J97>0,MIN(8,J97),"")) | W97: =IF((J97)>8,SUM(J97-V97),"") | X97: =(IF(K97>0,MIN(8,K97),"")) | Y97: =IF((K97)>8,SUM(K97-X97),"") | Z97: =VLOOKUP(A97,#REF!,5,FALSE) -> #REF! | AA97: =VLOOKUP(A97,#REF!,6,FALSE) -> #REF! | AB97: =IFERROR(VLOOKUP(A97,Table13[[#Headers],[#Data]],7,FALSE),0) -> 0 | AC97: =SUM(Z97:AB97) -> #REF! | AD97: =Z97*C97 -> #REF! | AE97: =AA97*C97*1.5 -> #REF! | AF97: =AB97*C97*2 -> 0 | AG97: =AD97+AE97+AF97 -> #REF! | AQ97: =AO97+AC97-AP97 -> #REF!
A98: MEDELLIN, CHRISTIAN | B98: Electrician | C98: =VLOOKUP('6001 1st'!$B98,Table6[],2,FALSE) -> 150 | L98: =(IF(E98>0,MIN(8,E98),"")) | M98: =IF((E98)>8,SUM(E98-L98),"") | N98: =(IF(F98>0,MIN(8,F98),"")) | O98: =IF((F98)>8,SUM(F98-N98),"") | P98: =(IF(G98>0,MIN(8,G98),"")) | Q98: =IF((G98)>8,SUM(G98-P98),"") | R98: =(IF(H98>0,MIN(8,H98),"")) | S98: =IF((H98)>8,SUM(H98-R98),"") | T98: =(IF(I98>0,MIN(8,I98),"")) | U98: =IF((I98)>8,SUM(I98-T98),"") | V98: =(IF(J98>0,MIN(8,J98),"")) | W98: =IF((J98)>8,SUM(J98-V98),"") | X98: =(IF(K98>0,MIN(8,K98),"")) | Y98: =IF((K98)>8,SUM(K98-X98),"") | Z98: =VLOOKUP(A98,#REF!,5,FALSE) -> #REF! | AA98: =VLOOKUP(A98,#REF!,6,FALSE) -> #REF! | AB98: =IFERROR(VLOOKUP(A98,Table13[[#Headers],[#Data]],7,FALSE),0) -> 0 | AC98: =SUM(Z98:AB98) -> #REF! | AD98: =Z98*C98 -> #REF! | AE98: =AA98*C98*1.5 -> #REF! | AF98: =AB98*C98*2 -> 0 | AG98: =AD98+AE98+AF98 -> #REF! | AQ98: =AO98+AC98-AP98 -> #REF!
A99: MENDOZA, BISMARCK | B99: Electrician | C99: =VLOOKUP('6001 1st'!$B99,Table6[],2,FALSE) -> 150 | L99: =(IF(E99>0,MIN(8,E99),"")) | M99: =IF((E99)>8,SUM(E99-L99),"") | N99: =(IF(F99>0,MIN(8,F99),"")) | O99: =IF((F99)>8,SUM(F99-N99),"") | P99: =(IF(G99>0,MIN(8,G99),"")) | Q99: =IF((G99)>8,SUM(G99-P99),"") | R99: =(IF(H99>0,MIN(8,H99),"")) | S99: =IF((H99)>8,SUM(H99-R99),"") | T99: =(IF(I99>0,MIN(8,I99),"")) | U99: =IF((I99)>8,SUM(I99-T99),"") | V99: =(IF(J99>0,MIN(8,J99),"")) | W99: =IF((J99)>8,SUM(J99-V99),"") | X99: =(IF(K99>0,MIN(8,K99),"")) | Y99: =IF((K99)>8,SUM(K99-X99),"") | Z99: =VLOOKUP(A99,#REF!,5,FALSE) -> #REF! | AA99: =VLOOKUP(A99,#REF!,6,FALSE) -> #REF! | AB99: =IFERROR(VLOOKUP(A99,Table13[[#Headers],[#Data]],7,FALSE),0) -> 0 | AC99: =SUM(Z99:AB99) -> #REF! | AD99: =Z99*C99 -> #REF! | AE99: =AA99*C99*1.5 -> #REF! | AF99: =AB99*C99*2 -> 0 | AG99: =AD99+AE99+AF99 -> #REF! | AQ99: =AO99+AC99-AP99 -> #REF!
A100: MENDOZA, CONSUELO SOLIS | B100: Electrician | C100: =VLOOKUP('6001 1st'!$B100,Table6[],2,FALSE) -> 150 | L100: =(IF(E100>0,MIN(8,E100),"")) | M100: =IF((E100)>8,SUM(E100-L100),"") | N100: =(IF(F100>0,MIN(8,F100),"")) | O100: =IF((F100)>8,SUM(F100-N100),"") | P100: =(IF(G100>0,MIN(8,G100),"")) | Q100: =IF((G100)>8,SUM(G100-P100),"") | R100: =(IF(H100>0,MIN(8,H100),"")) | S100: =IF((H100)>8,SUM(H100-R100),"") | T100: =(IF(I100>0,MIN(8,I100),"")) | U100: =IF((I100)>8,SUM(I100-T100),"") | V100: =(IF(J100>0,MIN(8,J100),"")) | W100: =IF((J100)>8,SUM(J100-V100),"") | X100: =(IF(K100>0,MIN(8,K100),"")) | Y100: =IF((K100)>8,SUM(K100-X100),"") | Z100: =VLOOKUP(A100,#REF!,5,FALSE) -> #REF! | AA100: =VLOOKUP(A100,#REF!,6,FALSE) -> #REF! | AB100: =IFERROR(VLOOKUP(A100,Table13[[#Headers],[#Data]],7,FALSE),0) -> 0 | AC100: =SUM(Z100:AB100) -> #REF! | AD100: =Z100*C100 -> #REF! | AE100: =AA100*C100*1.5 -> #REF! | AF100: =AB100*C100*2 -> 0 | AG100: =AD100+AE100+AF100 -> #REF! | AQ100: =AO100+AC100-AP100 -> #REF!
A101: MENDOZA, YANETH PENA | B101: Electrician | C101: =VLOOKUP('6001 1st'!$B101,Table6[],2,FALSE) -> 150 | L101: =(IF(E101>0,MIN(8,E101),"")) | M101: =IF((E101)>8,SUM(E101-L101),"") | N101: =(IF(F101>0,MIN(8,F101),"")) | O101: =IF((F101)>8,SUM(F101-N101),"") | P101: =(IF(G101>0,MIN(8,G101),"")) | Q101: =IF((G101)>8,SUM(G101-P101),"") | R101: =(IF(H101>0,MIN(8,H101),"")) | S101: =IF((H101)>8,SUM(H101-R101),"") | T101: =(IF(I101>0,MIN(8,I101),"")) | U101: =IF((I101)>8,SUM(I101-T101),"") | V101: =(IF(J101>0,MIN(8,J101),"")) | W101: =IF((J101)>8,SUM(J101-V101),"") | X101: =(IF(K101>0,MIN(8,K101),"")) | Y101: =IF((K101)>8,SUM(K101-X101),"") | Z101: =VLOOKUP(A101,#REF!,5,FALSE) -> #REF! | AA101: =VLOOKUP(A101,#REF!,6,FALSE) -> #REF! | AB101: =IFERROR(VLOOKUP(A101,Table13[[#Headers],[#Data]],7,FALSE),0) -> 0 | AC101: =SUM(Z101:AB101) -> #REF! | AD101: =Z101*C101 -> #REF! | AE101: =AA101*C101*1.5 -> #REF! | AF101: =AB101*C101*2 -> 0 | AG101: =AD101+AE101+AF101 -> #REF! | AQ101: =AO101+AC101-AP101 -> #REF!
A102: MEREGILDO, BAYRON | B102: Electrician | C102: =VLOOKUP('6001 1st'!$B102,Table6[],2,FALSE) -> 150 | L102: =(IF(E102>0,MIN(8,E102),"")) | M102: =IF((E102)>8,SUM(E102-L102),"") | N102: =(IF(F102>0,MIN(8,F102),"")) | O102: =IF((F102)>8,SUM(F102-N102),"") | P102: =(IF(G102>0,MIN(8,G102),"")) | Q102: =IF((G102)>8,SUM(G102-P102),"") | R102: =(IF(H102>0,MIN(8,H102),"")) | S102: =IF((H102)>8,SUM(H102-R102),"") | T102: =(IF(I102>0,MIN(8,I102),"")) | U102: =IF((I102)>8,SUM(I102-T102),"") | V102: =(IF(J102>0,MIN(8,J102),"")) | W102: =IF((J102)>8,SUM(J102-V102),"") | X102: =(IF(K102>0,MIN(8,K102),"")) | Y102: =IF((K102)>8,SUM(K102-X102),"") | Z102: =VLOOKUP(A102,#REF!,5,FALSE) -> #REF! | AA102: =VLOOKUP(A102,#REF!,6,FALSE) -> #REF! | AB102: =IFERROR(VLOOKUP(A102,Table13[[#Headers],[#Data]],7,FALSE),0) -> 0 | AC102: =SUM(Z102:AB102) -> #REF! | AD102: =Z102*C102 -> #REF! | AE102: =AA102*C102*1.5 -> #REF! | AF102: =AB102*C102*2 -> 0 | AG102: =AD102+AE102+AF102 -> #REF! | AQ102: =AO102+AC102-AP102 -> #REF!
A103: MEREZ, JESUS PALOMINO | B103: Electrician | C103: =VLOOKUP('6001 1st'!$B103,Table6[],2,FALSE) -> 150 | L103: =(IF(E103>0,MIN(8,E103),"")) | M103: =IF((E103)>8,SUM(E103-L103),"") | N103: =(IF(F103>0,MIN(8,F103),"")) | O103: =IF((F103)>8,SUM(F103-N103),"") | P103: =(IF(G103>0,MIN(8,G103),"")) | Q103: =IF((G103)>8,SUM(G103-P103),"") | R103: =(IF(H103>0,MIN(8,H103),"")) | S103: =IF((H103)>8,SUM(H103-R103),"") | T103: =(IF(I103>0,MIN(8,I103),"")) | U103: =IF((I103)>8,SUM(I103-T103),"") | V103: =(IF(J103>0,MIN(8,J103),"")) | W103: =IF((J103)>8,SUM(J103-V103),"") | X103: =(IF(K103>0,MIN(8,K103),"")) | Y103: =IF((K103)>8,SUM(K103-X103),"") | Z103: =VLOOKUP(A103,#REF!,5,FALSE) -> #REF! | AA103: =VLOOKUP(A103,#REF!,6,FALSE) -> #REF! | AB103: =IFERROR(VLOOKUP(A103,Table13[[#Headers],[#Data]],7,FALSE),0) -> 0 | AC103: =SUM(Z103:AB103) -> #REF! | AD103: =Z103*C103 -> #REF! | AE103: =AA103*C103*1.5 -> #REF! | AF103: =AB103*C103*2 -> 0 | AG103: =AD103+AE103+AF103 -> #REF! | AQ103: =AO103+AC103-AP103 -> #REF!
A104: MESA, MAIKEL SILIO | B104: Electrician | C104: =VLOOKUP('6001 1st'!$B104,Table6[],2,FALSE) -> 150 | L104: =(IF(E104>0,MIN(8,E104),"")) | M104: =IF((E104)>8,SUM(E104-L104),"") | N104: =(IF(F104>0,MIN(8,F104),"")) | O104: =IF((F104)>8,SUM(F104-N104),"") | P104: =(IF(G104>0,MIN(8,G104),"")) | Q104: =IF((G104)>8,SUM(G104-P104),"") | R104: =(IF(H104>0,MIN(8,H104),"")) | S104: =IF((H104)>8,SUM(H104-R104),"") | T104: =(IF(I104>0,MIN(8,I104),"")) | U104: =IF((I104)>8,SUM(I104-T104),"") | V104: =(IF(J104>0,MIN(8,J104),"")) | W104: =IF((J104)>8,SUM(J104-V104),"") | X104: =(IF(K104>0,MIN(8,K104),"")) | Y104: =IF((K104)>8,SUM(K104-X104),"") | Z104: =VLOOKUP(A104,#REF!,5,FALSE) -> #REF! | AA104: =VLOOKUP(A104,#REF!,6,FALSE) -> #REF! | AB104: =IFERROR(VLOOKUP(A104,Table13[[#Headers],[#Data]],7,FALSE),0) -> 0 | AC104: =SUM(Z104:AB104) -> #REF! | AD104: =Z104*C104 -> #REF! | AE104: =AA104*C104*1.5 -> #REF! | AF104: =AB104*C104*2 -> 0 | AG104: =AD104+AE104+AF104 -> #REF!
A105: MEZA, JHAN GALINDEZ | B105: Electrician | C105: =VLOOKUP('6001 1st'!$B105,Table6[],2,FALSE) -> 150 | L105: =(IF(E105>0,MIN(8,E105),"")) | M105: =IF((E105)>8,SUM(E105-L105),"") | N105: =(IF(F105>0,MIN(8,F105),"")) | O105: =IF((F105)>8,SUM(F105-N105),"") | P105: =(IF(G105>0,MIN(8,G105),"")) | Q105: =IF((G105)>8,SUM(G105-P105),"") | R105: =(IF(H105>0,MIN(8,H105),"")) | S105: =IF((H105)>8,SUM(H105-R105),"") | T105: =(IF(I105>0,MIN(8,I105),"")) | U105: =IF((I105)>8,SUM(I105-T105),"") | V105: =(IF(J105>0,MIN(8,J105),"")) | W105: =IF((J105)>8,SUM(J105-V105),"") | X105: =(IF(K105>0,MIN(8,K105),"")) | Y105: =IF((K105)>8,SUM(K105-X105),"") | Z105: =VLOOKUP(A105,#REF!,5,FALSE) -> #REF! | AA105: =VLOOKUP(A105,#REF!,6,FALSE) -> #REF! | AB105: =IFERROR(VLOOKUP(A105,Table13[[#Headers],[#Data]],7,FALSE),0) -> 0 | AC105: =SUM(Z105:AB105) -> #REF! | AD105: =Z105*C105 -> #REF! | AE105: =AA105*C105*1.5 -> #REF! | AF105: =AB105*C105*2 -> 0 | AG105: =AD105+AE105+AF105 -> #REF!
A106: MILLA, JOSE RODRIGUEZ | B106: Electrician | C106: =VLOOKUP('6001 1st'!$B106,Table6[],2,FALSE) -> 150 | L106: =(IF(E106>0,MIN(8,E106),"")) | M106: =IF((E106)>8,SUM(E106-L106),"") | N106: =(IF(F106>0,MIN(8,F106),"")) | O106: =IF((F106)>8,SUM(F106-N106),"") | P106: =(IF(G106>0,MIN(8,G106),"")) | Q106: =IF((G106)>8,SUM(G106-P106),"") | R106: =(IF(H106>0,MIN(8,H106),"")) | S106: =IF((H106)>8,SUM(H106-R106),"") | T106: =(IF(I106>0,MIN(8,I106),"")) | U106: =IF((I106)>8,SUM(I106-T106),"") | V106: =(IF(J106>0,MIN(8,J106),"")) | W106: =IF((J106)>8,SUM(J106-V106),"") | X106: =(IF(K106>0,MIN(8,K106),"")) | Y106: =IF((K106)>8,SUM(K106-X106),"") | Z106: =VLOOKUP(A106,#REF!,5,FALSE) -> #REF! | AA106: =VLOOKUP(A106,#REF!,6,FALSE) -> #REF! | AB106: =IFERROR(VLOOKUP(A106,Table13[[#Headers],[#Data]],7,FALSE),0) -> 0 | AC106: =SUM(Z106:AB106) -> #REF! | AD106: =Z106*C106 -> #REF! | AE106: =AA106*C106*1.5 -> #REF! | AF106: =AB106*C106*2 -> 0 | AG106: =AD106+AE106+AF106 -> #REF!
A107: MOBLEY, DEMETRIUS | B107: Electrician | C107: =VLOOKUP('6001 1st'!$B107,Table6[],2,FALSE) -> 150 | L107: =(IF(E107>0,MIN(8,E107),"")) | M107: =IF((E107)>8,SUM(E107-L107),"") | N107: =(IF(F107>0,MIN(8,F107),"")) | O107: =IF((F107)>8,SUM(F107-N107),"") | P107: =(IF(G107>0,MIN(8,G107),"")) | Q107: =IF((G107)>8,SUM(G107-P107),"") | R107: =(IF(H107>0,MIN(8,H107),"")) | S107: =IF((H107)>8,SUM(H107-R107),"") | T107: =(IF(I107>0,MIN(8,I107),"")) | U107: =IF((I107)>8,SUM(I107-T107),"") | V107: =(IF(J107>0,MIN(8,J107),"")) | W107: =IF((J107)>8,SUM(J107-V107),"") | X107: =(IF(K107>0,MIN(8,K107),"")) | Y107: =IF((K107)>8,SUM(K107-X107),"") | Z107: =VLOOKUP(A107,#REF!,5,FALSE) -> #REF! | AA107: =VLOOKUP(A107,#REF!,6,FALSE) -> #REF! | AB107: =IFERROR(VLOOKUP(A107,Table13[[#Headers],[#Data]],7,FALSE),0) -> 0 | AC107: =SUM(Z107:AB107) -> #REF! | AD107: =Z107*C107 -> #REF! | AE107: =AA107*C107*1.5 -> #REF! | AF107: =AB107*C107*2 -> 0 | AG107: =AD107+AE107+AF107 -> #REF!
A108: MOLINA, LUIS CHACON | B108: Electrician | C108: =VLOOKUP('6001 1st'!$B108,Table6[],2,FALSE) -> 150 | L108: =(IF(E108>0,MIN(8,E108),"")) | M108: =IF((E108)>8,SUM(E108-L108),"") | N108: =(IF(F108>0,MIN(8,F108),"")) | O108: =IF((F108)>8,SUM(F108-N108),"") | P108: =(IF(G108>0,MIN(8,G108),"")) | Q108: =IF((G108)>8,SUM(G108-P108),"") | R108: =(IF(H108>0,MIN(8,H108),"")) | S108: =IF((H108)>8,SUM(H108-R108),"") | T108: =(IF(I108>0,MIN(8,I108),"")) | U108: =IF((I108)>8,SUM(I108-T108),"") | V108: =(IF(J108>0,MIN(8,J108),"")) | W108: =IF((J108)>8,SUM(J108-V108),"") | X108: =(IF(K108>0,MIN(8,K108),"")) | Y108: =IF((K108)>8,SUM(K108-X108),"") | Z108: =VLOOKUP(A108,#REF!,5,FALSE) -> #REF! | AA108: =VLOOKUP(A108,#REF!,6,FALSE) -> #REF! | AB108: =IFERROR(VLOOKUP(A108,Table13[[#Headers],[#Data]],7,FALSE),0) -> 0 | AC108: =SUM(Z108:AB108) -> #REF! | AD108: =Z108*C108 -> #REF! | AE108: =AA108*C108*1.5 -> #REF! | AF108: =AB108*C108*2 -> 0 | AG108: =AD108+AE108+AF108 -> #REF!
A109: MOTA, JOSE GONZALEZ | B109: Electrician | C109: =VLOOKUP('6001 1st'!$B109,Table6[],2,FALSE) -> 150 | L109: =(IF(E109>0,MIN(8,E109),"")) | M109: =IF((E109)>8,SUM(E109-L109),"") | N109: =(IF(F109>0,MIN(8,F109),"")) | O109: =IF((F109)>8,SUM(F109-N109),"") | P109: =(IF(G109>0,MIN(8,G109),"")) | Q109: =IF((G109)>8,SUM(G109-P109),"") | R109: =(IF(H109>0,MIN(8,H109),"")) | S109: =IF((H109)>8,SUM(H109-R109),"") | T109: =(IF(I109>0,MIN(8,I109),"")) | U109: =IF((I109)>8,SUM(I109-T109),"") | V109: =(IF(J109>0,MIN(8,J109),"")) | W109: =IF((J109)>8,SUM(J109-V109),"") | X109: =(IF(K109>0,MIN(8,K109),"")) | Y109: =IF((K109)>8,SUM(K109-X109),"") | Z109: =VLOOKUP(A109,#REF!,5,FALSE) -> #REF! | AA109: =VLOOKUP(A109,#REF!,6,FALSE) -> #REF! | AB109: =IFERROR(VLOOKUP(A109,Table13[[#Headers],[#Data]],7,FALSE),0) -> 0 | AC109: =SUM(Z109:AB109) -> #REF! | AD109: =Z109*C109 -> #REF! | AE109: =AA109*C109*1.5 -> #REF! | AF109: =AB109*C109*2 -> 0 | AG109: =AD109+AE109+AF109 -> #REF!
A110: NEGRETTE, LUIJIN | B110: Electrician | C110: =VLOOKUP('6001 1st'!$B110,Table6[],2,FALSE) -> 150 | L110: =(IF(E110>0,MIN(8,E110),"")) | M110: =IF((E110)>8,SUM(E110-L110),"") | N110: =(IF(F110>0,MIN(8,F110),"")) | O110: =IF((F110)>8,SUM(F110-N110),"") | P110: =(IF(G110>0,MIN(8,G110),"")) | Q110: =IF((G110)>8,SUM(G110-P110),"") | R110: =(IF(H110>0,MIN(8,H110),"")) | S110: =IF((H110)>8,SUM(H110-R110),"") | T110: =(IF(I110>0,MIN(8,I110),"")) | U110: =IF((I110)>8,SUM(I110-T110),"") | V110: =(IF(J110>0,MIN(8,J110),"")) | W110: =IF((J110)>8,SUM(J110-V110),"") | X110: =(IF(K110>0,MIN(8,K110),"")) | Y110: =IF((K110)>8,SUM(K110-X110),"") | Z110: =VLOOKUP(A110,#REF!,5,FALSE) -> #REF! | AA110: =VLOOKUP(A110,#REF!,6,FALSE) -> #REF! | AB110: =IFERROR(VLOOKUP(A110,Table13[[#Headers],[#Data]],7,FALSE),0) -> 0 | AC110: =SUM(Z110:AB110) -> #REF! | AD110: =Z110*C110 -> #REF! | AE110: =AA110*C110*1.5 -> #REF! | AF110: =AB110*C110*2 -> 0 | AG110: =AD110+AE110+AF110 -> #REF!
A111: OBANDO, WALTER A ACEVEO | B111: Electrician | C111: =VLOOKUP('6001 1st'!$B111,Table6[],2,FALSE) -> 150 | L111: =(IF(E111>0,MIN(8,E111),"")) | M111: =IF((E111)>8,SUM(E111-L111),"") | N111: =(IF(F111>0,MIN(8,F111),"")) | O111: =IF((F111)>8,SUM(F111-N111),"") | P111: =(IF(G111>0,MIN(8,G111),"")) | Q111: =IF((G111)>8,SUM(G111-P111),"") | R111: =(IF(H111>0,MIN(8,H111),"")) | S111: =IF((H111)>8,SUM(H111-R111),"") | T111: =(IF(I111>0,MIN(8,I111),"")) | U111: =IF((I111)>8,SUM(I111-T111),"") | V111: =(IF(J111>0,MIN(8,J111),"")) | W111: =IF((J111)>8,SUM(J111-V111),"") | X111: =(IF(K111>0,MIN(8,K111),"")) | Y111: =IF((K111)>8,SUM(K111-X111),"") | Z111: =VLOOKUP(A111,#REF!,5,FALSE) -> #REF! | AA111: =VLOOKUP(A111,#REF!,6,FALSE) -> #REF! | AB111: =IFERROR(VLOOKUP(A111,Table13[[#Headers],[#Data]],7,FALSE),0) -> 0 | AC111: =SUM(Z111:AB111) -> #REF! | AD111: =Z111*C111 -> #REF! | AE111: =AA111*C111*1.5 -> #REF! | AF111: =AB111*C111*2 -> 0 | AG111: =AD111+AE111+AF111 -> #REF!
A112: OLIVAS, CARLOS | B112: Electrician | C112: =VLOOKUP('6001 1st'!$B112,Table6[],2,FALSE) -> 150 | Z112: =VLOOKUP(A112,#REF!,5,FALSE) -> #REF! | AA112: =VLOOKUP(A112,#REF!,6,FALSE) -> #REF! | AB112: =IFERROR(VLOOKUP(A112,Table13[[#Headers],[#Data]],7,FALSE),0) -> 0 | AC112: =SUM(Z112:AB112) -> #REF! | AD112: =Z112*C112 -> #REF! | AE112: =AA112*C112*1.5 -> #REF! | AF112: =AB112*C112*2 -> 0 | AG112: =AD112+AE112+AF112 -> #REF!
A113: ORDONEZ, SELENA D CENTENO | B113: Electrician | C113: =VLOOKUP('6001 1st'!$B113,Table6[],2,FALSE) -> 150 | Z113: =VLOOKUP(A113,#REF!,5,FALSE) -> #REF! | AA113: =VLOOKUP(A113,#REF!,6,FALSE) -> #REF! | AB113: =IFERROR(VLOOKUP(A113,Table13[[#Headers],[#Data]],7,FALSE),0) -> 0 | AC113: =SUM(Z113:AB113) -> #REF! | AD113: =Z113*C113 -> #REF! | AE113: =AA113*C113*1.5 -> #REF! | AF113: =AB113*C113*2 -> 0 | AG113: =AD113+AE113+AF113 -> #REF!
A114: ORELLANA, BRYAND BELIZ | B114: Electrician | C114: =VLOOKUP('6001 1st'!$B114,Table6[],2,FALSE) -> 150 | Z114: =VLOOKUP(A114,#REF!,5,FALSE) -> #REF! | AA114: =VLOOKUP(A114,#REF!,6,FALSE) -> #REF! | AB114: =IFERROR(VLOOKUP(A114,Table13[[#Headers],[#Data]],7,FALSE),0) -> 0 | AC114: =SUM(Z114:AB114) -> #REF! | AD114: =Z114*C114 -> #REF! | AE114: =AA114*C114*1.5 -> #REF! | AF114: =AB114*C114*2 -> 0 | AG114: =AD114+AE114+AF114 -> #REF!
A115: ORTIZ, JOSE ANGEL FELICIANO | B115: Electrician | C115: =VLOOKUP('6001 1st'!$B115,Table6[],2,FALSE) -> 150 | Z115: =VLOOKUP(A115,#REF!,5,FALSE) -> #REF! | AA115: =VLOOKUP(A115,#REF!,6,FALSE) -> #REF! | AB115: =IFERROR(VLOOKUP(A115,Table13[[#Headers],[#Data]],7,FALSE),0) -> 0 | AC115: =SUM(Z115:AB115) -> #REF! | AD115: =Z115*C115 -> #REF! | AE115: =AA115*C115*1.5 -> #REF! | AF115: =AB115*C115*2 -> 0 | AG115: =AD115+AE115+AF115 -> #REF!
A116: PALMAR, LUIS A. LABARCA | B116: Electrician | C116: =VLOOKUP('6001 1st'!$B116,Table6[],2,FALSE) -> 150 | Z116: =VLOOKUP(A116,#REF!,5,FALSE) -> #REF! | AA116: =VLOOKUP(A116,#REF!,6,FALSE) -> #REF! | AB116: =IFERROR(VLOOKUP(A116,Table13[[#Headers],[#Data]],7,FALSE),0) -> 0 | AC116: =SUM(Z116:AB116) -> #REF! | AD116: =Z116*C116 -> #REF! | AE116: =AA116*C116*1.5 -> #REF! | AF116: =AB116*C116*2 -> 0 | AG116: =AD116+AE116+AF116 -> #REF!
A117: PARRA, ANGEL | B117: Electrician | C117: =VLOOKUP('6001 1st'!$B117,Table6[],2,FALSE) -> 150 | L117: =(IF(E117>0,MIN(8,E117),"")) | M117: =IF((E117)>8,SUM(E117-L117),"") | N117: =(IF(F117>0,MIN(8,F117),"")) | O117: =IF((F117)>8,SUM(F117-N117),"") | P117: =(IF(G117>0,MIN(8,G117),"")) | Q117: =IF((G117)>8,SUM(G117-P117),"") | R117: =(IF(H117>0,MIN(8,H117),"")) | S117: =IF((H117)>8,SUM(H117-R117),"") | T117: =(IF(I117>0,MIN(8,I117),"")) | U117: =IF((I117)>8,SUM(I117-T117),"") | V117: =(IF(J117>0,MIN(8,J117),"")) | W117: =IF((J117)>8,SUM(J117-V117),"") | X117: =(IF(K117>0,MIN(8,K117),"")) | Y117: =IF((K117)>8,SUM(K117-X117),"") | Z117: =VLOOKUP(A117,#REF!,5,FALSE) -> #REF! | AA117: =VLOOKUP(A117,#REF!,6,FALSE) -> #REF! | AB117: =IFERROR(VLOOKUP(A117,Table13[[#Headers],[#Data]],7,FALSE),0) -> 0 | AC117: =SUM(Z117:AB117) -> #REF! | AD117: =Z117*C117 -> #REF! | AE117: =AA117*C117*1.5 -> #REF! | AF117: =AB117*C117*2 -> 0 | AG117: =AD117+AE117+AF117 -> #REF!
A118: PERDOMO, FELIX OMAR SEPULVEDA | B118: Electrician | C118: =VLOOKUP('6001 1st'!$B118,Table6[],2,FALSE) -> 150 | L118: =(IF(E118>0,MIN(8,E118),"")) | M118: =IF((E118)>8,SUM(E118-L118),"") | N118: =(IF(F118>0,MIN(8,F118),"")) | O118: =IF((F118)>8,SUM(F118-N118),"") | P118: =(IF(G118>0,MIN(8,G118),"")) | Q118: =IF((G118)>8,SUM(G118-P118),"") | R118: =(IF(H118>0,MIN(8,H118),"")) | S118: =IF((H118)>8,SUM(H118-R118),"") | T118: =(IF(I118>0,MIN(8,I118),"")) | U118: =IF((I118)>8,SUM(I118-T118),"") | V118: =(IF(J118>0,MIN(8,J118),"")) | W118: =IF((J118)>8,SUM(J118-V118),"") | X118: =(IF(K118>0,MIN(8,K118),"")) | Y118: =IF((K118)>8,SUM(K118-X118),"") | Z118: =VLOOKUP(A118,#REF!,5,FALSE) -> #REF! | AA118: =VLOOKUP(A118,#REF!,6,FALSE) -> #REF! | AB118: =IFERROR(VLOOKUP(A118,Table13[[#Headers],[#Data]],7,FALSE),0) -> 0 | AC118: =SUM(Z118:AB118) -> #REF! | AD118: =Z118*C118 -> #REF! | AE118: =AA118*C118*1.5 -> #REF! | AF118: =AB118*C118*2 -> 0 | AG118: =AD118+AE118+AF118 -> #REF!
...

Sheet 6002 2nd
A1: 6002 Original ROM TM Labor 2nd Shift | C1: 0 | AO1: on 7.18 payroll previously billed | AP1: will hit 8.1.25 payroll
A2: INPWR INVOICE NUMBER | B2: ='INVOICE COVER 7256'!F3 -> 25108-09
A3: CUSTOMER REFERENCE | B3: ='INVOICE COVER 7256'!D5 -> 7256
A4: JOB NAME | B4: ='INVOICE COVER 7256'!C5 -> Marble NC
A5: JOB NUMBER | B5: ='INVOICE COVER 7256'!E5 -> 25108
A6: Period Ending Week-ending 8.10.25 Thru | B6: ='INVOICE COVER 7256'!F5 -> 45942
A7: EMPLOYEE NAME | B7: CLASS | C7: REGULAR | D7: Per Diem | E7: PER DAY | L7: =B6-6 -> 45936 | N7: =B6-5 -> 45937 | P7: =B6-4 -> 45938 | R7: =B6-3 -> 45939 | T7: =B6-2 -> 45940 | V7: =B6-1 -> 45941 | X7: =B6 -> 45942 | Z7: REG | AA7: OT | AB7: DT | AC7: Total | AD7: ST. LABOR | AE7: OT LABOR | AF7: DT LABOR | AG7: LABOR
C8: RATE | D8: Y/N | E8: =B6-6 -> 45936 | F8: =E8+1 -> 45937 | G8: =F8+1 -> 45938 | H8: =G8+1 -> 45939 | I8: =H8+1 -> 45940 | J8: =I8+1 -> 45941 | K8: =J8+1 -> 45942 | L8: REG. | M8: OT | N8: REG. | O8: OT | P8: REG | Q8: OT | R8: REG | S8: OT | T8: REG | U8: OT | V8: REG | W8: OT | X8: REG | Y8: OT | Z8: TOT | AA8: TOT | AB8: Hours | AC8: Hours | AD8: TOTAL | AE8: TOTAL | AF8: TOTAL | AG8: TOTAL
A9: MUBIN, NASIR | B9: QA/QC | C9: =VLOOKUP('6002 2nd'!$B9,Table6[],2,FALSE)+15 -> 180 | D9: 0 | E9: 0 | F9: 0 | G9: 0 | H9: 0 | I9: 0 | J9: 0 | K9: 0 | L9: =(IF(E9>0,MIN(8,E9),"")) | M9: =IF((E9)>8,SUM(E9-L9),"") | N9: =(IF(F9>0,MIN(8,F9),"")) | O9: =IF((F9)>8,SUM(F9-N9),"") | P9: =(IF(G9>0,MIN(8,G9),"")) | Q9: =IF((G9)>8,SUM(G9-P9),"") | R9: =(IF(H9>0,MIN(8,H9),"")) | S9: =IF((H9)>8,SUM(H9-R9),"") | T9: =(IF(I9>0,MIN(8,I9),"")) | U9: =IF((I9)>8,SUM(I9-T9),"") | V9: =(IF(J9>0,MIN(8,J9),"")) | W9: =IF((J9)>8,SUM(J9-V9),"") | X9: =(IF(K9>0,MIN(8,K9),"")) | Y9: =IF((K9)>8,SUM(K9-X9),"") | Z9: =VLOOKUP(A9,#REF!,7,FALSE) -> #REF! | AA9: =VLOOKUP(A9,#REF!,8,FALSE) -> #REF! | AB9: =IFERROR(VLOOKUP(A9,Table13[[#Headers],[#Data]],7,FALSE),0) -> 0 | AC9: =SUM(Z9:AB9) -> #REF! | AD9: =Z9*C9 -> #REF! | AE9: =AA9*C9*1.5 -> #REF! | AF9: =AB9*C9*2 -> 0 | AG9: =AD9+AE9+AF9 -> #REF!
A10: ACERO, MAURICIO | B10: Electrician | C10: =VLOOKUP('6002 2nd'!$B10,Table6[],2,FALSE)+15 -> 165 | D10: 0 | E10: 0 | F10: 0 | G10: 0 | H10: 0 | I10: 0 | J10: 0 | K10: 0 | L10: 0 | M10: 0 | N10: 0 | O10: 0 | P10: 0 | Q10: 0 | R10: 0 | S10: 0 | T10: 0 | U10: 0 | V10: 0 | W10: 0 | X10: 0 | Y10: 0 | Z10: =VLOOKUP(A10,#REF!,7,FALSE) -> #REF! | AA10: =VLOOKUP(A10,#REF!,8,FALSE) -> #REF! | AB10: =IFERROR(VLOOKUP(A10,Table13[[#Headers],[#Data]],7,FALSE),0) -> 0 | AC10: =SUM(Z10:AB10) -> #REF! | AD10: =Z10*C10 -> #REF! | AE10: =AA10*C10*1.5 -> #REF! | AF10: =AB10*C10*2 -> 0 | AG10: =AD10+AE10+AF10 -> #REF!
A11: AGUERO, JONATHAN | B11: Electrician | C11: =VLOOKUP('6002 2nd'!$B11,Table6[],2,FALSE)+15 -> 165 | D11: 0 | E11: 0 | F11: 0 | G11: 0 | H11: 0 | I11: 0 | J11: 0 | K11: 0 | L11: =(IF(E11>0,MIN(8,E11),"")) | M11: =IF((E11)>8,SUM(E11-L11),"") | N11: =(IF(F11>0,MIN(8,F11),"")) | O11: =IF((F11)>8,SUM(F11-N11),"") | P11: =(IF(G11>0,MIN(8,G11),"")) | Q11: =IF((G11)>8,SUM(G11-P11),"") | R11: =(IF(H11>0,MIN(8,H11),"")) | S11: =IF((H11)>8,SUM(H11-R11),"") | T11: =(IF(I11>0,MIN(8,I11),"")) | U11: =IF((I11)>8,SUM(I11-T11),"") | V11: =(IF(J11>0,MIN(8,J11),"")) | W11: =IF((J11)>8,SUM(J11-V11),"") | X11: =(IF(K11>0,MIN(8,K11),"")) | Y11: =IF((K11)>8,SUM(K11-X11),"") | Z11: =VLOOKUP(A11,#REF!,7,FALSE) -> #REF! | AA11: =VLOOKUP(A11,#REF!,8,FALSE) -> #REF! | AB11: =IFERROR(VLOOKUP(A11,Table13[[#Headers],[#Data]],7,FALSE),0) -> 0 | AC11: =SUM(Z11:AB11) -> #REF! | AD11: =Z11*C11 -> #REF! | AE11: =AA11*C11*1.5 -> #REF! | AF11: =AB11*C11*2 -> 0 | AG11: =AD11+AE11+AF11 -> #REF!
A12: ASHCRAFT, JOHN | B12: Electrician | C12: =VLOOKUP('6002 2nd'!$B12,Table6[],2,FALSE)+15 -> 165 | D12: Y | E12: 0 | F12: 0 | G12: 0 | H12: 0 | I12: 0 | J12: 0 | K12: 0 | L12: =(IF(E12>0,MIN(8,E12),"")) | M12: =IF((E12)>8,SUM(E12-L12),"") | N12: =(IF(F12>0,MIN(8,F12),"")) | O12: =IF((F12)>8,SUM(F12-N12),"") | P12: =(IF(G12>0,MIN(8,G12),"")) | Q12: =IF((G12)>8,SUM(G12-P12),"") | R12: =(IF(H12>0,MIN(8,H12),"")) | S12: =IF((H12)>8,SUM(H12-R12),"") | T12: =(IF(I12>0,MIN(8,I12),"")) | U12: =IF((I12)>8,SUM(I12-T12),"") | V12: =(IF(J12>0,MIN(8,J12),"")) | W12: =IF((J12)>8,SUM(J12-V12),"") | X12: =(IF(K12>0,MIN(8,K12),"")) | Y12: =IF((K12)>8,SUM(K12-X12),"") | Z12: =VLOOKUP(A12,#REF!,7,FALSE) -> #REF! | AA12: =VLOOKUP(A12,#REF!,8,FALSE) -> #REF! | AB12: =IFERROR(VLOOKUP(A12,Table13[[#Headers],[#Data]],7,FALSE),0) -> 0 | AC12: =SUM(Z12:AB12) -> #REF! | AD12: =Z12*C12 -> #REF! | AE12: =AA12*C12*1.5 -> #REF! | AF12: =AB12*C12*2 -> 0 | AG12: =AD12+AE12+AF12 -> #REF!
A13: ARROYO, JESUS MACIAS | B13: Electrician | C13: =VLOOKUP('6002 2nd'!$B13,Table6[],2,FALSE)+15 -> 165 | D13: 0 | E13: 0 | F13: 0 | G13: 0 | H13: 0 | I13: 0 | J13: 0 | K13: 0 | L13: =(IF(E13>0,MIN(8,E13),"")) | M13: =IF((E13)>8,SUM(E13-L13),"") | N13: =(IF(F13>0,MIN(8,F13),"")) | O13: =IF((F13)>8,SUM(F13-N13),"") | P13: =(IF(G13>0,MIN(8,G13),"")) | Q13: =IF((G13)>8,SUM(G13-P13),"") | R13: =(IF(H13>0,MIN(8,H13),"")) | S13: =IF((H13)>8,SUM(H13-R13),"") | T13: =(IF(I13>0,MIN(8,I13),"")) | U13: =IF((I13)>8,SUM(I13-T13),"") | V13: =(IF(J13>0,MIN(8,J13),"")) | W13: =IF((J13)>8,SUM(J13-V13),"") | X13: =(IF(K13>0,MIN(8,K13),"")) | Y13: =IF((K13)>8,SUM(K13-X13),"") | Z13: =VLOOKUP(A13,#REF!,7,FALSE) -> #REF! | AA13: =VLOOKUP(A13,#REF!,8,FALSE) -> #REF! | AB13: =IFERROR(VLOOKUP(A13,Table13[[#Headers],[#Data]],7,FALSE),0) -> 0 | AC13: =SUM(Z13:AB13) -> #REF! | AD13: =Z13*C13 -> #REF! | AE13: =AA13*C13*1.5 -> #REF! | AF13: =AB13*C13*2 -> 0 | AG13: =AD13+AE13+AF13 -> #REF!
A14: AVILEZ, IVAN OMAR CASTILLO | B14: Electrician | C14: =VLOOKUP('6002 2nd'!$B14,Table6[],2,FALSE)+15 -> 165 | D14: 0 | E14: 0 | F14: 0 | G14: 0 | H14: 0 | I14: 0 | J14: 0 | K14: 0 | L14: =(IF(E14>0,MIN(8,E14),"")) | M14: =IF((E14)>8,SUM(E14-L14),"") | N14: =(IF(F14>0,MIN(8,F14),"")) | O14: =IF((F14)>8,SUM(F14-N14),"") | P14: =(IF(G14>0,MIN(8,G14),"")) | Q14: =IF((G14)>8,SUM(G14-P14),"") | R14: =(IF(H14>0,MIN(8,H14),"")) | S14: =IF((H14)>8,SUM(H14-R14),"") | T14: =(IF(I14>0,MIN(8,I14),"")) | U14: =IF((I14)>8,SUM(I14-T14),"") | V14: =(IF(J14>0,MIN(8,J14),"")) | W14: =IF((J14)>8,SUM(J14-V14),"") | X14: =(IF(K14>0,MIN(8,K14),"")) | Y14: =IF((K14)>8,SUM(K14-X14),"") | Z14: =VLOOKUP(A14,#REF!,7,FALSE) -> #REF! | AA14: =VLOOKUP(A14,#REF!,8,FALSE) -> #REF! | AB14: =IFERROR(VLOOKUP(A14,Table13[[#Headers],[#Data]],7,FALSE),0) -> 0 | AC14: =SUM(Z14:AB14) -> #REF! | AD14: =Z14*C14 -> #REF! | AE14: =AA14*C14*1.5 -> #REF! | AF14: =AB14*C14*2 -> 0 | AG14: =AD14+AE14+AF14 -> #REF!
A15: BARRIOS, ANDRES | B15: Electrician | C15: =VLOOKUP('6002 2nd'!$B15,Table6[],2,FALSE)+15 -> 165 | D15: 0 | E15: 0 | F15: 0 | G15: 0 | H15: 0 | I15: 0 | J15: 0 | K15: 0 | L15: =(IF(E15>0,MIN(8,E15),"")) | M15: =IF((E15)>8,SUM(E15-L15),"") | N15: =(IF(F15>0,MIN(8,F15),"")) | O15: =IF((F15)>8,SUM(F15-N15),"") | P15: =(IF(G15>0,MIN(8,G15),"")) | Q15: =IF((G15)>8,SUM(G15-P15),"") | R15: =(IF(H15>0,MIN(8,H15),"")) | S15: =IF((H15)>8,SUM(H15-R15),"") | T15: =(IF(I15>0,MIN(8,I15),"")) | U15: =IF((I15)>8,SUM(I15-T15),"") | V15: =(IF(J15>0,MIN(8,J15),"")) | W15: =IF((J15)>8,SUM(J15-V15),"") | X15: =(IF(K15>0,MIN(8,K15),"")) | Y15: =IF((K15)>8,SUM(K15-X15),"") | Z15: =VLOOKUP(A15,#REF!,7,FALSE) -> #REF! | AA15: =VLOOKUP(A15,#REF!,8,FALSE) -> #REF! | AB15: =IFERROR(VLOOKUP(A15,Table13[[#Headers],[#Data]],7,FALSE),0) -> 0 | AC15: =SUM(Z15:AB15) -> #REF! | AD15: =Z15*C15 -> #REF! | AE15: =AA15*C15*1.5 -> #REF! | AF15: =AB15*C15*2 -> 0 | AG15: =AD15+AE15+AF15 -> #REF!
A16: BAUTISTA, MELVIN HERNANDEZ | B16: Electrician | C16: =VLOOKUP('6002 2nd'!$B16,Table6[],2,FALSE)+15 -> 165 | D16: 0 | E16: 0 | F16: 0 | G16: 0 | H16: 0 | I16: 0 | J16: 0 | K16: 0 | L16: =(IF(E16>0,MIN(8,E16),"")) | M16: =IF((E16)>8,SUM(E16-L16),"") | N16: =(IF(F16>0,MIN(8,F16),"")) | O16: =IF((F16)>8,SUM(F16-N16),"") | P16: =(IF(G16>0,MIN(8,G16),"")) | Q16: =IF((G16)>8,SUM(G16-P16),"") | R16: =(IF(H16>0,MIN(8,H16),"")) | S16: =IF((H16)>8,SUM(H16-R16),"") | T16: =(IF(I16>0,MIN(8,I16),"")) | U16: =IF((I16)>8,SUM(I16-T16),"") | V16: =(IF(J16>0,MIN(8,J16),"")) | W16: =IF((J16)>8,SUM(J16-V16),"") | X16: =(IF(K16>0,MIN(8,K16),"")) | Y16: =IF((K16)>8,SUM(K16-X16),"") | Z16: =VLOOKUP(A16,#REF!,7,FALSE) -> #REF! | AA16: =VLOOKUP(A16,#REF!,8,FALSE) -> #REF! | AB16: =IFERROR(VLOOKUP(A16,Table13[[#Headers],[#Data]],7,FALSE),0) -> 0 | AC16: =SUM(Z16:AB16) -> #REF! | AD16: =Z16*C16 -> #REF! | AE16: =AA16*C16*1.5 -> #REF! | AF16: =AB16*C16*2 -> 0 | AG16: =AD16+AE16+AF16 -> #REF!
A17: BLANDON, ELVIN MORENO | B17: Electrician | C17: =VLOOKUP('6002 2nd'!$B17,Table6[],2,FALSE)+15 -> 165 | D17: 0 | E17: 0 | F17: 0 | G17: 0 | H17: 0 | I17: 0 | J17: 0 | K17: 0 | L17: =(IF(E17>0,MIN(8,E17),"")) | M17: =IF((E17)>8,SUM(E17-L17),"") | N17: =(IF(F17>0,MIN(8,F17),"")) | O17: =IF((F17)>8,SUM(F17-N17),"") | P17: =(IF(G17>0,MIN(8,G17),"")) | Q17: =IF((G17)>8,SUM(G17-P17),"") | R17: =(IF(H17>0,MIN(8,H17),"")) | S17: =IF((H17)>8,SUM(H17-R17),"") | T17: =(IF(I17>0,MIN(8,I17),"")) | U17: =IF((I17)>8,SUM(I17-T17),"") | V17: =(IF(J17>0,MIN(8,J17),"")) | W17: =IF((J17)>8,SUM(J17-V17),"") | X17: =(IF(K17>0,MIN(8,K17),"")) | Y17: =IF((K17)>8,SUM(K17-X17),"") | Z17: =VLOOKUP(A17,#REF!,7,FALSE) -> #REF! | AA17: =VLOOKUP(A17,#REF!,8,FALSE) -> #REF! | AB17: =IFERROR(VLOOKUP(A17,Table13[[#Headers],[#Data]],7,FALSE),0) -> 0 | AC17: =SUM(Z17:AB17) -> #REF! | AD17: =Z17*C17 -> #REF! | AE17: =AA17*C17*1.5 -> #REF! | AF17: =AB17*C17*2 -> 0 | AG17: =AD17+AE17+AF17 -> #REF!
A18: BLANDON, OSCAR DANILO MORENO | B18: Electrician | C18: =VLOOKUP('6002 2nd'!$B18,Table6[],2,FALSE)+15 -> 165 | D18: 0 | E18: 0 | F18: 0 | G18: 0 | H18: 0 | I18: 0 | J18: 0 | K18: 0 | L18: =(IF(E18>0,MIN(8,E18),"")) | M18: =IF((E18)>8,SUM(E18-L18),"") | N18: =(IF(F18>0,MIN(8,F18),"")) | O18: =IF((F18)>8,SUM(F18-N18),"") | P18: =(IF(G18>0,MIN(8,G18),"")) | Q18: =IF((G18)>8,SUM(G18-P18),"") | R18: =(IF(H18>0,MIN(8,H18),"")) | S18: =IF((H18)>8,SUM(H18-R18),"") | T18: =(IF(I18>0,MIN(8,I18),"")) | U18: =IF((I18)>8,SUM(I18-T18),"") | V18: =(IF(J18>0,MIN(8,J18),"")) | W18: =IF((J18)>8,SUM(J18-V18),"") | X18: =(IF(K18>0,MIN(8,K18),"")) | Y18: =IF((K18)>8,SUM(K18-X18),"") | Z18: =VLOOKUP(A18,#REF!,7,FALSE) -> #REF! | AA18: =VLOOKUP(A18,#REF!,8,FALSE) -> #REF! | AB18: =IFERROR(VLOOKUP(A18,Table13[[#Headers],[#Data]],7,FALSE),0) -> 0 | AC18: =SUM(Z18:AB18) -> #REF! | AD18: =Z18*C18 -> #REF! | AE18: =AA18*C18*1.5 -> #REF! | AF18: =AB18*C18*2 -> 0 | AG18: =AD18+AE18+AF18 -> #REF!
A19: BOHORQUEZ, AUDIE CHOURIO | B19: Electrician | C19: =VLOOKUP('6002 2nd'!$B19,Table6[],2,FALSE)+15 -> 165 | D19: 0 | E19: 0 | F19: 0 | G19: 0 | H19: 0 | I19: 0 | J19: 0 | K19: 0 | L19: =(IF(E19>0,MIN(8,E19),"")) | M19: =IF((E19)>8,SUM(E19-L19),"") | N19: =(IF(F19>0,MIN(8,F19),"")) | O19: =IF((F19)>8,SUM(F19-N19),"") | P19: =(IF(G19>0,MIN(8,G19),"")) | Q19: =IF((G19)>8,SUM(G19-P19),"") | R19: =(IF(H19>0,MIN(8,H19),"")) | S19: =IF((H19)>8,SUM(H19-R19),"") | T19: =(IF(I19>0,MIN(8,I19),"")) | U19: =IF((I19)>8,SUM(I19-T19),"") | V19: =(IF(J19>0,MIN(8,J19),"")) | W19: =IF((J19)>8,SUM(J19-V19),"") | X19: =(IF(K19>0,MIN(8,K19),"")) | Y19: =IF((K19)>8,SUM(K19-X19),"") | Z19: =VLOOKUP(A19,#REF!,7,FALSE) -> #REF! | AA19: =VLOOKUP(A19,#REF!,8,FALSE) -> #REF! | AB19: =IFERROR(VLOOKUP(A19,Table13[[#Headers],[#Data]],7,FALSE),0) -> 0 | AC19: =SUM(Z19:AB19) -> #REF! | AD19: =Z19*C19 -> #REF! | AE19: =AA19*C19*1.5 -> #REF! | AF19: =AB19*C19*2 -> 0 | AG19: =AD19+AE19+AF19 -> #REF!
A20: BRAVO, JOSE BRICERNO | B20: Electrician | C20: =VLOOKUP('6002 2nd'!$B20,Table6[],2,FALSE)+15 -> 165 | D20: 0 | E20: 0 | F20: 0 | G20: 0 | H20: 0 | I20: 0 | J20: 0 | K20: 0 | L20: =(IF(E20>0,MIN(8,E20),"")) | M20: =IF((E20)>8,SUM(E20-L20),"") | N20: =(IF(F20>0,MIN(8,F20),"")) | O20: =IF((F20)>8,SUM(F20-N20),"") | P20: =(IF(G20>0,MIN(8,G20),"")) | Q20: =IF((G20)>8,SUM(G20-P20),"") | R20: =(IF(H20>0,MIN(8,H20),"")) | S20: =IF((H20)>8,SUM(H20-R20),"") | T20: =(IF(I20>0,MIN(8,I20),"")) | U20: =IF((I20)>8,SUM(I20-T20),"") | V20: =(IF(J20>0,MIN(8,J20),"")) | W20: =IF((J20)>8,SUM(J20-V20),"") | X20: =(IF(K20>0,MIN(8,K20),"")) | Y20: =IF((K20)>8,SUM(K20-X20),"") | Z20: =VLOOKUP(A20,#REF!,7,FALSE) -> #REF! | AA20: =VLOOKUP(A20,#REF!,8,FALSE) -> #REF! | AB20: =IFERROR(VLOOKUP(A20,Table13[[#Headers],[#Data]],7,FALSE),0) -> 0 | AC20: =SUM(Z20:AB20) -> #REF! | AD20: =Z20*C20 -> #REF! | AE20: =AA20*C20*1.5 -> #REF! | AF20: =AB20*C20*2 -> 0 | AG20: =AD20+AE20+AF20 -> #REF!
A21: BUITRON, ROBERTO | B21: Electrician | C21: =VLOOKUP('6002 2nd'!$B21,Table6[],2,FALSE)+15 -> 165 | D21: 0 | E21: 0 | F21: 0 | G21: 0 | H21: 0 | I21: 0 | J21: 0 | K21: 0 | L21: =(IF(E21>0,MIN(8,E21),"")) | M21: =IF((E21)>8,SUM(E21-L21),"") | N21: =(IF(F21>0,MIN(8,F21),"")) | O21: =IF((F21)>8,SUM(F21-N21),"") | P21: =(IF(G21>0,MIN(8,G21),"")) | Q21: =IF((G21)>8,SUM(G21-P21),"") | R21: =(IF(H21>0,MIN(8,H21),"")) | S21: =IF((H21)>8,SUM(H21-R21),"") | T21: =(IF(I21>0,MIN(8,I21),"")) | U21: =IF((I21)>8,SUM(I21-T21),"") | V21: =(IF(J21>0,MIN(8,J21),"")) | W21: =IF((J21)>8,SUM(J21-V21),"") | X21: =(IF(K21>0,MIN(8,K21),"")) | Y21: =IF((K21)>8,SUM(K21-X21),"") | Z21: =VLOOKUP(A21,#REF!,7,FALSE) -> #REF! | AA21: =VLOOKUP(A21,#REF!,8,FALSE) -> #REF! | AB21: =IFERROR(VLOOKUP(A21,Table13[[#Headers],[#Data]],7,FALSE),0) -> 0 | AC21: =SUM(Z21:AB21) -> #REF! | AD21: =Z21*C21 -> #REF! | AE21: =AA21*C21*1.5 -> #REF! | AF21: =AB21*C21*2 -> 0 | AG21: =AD21+AE21+AF21 -> #REF!
A22: CAMPOS, JONATHAN RAMOS | B22: Electrician | C22: =VLOOKUP('6002 2nd'!$B22,Table6[],2,FALSE)+15 -> 165 | D22: Y | E22: 0 | F22: 0 | G22: 0 | H22: 0 | I22: 0 | J22: 0 | K22: 0 | L22: =(IF(E22>0,MIN(8,E22),"")) | M22: =IF((E22)>8,SUM(E22-L22),"") | N22: =(IF(F22>0,MIN(8,F22),"")) | O22: =IF((F22)>8,SUM(F22-N22),"") | P22: =(IF(G22>0,MIN(8,G22),"")) | Q22: =IF((G22)>8,SUM(G22-P22),"") | R22: =(IF(H22>0,MIN(8,H22),"")) | S22: =IF((H22)>8,SUM(H22-R22),"") | T22: =(IF(I22>0,MIN(8,I22),"")) | U22: =IF((I22)>8,SUM(I22-T22),"") | V22: =(IF(J22>0,MIN(8,J22),"")) | W22: =IF((J22)>8,SUM(J22-V22),"") | X22: =(IF(K22>0,MIN(8,K22),"")) | Y22: =IF((K22)>8,SUM(K22-X22),"") | Z22: =VLOOKUP(A22,#REF!,7,FALSE) -> #REF! | AA22: =VLOOKUP(A22,#REF!,8,FALSE) -> #REF! | AB22: =IFERROR(VLOOKUP(A22,Table13[[#Headers],[#Data]],7,FALSE),0) -> 0 | AC22: =SUM(Z22:AB22) -> #REF! | AD22: =Z22*C22 -> #REF! | AE22: =AA22*C22*1.5 -> #REF! | AF22: =AB22*C22*2 -> 0 | AG22: =AD22+AE22+AF22 -> #REF!
A23: CARBALLO, DAVID | B23: Electrician | C23: =VLOOKUP('6002 2nd'!$B23,Table6[],2,FALSE)+15 -> 165 | D23: 0 | E23: 0 | F23: 0 | G23: 0 | H23: 0 | I23: 0 | J23: 0 | K23: 0 | L23: =(IF(E23>0,MIN(8,E23),"")) | M23: =IF((E23)>8,SUM(E23-L23),"") | N23: =(IF(F23>0,MIN(8,F23),"")) | O23: =IF((F23)>8,SUM(F23-N23),"") | P23: =(IF(G23>0,MIN(8,G23),"")) | Q23: =IF((G23)>8,SUM(G23-P23),"") | R23: =(IF(H23>0,MIN(8,H23),"")) | S23: =IF((H23)>8,SUM(H23-R23),"") | T23: =(IF(I23>0,MIN(8,I23),"")) | U23: =IF((I23)>8,SUM(I23-T23),"") | V23: =(IF(J23>0,MIN(8,J23),"")) | W23: =IF((J23)>8,SUM(J23-V23),"") | X23: =(IF(K23>0,MIN(8,K23),"")) | Y23: =IF((K23)>8,SUM(K23-X23),"") | Z23: =VLOOKUP(A23,#REF!,7,FALSE) -> #REF! | AA23: =VLOOKUP(A23,#REF!,8,FALSE) -> #REF! | AB23: =IFERROR(VLOOKUP(A23,Table13[[#Headers],[#Data]],7,FALSE),0) -> 0 | AC23: =SUM(Z23:AB23) -> #REF! | AD23: =Z23*C23 -> #REF! | AE23: =AA23*C23*1.5 -> #REF! | AF23: =AB23*C23*2 -> 0 | AG23: =AD23+AE23+AF23 -> #REF!
A24: CASANOVA, HUMBERTO FUENMAYOR | B24: Electrician | C24: =VLOOKUP('6002 2nd'!$B24,Table6[],2,FALSE)+15 -> 165 | D24: 0 | E24: 0 | F24: 0 | G24: 0 | H24: 0 | I24: 0 | J24: 0 | K24: 0 | L24: =(IF(E24>0,MIN(8,E24),"")) | M24: =IF((E24)>8,SUM(E24-L24),"") | N24: =(IF(F24>0,MIN(8,F24),"")) | O24: =IF((F24)>8,SUM(F24-N24),"") | P24: =(IF(G24>0,MIN(8,G24),"")) | Q24: =IF((G24)>8,SUM(G24-P24),"") | R24: =(IF(H24>0,MIN(8,H24),"")) | S24: =IF((H24)>8,SUM(H24-R24),"") | T24: =(IF(I24>0,MIN(8,I24),"")) | U24: =IF((I24)>8,SUM(I24-T24),"") | V24: =(IF(J24>0,MIN(8,J24),"")) | W24: =IF((J24)>8,SUM(J24-V24),"") | X24: =(IF(K24>0,MIN(8,K24),"")) | Y24: =IF((K24)>8,SUM(K24-X24),"") | Z24: =VLOOKUP(A24,#REF!,7,FALSE) -> #REF! | AA24: =VLOOKUP(A24,#REF!,8,FALSE) -> #REF! | AB24: =IFERROR(VLOOKUP(A24,Table13[[#Headers],[#Data]],7,FALSE),0) -> 0 | AC24: =SUM(Z24:AB24) -> #REF! | AD24: =Z24*C24 -> #REF! | AE24: =AA24*C24*1.5 -> #REF! | AF24: =AB24*C24*2 -> 0 | AG24: =AD24+AE24+AF24 -> #REF!
A25: CASTILLO, DERBYS URDANETA | B25: Electrician | C25: =VLOOKUP('6002 2nd'!$B25,Table6[],2,FALSE)+15 -> 165 | D25: 0 | E25: 0 | F25: 0 | G25: 0 | H25: 0 | I25: 0 | J25: 0 | K25: 0 | L25: =(IF(E25>0,MIN(8,E25),"")) | M25: =IF((E25)>8,SUM(E25-L25),"") | N25: =(IF(F25>0,MIN(8,F25),"")) | O25: =IF((F25)>8,SUM(F25-N25),"") | P25: =(IF(G25>0,MIN(8,G25),"")) | Q25: =IF((G25)>8,SUM(G25-P25),"") | R25: =(IF(H25>0,MIN(8,H25),"")) | S25: =IF((H25)>8,SUM(H25-R25),"") | T25: =(IF(I25>0,MIN(8,I25),"")) | U25: =IF((I25)>8,SUM(I25-T25),"") | V25: =(IF(J25>0,MIN(8,J25),"")) | W25: =IF((J25)>8,SUM(J25-V25),"") | X25: =(IF(K25>0,MIN(8,K25),"")) | Y25: =IF((K25)>8,SUM(K25-X25),"") | Z25: =VLOOKUP(A25,#REF!,7,FALSE) -> #REF! | AA25: =VLOOKUP(A25,#REF!,8,FALSE) -> #REF! | AB25: =IFERROR(VLOOKUP(A25,Table13[[#Headers],[#Data]],7,FALSE),0) -> 0 | AC25: =SUM(Z25:AB25) -> #REF! | AD25: =Z25*C25 -> #REF! | AE25: =AA25*C25*1.5 -> #REF! | AF25: =AB25*C25*2 -> 0 | AG25: =AD25+AE25+AF25 -> #REF!
A26: CASTILLO, JUAN SALAZAR DEL | B26: Electrician | C26: =VLOOKUP('6002 2nd'!$B26,Table6[],2,FALSE)+15 -> 165 | D26: 0 | E26: 0 | F26: 0 | G26: 0 | H26: 0 | I26: 0 | J26: 0 | K26: 0 | L26: =(IF(E26>0,MIN(8,E26),"")) | M26: =IF((E26)>8,SUM(E26-L26),"") | N26: =(IF(F26>0,MIN(8,F26),"")) | O26: =IF((F26)>8,SUM(F26-N26),"") | P26: =(IF(G26>0,MIN(8,G26),"")) | Q26: =IF((G26)>8,SUM(G26-P26),"") | R26: =(IF(H26>0,MIN(8,H26),"")) | S26: =IF((H26)>8,SUM(H26-R26),"") | T26: =(IF(I26>0,MIN(8,I26),"")) | U26: =IF((I26)>8,SUM(I26-T26),"") | V26: =(IF(J26>0,MIN(8,J26),"")) | W26: =IF((J26)>8,SUM(J26-V26),"") | X26: =(IF(K26>0,MIN(8,K26),"")) | Y26: =IF((K26)>8,SUM(K26-X26),"") | Z26: =VLOOKUP(A26,#REF!,7,FALSE) -> #REF! | AA26: =VLOOKUP(A26,#REF!,8,FALSE) -> #REF! | AB26: =IFERROR(VLOOKUP(A26,Table13[[#Headers],[#Data]],7,FALSE),0) -> 0 | AC26: =SUM(Z26:AB26) -> #REF! | AD26: =Z26*C26 -> #REF! | AE26: =AA26*C26*1.5 -> #REF! | AF26: =AB26*C26*2 -> 0 | AG26: =AD26+AE26+AF26 -> #REF!
A27: CASTILLO, LUIS YUNES | B27: Electrician | C27: =VLOOKUP('6002 2nd'!$B27,Table6[],2,FALSE)+15 -> 165 | D27: 0 | E27: 0 | F27: 0 | G27: 0 | H27: 0 | I27: 0 | J27: 0 | K27: 0 | L27: =(IF(E27>0,MIN(8,E27),"")) | M27: =IF((E27)>8,SUM(E27-L27),"") | N27: =(IF(F27>0,MIN(8,F27),"")) | O27: =IF((F27)>8,SUM(F27-N27),"") | P27: =(IF(G27>0,MIN(8,G27),"")) | Q27: =IF((G27)>8,SUM(G27-P27),"") | R27: =(IF(H27>0,MIN(8,H27),"")) | S27: =IF((H27)>8,SUM(H27-R27),"") | T27: =(IF(I27>0,MIN(8,I27),"")) | U27: =IF((I27)>8,SUM(I27-T27),"") | V27: =(IF(J27>0,MIN(8,J27),"")) | W27: =IF((J27)>8,SUM(J27-V27),"") | X27: =(IF(K27>0,MIN(8,K27),"")) | Y27: =IF((K27)>8,SUM(K27-X27),"") | Z27: =VLOOKUP(A27,#REF!,7,FALSE) -> #REF! | AA27: =VLOOKUP(A27,#REF!,8,FALSE) -> #REF! | AB27: =IFERROR(VLOOKUP(A27,Table13[[#Headers],[#Data]],7,FALSE),0) -> 0 | AC27: =SUM(Z27:AB27) -> #REF! | AD27: =Z27*C27 -> #REF! | AE27: =AA27*C27*1.5 -> #REF! | AF27: =AB27*C27*2 -> 0 | AG27: =AD27+AE27+AF27 -> #REF!
A28: CASTRILLON, DERWIN ZABALA | B28: Electrician | C28: =VLOOKUP('6002 2nd'!$B28,Table6[],2,FALSE)+15 -> 165 | D28: 0 | E28: 0 | F28: 0 | G28: 0 | H28: 0 | I28: 0 | J28: 0 | K28: 0 | L28: =(IF(E28>0,MIN(8,E28),"")) | M28: =IF((E28)>8,SUM(E28-L28),"") | N28: =(IF(F28>0,MIN(8,F28),"")) | O28: =IF((F28)>8,SUM(F28-N28),"") | P28: =(IF(G28>0,MIN(8,G28),"")) | Q28: =IF((G28)>8,SUM(G28-P28),"") | R28: =(IF(H28>0,MIN(8,H28),"")) | S28: =IF((H28)>8,SUM(H28-R28),"") | T28: =(IF(I28>0,MIN(8,I28),"")) | U28: =IF((I28)>8,SUM(I28-T28),"") | V28: =(IF(J28>0,MIN(8,J28),"")) | W28: =IF((J28)>8,SUM(J28-V28),"") | X28: =(IF(K28>0,MIN(8,K28),"")) | Y28: =IF((K28)>8,SUM(K28-X28),"") | Z28: =VLOOKUP(A28,#REF!,7,FALSE) -> #REF! | AA28: =VLOOKUP(A28,#REF!,8,FALSE) -> #REF! | AB28: =IFERROR(VLOOKUP(A28,Table13[[#Headers],[#Data]],7,FALSE),0) -> 0 | AC28: =SUM(Z28:AB28) -> #REF! | AD28: =Z28*C28 -> #REF! | AE28: =AA28*C28*1.5 -> #REF! | AF28: =AB28*C28*2 -> 0 | AG28: =AD28+AE28+AF28 -> #REF!
A29: CASTRO, DANIEL | B29: Electrician | C29: =VLOOKUP('6002 2nd'!$B29,Table6[],2,FALSE)+15 -> 165 | D29: 0 | E29: 0 | F29: 0 | G29: 0 | H29: 0 | I29: 0 | J29: 0 | K29: 0 | L29: =(IF(E29>0,MIN(8,E29),"")) | M29: =IF((E29)>8,SUM(E29-L29),"") | N29: =(IF(F29>0,MIN(8,F29),"")) | O29: =IF((F29)>8,SUM(F29-N29),"") | P29: =(IF(G29>0,MIN(8,G29),"")) | Q29: =IF((G29)>8,SUM(G29-P29),"") | R29: =(IF(H29>0,MIN(8,H29),"")) | S29: =IF((H29)>8,SUM(H29-R29),"") | T29: =(IF(I29>0,MIN(8,I29),"")) | U29: =IF((I29)>8,SUM(I29-T29),"") | V29: =(IF(J29>0,MIN(8,J29),"")) | W29: =IF((J29)>8,SUM(J29-V29),"") | X29: =(IF(K29>0,MIN(8,K29),"")) | Y29: =IF((K29)>8,SUM(K29-X29),"") | Z29: =VLOOKUP(A29,#REF!,7,FALSE) -> #REF! | AA29: =VLOOKUP(A29,#REF!,8,FALSE) -> #REF! | AB29: =IFERROR(VLOOKUP(A29,Table13[[#Headers],[#Data]],7,FALSE),0) -> 0 | AC29: =SUM(Z29:AB29) -> #REF! | AD29: =Z29*C29 -> #REF! | AE29: =AA29*C29*1.5 -> #REF! | AF29: =AB29*C29*2 -> 0 | AG29: =AD29+AE29+AF29 -> #REF!
A30: CHASE, SHANE | B30: Electrician | C30: =VLOOKUP('6002 2nd'!$B30,Table6[],2,FALSE)+15 -> 165 | D30: 0 | E30: 0 | F30: 0 | G30: 0 | H30: 0 | I30: 0 | J30: 0 | K30: 0 | L30: =(IF(E30>0,MIN(8,E30),"")) | M30: =IF((E30)>8,SUM(E30-L30),"") | N30: =(IF(F30>0,MIN(8,F30),"")) | O30: =IF((F30)>8,SUM(F30-N30),"") | P30: =(IF(G30>0,MIN(8,G30),"")) | Q30: =IF((G30)>8,SUM(G30-P30),"") | R30: =(IF(H30>0,MIN(8,H30),"")) | S30: =IF((H30)>8,SUM(H30-R30),"") | T30: =(IF(I30>0,MIN(8,I30),"")) | U30: =IF((I30)>8,SUM(I30-T30),"") | V30: =(IF(J30>0,MIN(8,J30),"")) | W30: =IF((J30)>8,SUM(J30-V30),"") | X30: =(IF(K30>0,MIN(8,K30),"")) | Y30: =IF((K30)>8,SUM(K30-X30),"") | Z30: =VLOOKUP(A30,#REF!,7,FALSE) -> #REF! | AA30: =VLOOKUP(A30,#REF!,8,FALSE) -> #REF! | AB30: =IFERROR(VLOOKUP(A30,Table13[[#Headers],[#Data]],7,FALSE),0) -> 0 | AC30: =SUM(Z30:AB30) -> #REF! | AD30: =Z30*C30 -> #REF! | AE30: =AA30*C30*1.5 -> #REF! | AF30: =AB30*C30*2 -> 0 | AG30: =AD30+AE30+AF30 -> #REF!
A31: CHAVARRIA, GLORIA CRISTINA TORREZ | B31: Electrician | C31: =VLOOKUP('6002 2nd'!$B31,Table6[],2,FALSE)+15 -> 165 | D31: 0 | E31: 0 | F31: 0 | G31: 0 | H31: 0 | I31: 0 | J31: 0 | K31: 0 | L31: =(IF(E31>0,MIN(8,E31),"")) | M31: =IF((E31)>8,SUM(E31-L31),"") | N31: =(IF(F31>0,MIN(8,F31),"")) | O31: =IF((F31)>8,SUM(F31-N31),"") | P31: =(IF(G31>0,MIN(8,G31),"")) | Q31: =IF((G31)>8,SUM(G31-P31),"") | R31: =(IF(H31>0,MIN(8,H31),"")) | S31: =IF((H31)>8,SUM(H31-R31),"") | T31: =(IF(I31>0,MIN(8,I31),"")) | U31: =IF((I31)>8,SUM(I31-T31),"") | V31: =(IF(J31>0,MIN(8,J31),"")) | W31: =IF((J31)>8,SUM(J31-V31),"") | X31: =(IF(K31>0,MIN(8,K31),"")) | Y31: =IF((K31)>8,SUM(K31-X31),"") | Z31: =VLOOKUP(A31,#REF!,7,FALSE) -> #REF! | AA31: =VLOOKUP(A31,#REF!,8,FALSE) -> #REF! | AB31: =IFERROR(VLOOKUP(A31,Table13[[#Headers],[#Data]],7,FALSE),0) -> 0 | AC31: =SUM(Z31:AB31) -> #REF! | AD31: =Z31*C31 -> #REF! | AE31: =AA31*C31*1.5 -> #REF! | AF31: =AB31*C31*2 -> 0 | AG31: =AD31+AE31+AF31 -> #REF!
A32: CHAVEZ ABELARDO, JANDIEL | B32: Electrician | C32: =VLOOKUP('6002 2nd'!$B32,Table6[],2,FALSE)+15 -> 165 | D32: 0 | E32: 0 | F32: 0 | G32: 0 | H32: 0 | I32: 0 | J32: 0 | K32: 0 | L32: =(IF(E32>0,MIN(8,E32),"")) | M32: =IF((E32)>8,SUM(E32-L32),"") | N32: =(IF(F32>0,MIN(8,F32),"")) | O32: =IF((F32)>8,SUM(F32-N32),"") | P32: =(IF(G32>0,MIN(8,G32),"")) | Q32: =IF((G32)>8,SUM(G32-P32),"") | R32: =(IF(H32>0,MIN(8,H32),"")) | S32: =IF((H32)>8,SUM(H32-R32),"") | T32: =(IF(I32>0,MIN(8,I32),"")) | U32: =IF((I32)>8,SUM(I32-T32),"") | V32: =(IF(J32>0,MIN(8,J32),"")) | W32: =IF((J32)>8,SUM(J32-V32),"") | X32: =(IF(K32>0,MIN(8,K32),"")) | Y32: =IF((K32)>8,SUM(K32-X32),"") | Z32: =VLOOKUP(A32,#REF!,7,FALSE) -> #REF! | AA32: =VLOOKUP(A32,#REF!,8,FALSE) -> #REF! | AB32: =IFERROR(VLOOKUP(A32,Table13[[#Headers],[#Data]],7,FALSE),0) -> 0 | AC32: =SUM(Z32:AB32) -> #REF! | AD32: =Z32*C32 -> #REF! | AE32: =AA32*C32*1.5 -> #REF! | AF32: =AB32*C32*2 -> 0 | AG32: =AD32+AE32+AF32 -> #REF!
A33: CHIRINOS, DANNY | B33: Electrician | C33: =VLOOKUP('6002 2nd'!$B33,Table6[],2,FALSE)+15 -> 165 | D33: 0 | E33: 0 | F33: 0 | G33: 0 | H33: 0 | I33: 0 | J33: 0 | K33: 0 | L33: =(IF(E33>0,MIN(8,E33),"")) | M33: =IF((E33)>8,SUM(E33-L33),"") | N33: =(IF(F33>0,MIN(8,F33),"")) | O33: =IF((F33)>8,SUM(F33-N33),"") | P33: =(IF(G33>0,MIN(8,G33),"")) | Q33: =IF((G33)>8,SUM(G33-P33),"") | R33: =(IF(H33>0,MIN(8,H33),"")) | S33: =IF((H33)>8,SUM(H33-R33),"") | T33: =(IF(I33>0,MIN(8,I33),"")) | U33: =IF((I33)>8,SUM(I33-T33),"") | V33: =(IF(J33>0,MIN(8,J33),"")) | W33: =IF((J33)>8,SUM(J33-V33),"") | X33: =(IF(K33>0,MIN(8,K33),"")) | Y33: =IF((K33)>8,SUM(K33-X33),"") | Z33: =VLOOKUP(A33,#REF!,7,FALSE) -> #REF! | AA33: =VLOOKUP(A33,#REF!,8,FALSE) -> #REF! | AB33: =IFERROR(VLOOKUP(A33,Table13[[#Headers],[#Data]],7,FALSE),0) -> 0 | AC33: =SUM(Z33:AB33) -> #REF! | AD33: =Z33*C33 -> #REF! | AE33: =AA33*C33*1.5 -> #REF! | AF33: =AB33*C33*2 -> 0 | AG33: =AD33+AE33+AF33 -> #REF!
A34: CHOC, ALEJANDRO | B34: Electrician | C34: =VLOOKUP('6002 2nd'!$B34,Table6[],2,FALSE)+15 -> 165 | D34: 0 | E34: 0 | F34: 0 | G34: 0 | H34: 0 | I34: 0 | J34: 0 | K34: 0 | L34: =(IF(E34>0,MIN(8,E34),"")) | M34: =IF((E34)>8,SUM(E34-L34),"") | N34: =(IF(F34>0,MIN(8,F34),"")) | O34: =IF((F34)>8,SUM(F34-N34),"") | P34: =(IF(G34>0,MIN(8,G34),"")) | Q34: =IF((G34)>8,SUM(G34-P34),"") | R34: =(IF(H34>0,MIN(8,H34),"")) | S34: =IF((H34)>8,SUM(H34-R34),"") | T34: =(IF(I34>0,MIN(8,I34),"")) | U34: =IF((I34)>8,SUM(I34-T34),"") | V34: =(IF(J34>0,MIN(8,J34),"")) | W34: =IF((J34)>8,SUM(J34-V34),"") | X34: =(IF(K34>0,MIN(8,K34),"")) | Y34: =IF((K34)>8,SUM(K34-X34),"") | Z34: =VLOOKUP(A34,#REF!,7,FALSE) -> #REF! | AA34: =VLOOKUP(A34,#REF!,8,FALSE) -> #REF! | AB34: =IFERROR(VLOOKUP(A34,Table13[[#Headers],[#Data]],7,FALSE),0) -> 0 | AC34: =SUM(Z34:AB34) -> #REF! | AD34: =Z34*C34 -> #REF! | AE34: =AA34*C34*1.5 -> #REF! | AF34: =AB34*C34*2 -> 0 | AG34: =AD34+AE34+AF34 -> #REF!
... A89: LUERA, JOSUE SILVA DE | B89: Electrician | C89: =VLOOKUP('6002 2nd'!$B89,Table6[],2,FALSE)+15 -> 165 | D89: 0 | E89: 0 | F89: 0 | G89: 0 | H89: 0 | I89: 0 | J89: 0 | K89: 0 | L89: =(IF(E89>0,MIN(8,E89),"")) | M89: =IF((E89)>8,SUM(E89-L89),"") | N89: =(IF(F89>0,MIN(8,F89),"")) | O89: =IF((F89)>8,SUM(F89-N89),"") | P89: =(IF(G89>0,MIN(8,G89),"")) | Q89: =IF((G89)>8,SUM(G89-P89),"") | R89: =(IF(H89>0,MIN(8,H89),"")) | S89: =IF((H89)>8,SUM(H89-R89),"") | T89: =(IF(I89>0,MIN(8,I89),"")) | U89: =IF((I89)>8,SUM(I89-T89),"") | V89: =(IF(J89>0,MIN(8,J89),"")) | W89: =IF((J89)>8,SUM(J89-V89),"") | X89: =(IF(K89>0,MIN(8,K89),"")) | Y89: =IF((K89)>8,SUM(K89-X89),"") | Z89: =VLOOKUP(A89,#REF!,7,FALSE) -> #REF! | AA89: =VLOOKUP(A89,#REF!,8,FALSE) -> #REF! | AB89: =IFERROR(VLOOKUP(A89,Table13[[#Headers],[#Data]],7,FALSE),0) -> 0 | AC89: =SUM(Z89:AB89) -> #REF! | AD89: =Z89*C89 -> #REF! | AE89: =AA89*C89*1.5 -> #REF! | AF89: =AB89*C89*2 -> 0 | AG89: =AD89+AE89+AF89 -> #REF!
A90: LUGARDO, CARLOS | B90: QA/QC Director | C90: 190 | Z90: =VLOOKUP(A90,#REF!,7,FALSE) -> #REF! | AA90: =VLOOKUP(A90,#REF!,8,FALSE) -> #REF! | AB90: =IFERROR(VLOOKUP(A90,Table13[[#Headers],[#Data]],7,FALSE),0) -> 0 | AC90: =SUM(Z90:AB90) -> #REF! | AD90: =Z90*C90 -> #REF! | AE90: =AA90*C90*1.5 -> #REF! | AF90: =AB90*C90*2 -> 0 | AG90: =AD90+AE90+AF90 -> #REF!
A91: MACIAS, LEONARDO | B91: Electrician | C91: =VLOOKUP('6002 2nd'!$B91,Table6[],2,FALSE)+15 -> 165 | D91: 0 | E91: 0 | F91: 0 | G91: 0 | H91: 0 | I91: 0 | J91: 0 | K91: 0 | L91: =(IF(E91>0,MIN(8,E91),"")) | M91: =IF((E91)>8,SUM(E91-L91),"") | N91: =(IF(F91>0,MIN(8,F91),"")) | O91: =IF((F91)>8,SUM(F91-N91),"") | P91: =(IF(G91>0,MIN(8,G91),"")) | Q91: =IF((G91)>8,SUM(G91-P91),"") | R91: =(IF(H91>0,MIN(8,H91),"")) | S91: =IF((H91)>8,SUM(H91-R91),"") | T91: =(IF(I91>0,MIN(8,I91),"")) | U91: =IF((I91)>8,SUM(I91-T91),"") | V91: =(IF(J91>0,MIN(8,J91),"")) | W91: =IF((J91)>8,SUM(J91-V91),"") | X91: =(IF(K91>0,MIN(8,K91),"")) | Y91: =IF((K91)>8,SUM(K91-X91),"") | Z91: =VLOOKUP(A91,#REF!,7,FALSE) -> #REF! | AA91: =VLOOKUP(A91,#REF!,8,FALSE) -> #REF! | AB91: =IFERROR(VLOOKUP(A91,Table13[[#Headers],[#Data]],7,FALSE),0) -> 0 | AC91: =SUM(Z91:AB91) -> #REF! | AD91: =Z91*C91 -> #REF! | AE91: =AA91*C91*1.5 -> #REF! | AF91: =AB91*C91*2 -> 0 | AG91: =AD91+AE91+AF91 -> #REF!
A92: LUQUE, WILLIAM | B92: Electrician | C92: =VLOOKUP('6002 2nd'!$B92,Table6[],2,FALSE)+15 -> 165 | D92: 0 | E92: 0 | F92: 0 | G92: 0 | H92: 0 | I92: 0 | J92: 0 | K92: 0 | L92: =(IF(E92>0,MIN(8,E92),"")) | M92: =IF((E92)>8,SUM(E92-L92),"") | N92: =(IF(F92>0,MIN(8,F92),"")) | O92: =IF((F92)>8,SUM(F92-N92),"") | P92: =(IF(G92>0,MIN(8,G92),"")) | Q92: =IF((G92)>8,SUM(G92-P92),"") | R92: =(IF(H92>0,MIN(8,H92),"")) | S92: =IF((H92)>8,SUM(H92-R92),"") | T92: =(IF(I92>0,MIN(8,I92),"")) | U92: =IF((I92)>8,SUM(I92-T92),"") | V92: =(IF(J92>0,MIN(8,J92),"")) | W92: =IF((J92)>8,SUM(J92-V92),"") | X92: =(IF(K92>0,MIN(8,K92),"")) | Y92: =IF((K92)>8,SUM(K92-X92),"") | Z92: =VLOOKUP(A92,#REF!,7,FALSE) -> #REF! | AA92: =VLOOKUP(A92,#REF!,8,FALSE) -> #REF! | AB92: =IFERROR(VLOOKUP(A92,Table13[[#Headers],[#Data]],7,FALSE),0) -> 0 | AC92: =SUM(Z92:AB92) -> #REF! | AD92: =Z92*C92 -> #REF! | AE92: =AA92*C92*1.5 -> #REF! | AF92: =AB92*C92*2 -> 0 | AG92: =AD92+AE92+AF92 -> #REF!
A93: MARQUEZ, CESAR | B93: Electrician | C93: =VLOOKUP('6002 2nd'!$B93,Table6[],2,FALSE)+15 -> 165 | D93: 0 | E93: 0 | F93: 0 | G93: 0 | H93: 0 | I93: 0 | J93: 0 | K93: 0 | L93: =(IF(E93>0,MIN(8,E93),"")) | M93: =IF((E93)>8,SUM(E93-L93),"") | N93: =(IF(F93>0,MIN(8,F93),"")) | O93: =IF((F93)>8,SUM(F93-N93),"") | P93: =(IF(G93>0,MIN(8,G93),"")) | Q93: =IF((G93)>8,SUM(G93-P93),"") | R93: =(IF(H93>0,MIN(8,H93),"")) | S93: =IF((H93)>8,SUM(H93-R93),"") | T93: =(IF(I93>0,MIN(8,I93),"")) | U93: =IF((I93)>8,SUM(I93-T93),"") | V93: =(IF(J93>0,MIN(8,J93),"")) | W93: =IF((J93)>8,SUM(J93-V93),"") | X93: =(IF(K93>0,MIN(8,K93),"")) | Y93: =IF((K93)>8,SUM(K93-X93),"") | Z93: =VLOOKUP(A93,#REF!,7,FALSE) -> #REF! | AA93: =VLOOKUP(A93,#REF!,8,FALSE) -> #REF! | AB93: =IFERROR(VLOOKUP(A93,Table13[[#Headers],[#Data]],7,FALSE),0) -> 0 | AC93: =SUM(Z93:AB93) -> #REF! | AD93: =Z93*C93 -> #REF! | AE93: =AA93*C93*1.5 -> #REF! | AF93: =AB93*C93*2 -> 0 | AG93: =AD93+AE93+AF93 -> #REF!
A94: MARROQUIN, JUAN | B94: Electrician | C94: =VLOOKUP('6002 2nd'!$B94,Table6[],2,FALSE)+15 -> 165 | D94: 0 | E94: 0 | F94: 0 | G94: 0 | H94: 0 | I94: 0 | J94: 0 | K94: 0 | L94: =(IF(E94>0,MIN(8,E94),"")) | M94: =IF((E94)>8,SUM(E94-L94),"") | N94: =(IF(F94>0,MIN(8,F94),"")) | O94: =IF((F94)>8,SUM(F94-N94),"") | P94: =(IF(G94>0,MIN(8,G94),"")) | Q94: =IF((G94)>8,SUM(G94-P94),"") | R94: =(IF(H94>0,MIN(8,H94),"")) | S94: =IF((H94)>8,SUM(H94-R94),"") | T94: =(IF(I94>0,MIN(8,I94),"")) | U94: =IF((I94)>8,SUM(I94-T94),"") | V94: =(IF(J94>0,MIN(8,J94),"")) | W94: =IF((J94)>8,SUM(J94-V94),"") | X94: =(IF(K94>0,MIN(8,K94),"")) | Y94: =IF((K94)>8,SUM(K94-X94),"") | Z94: =VLOOKUP(A94,#REF!,7,FALSE) -> #REF! | AA94: =VLOOKUP(A94,#REF!,8,FALSE) -> #REF! | AB94: =IFERROR(VLOOKUP(A94,Table13[[#Headers],[#Data]],7,FALSE),0) -> 0 | AC94: =SUM(Z94:AB94) -> #REF! | AD94: =Z94*C94 -> #REF! | AE94: =AA94*C94*1.5 -> #REF! | AF94: =AB94*C94*2 -> 0 | AG94: =AD94+AE94+AF94 -> #REF!
A95: MARTIN, JUAN JOSE REYNA | B95: Electrician | C95: =VLOOKUP('6002 2nd'!$B95,Table6[],2,FALSE)+15 -> 165 | D95: 0 | E95: 0 | F95: 0 | G95: 0 | H95: 0 | I95: 0 | J95: 0 | K95: 0 | L95: =(IF(E95>0,MIN(8,E95),"")) | M95: =IF((E95)>8,SUM(E95-L95),"") | N95: =(IF(F95>0,MIN(8,F95),"")) | O95: =IF((F95)>8,SUM(F95-N95),"") | P95: =(IF(G95>0,MIN(8,G95),"")) | Q95: =IF((G95)>8,SUM(G95-P95),"") | R95: =(IF(H95>0,MIN(8,H95),"")) | S95: =IF((H95)>8,SUM(H95-R95),"") | T95: =(IF(I95>0,MIN(8,I95),"")) | U95: =IF((I95)>8,SUM(I95-T95),"") | V95: =(IF(J95>0,MIN(8,J95),"")) | W95: =IF((J95)>8,SUM(J95-V95),"") | X95: =(IF(K95>0,MIN(8,K95),"")) | Y95: =IF((K95)>8,SUM(K95-X95),"") | Z95: =VLOOKUP(A95,#REF!,7,FALSE) -> #REF! | AA95: =VLOOKUP(A95,#REF!,8,FALSE) -> #REF! | AB95: =IFERROR(VLOOKUP(A95,Table13[[#Headers],[#Data]],7,FALSE),0) -> 0 | AC95: =SUM(Z95:AB95) -> #REF! | AD95: =Z95*C95 -> #REF! | AE95: =AA95*C95*1.5 -> #REF! | AF95: =AB95*C95*2 -> 0 | AG95: =AD95+AE95+AF95 -> #REF!
A96: MATURINO, JESUS | B96: Electrician | C96: =VLOOKUP('6002 2nd'!$B96,Table6[],2,FALSE)+15 -> 165 | D96: 0 | E96: 0 | F96: 0 | G96: 0 | H96: 0 | I96: 0 | J96: 0 | K96: 0 | L96: =(IF(E96>0,MIN(8,E96),"")) | M96: =IF((E96)>8,SUM(E96-L96),"") | N96: =(IF(F96>0,MIN(8,F96),"")) | O96: =IF((F96)>8,SUM(F96-N96),"") | P96: =(IF(G96>0,MIN(8,G96),"")) | Q96: =IF((G96)>8,SUM(G96-P96),"") | R96: =(IF(H96>0,MIN(8,H96),"")) | S96: =IF((H96)>8,SUM(H96-R96),"") | T96: =(IF(I96>0,MIN(8,I96),"")) | U96: =IF((I96)>8,SUM(I96-T96),"") | V96: =(IF(J96>0,MIN(8,J96),"")) | W96: =IF((J96)>8,SUM(J96-V96),"") | X96: =(IF(K96>0,MIN(8,K96),"")) | Y96: =IF((K96)>8,SUM(K96-X96),"") | Z96: =VLOOKUP(A96,#REF!,7,FALSE) -> #REF! | AA96: =VLOOKUP(A96,#REF!,8,FALSE) -> #REF! | AB96: =IFERROR(VLOOKUP(A96,Table13[[#Headers],[#Data]],7,FALSE),0) -> 0 | AC96: =SUM(Z96:AB96) -> #REF! | AD96: =Z96*C96 -> #REF! | AE96: =AA96*C96*1.5 -> #REF! | AF96: =AB96*C96*2 -> 0 | AG96: =AD96+AE96+AF96 -> #REF!
A97: MCDONALD, ROBERT | B97: Electrician | C97: =VLOOKUP('6002 2nd'!$B97,Table6[],2,FALSE)+15 -> 165 | D97: 0 | E97: 0 | F97: 0 | G97: 0 | H97: 0 | I97: 0 | J97: 0 | K97: 0 | L97: =(IF(E97>0,MIN(8,E97),"")) | M97: =IF((E97)>8,SUM(E97-L97),"") | N97: =(IF(F97>0,MIN(8,F97),"")) | O97: =IF((F97)>8,SUM(F97-N97),"") | P97: =(IF(G97>0,MIN(8,G97),"")) | Q97: =IF((G97)>8,SUM(G97-P97),"") | R97: =(IF(H97>0,MIN(8,H97),"")) | S97: =IF((H97)>8,SUM(H97-R97),"") | T97: =(IF(I97>0,MIN(8,I97),"")) | U97: =IF((I97)>8,SUM(I97-T97),"") | V97: =(IF(J97>0,MIN(8,J97),"")) | W97: =IF((J97)>8,SUM(J97-V97),"") | X97: =(IF(K97>0,MIN(8,K97),"")) | Y97: =IF((K97)>8,SUM(K97-X97),"") | Z97: =VLOOKUP(A97,#REF!,7,FALSE) -> #REF! | AA97: =VLOOKUP(A97,#REF!,8,FALSE) -> #REF! | AB97: =IFERROR(VLOOKUP(A97,Table13[[#Headers],[#Data]],7,FALSE),0) -> 0 | AC97: =SUM(Z97:AB97) -> #REF! | AD97: =Z97*C97 -> #REF! | AE97: =AA97*C97*1.5 -> #REF! | AF97: =AB97*C97*2 -> 0 | AG97: =AD97+AE97+AF97 -> #REF!
A98: MEDELLIN, CHRISTIAN | B98: Electrician | C98: =VLOOKUP('6002 2nd'!$B98,Table6[],2,FALSE)+15 -> 165 | D98: 0 | E98: 0 | F98: 0 | G98: 0 | H98: 0 | I98: 0 | J98: 0 | K98: 0 | L98: =(IF(E98>0,MIN(8,E98),"")) | M98: =IF((E98)>8,SUM(E98-L98),"") | N98: =(IF(F98>0,MIN(8,F98),"")) | O98: =IF((F98)>8,SUM(F98-N98),"") | P98: =(IF(G98>0,MIN(8,G98),"")) | Q98: =IF((G98)>8,SUM(G98-P98),"") | R98: =(IF(H98>0,MIN(8,H98),"")) | S98: =IF((H98)>8,SUM(H98-R98),"") | T98: =(IF(I98>0,MIN(8,I98),"")) | U98: =IF((I98)>8,SUM(I98-T98),"") | V98: =(IF(J98>0,MIN(8,J98),"")) | W98: =IF((J98)>8,SUM(J98-V98),"") | X98: =(IF(K98>0,MIN(8,K98),"")) | Y98: =IF((K98)>8,SUM(K98-X98),"") | Z98: =VLOOKUP(A98,#REF!,7,FALSE) -> #REF! | AA98: =VLOOKUP(A98,#REF!,8,FALSE) -> #REF! | AB98: =IFERROR(VLOOKUP(A98,Table13[[#Headers],[#Data]],7,FALSE),0) -> 0 | AC98: =SUM(Z98:AB98) -> #REF! | AD98: =Z98*C98 -> #REF! | AE98: =AA98*C98*1.5 -> #REF! | AF98: =AB98*C98*2 -> 0 | AG98: =AD98+AE98+AF98 -> #REF!
A99: MENDOZA, BISMARCK | B99: Electrician | C99: =VLOOKUP('6002 2nd'!$B99,Table6[],2,FALSE)+15 -> 165 | D99: 0 | E99: 0 | F99: 0 | G99: 0 | H99: 0 | I99: 0 | J99: 0 | K99: 0 | L99: =(IF(E99>0,MIN(8,E99),"")) | M99: =IF((E99)>8,SUM(E99-L99),"") | N99: =(IF(F99>0,MIN(8,F99),"")) | O99: =IF((F99)>8,SUM(F99-N99),"") | P99: =(IF(G99>0,MIN(8,G99),"")) | Q99: =IF((G99)>8,SUM(G99-P99),"") | R99: =(IF(H99>0,MIN(8,H99),"")) | S99: =IF((H99)>8,SUM(H99-R99),"") | T99: =(IF(I99>0,MIN(8,I99),"")) | U99: =IF((I99)>8,SUM(I99-T99),"") | V99: =(IF(J99>0,MIN(8,J99),"")) | W99: =IF((J99)>8,SUM(J99-V99),"") | X99: =(IF(K99>0,MIN(8,K99),"")) | Y99: =IF((K99)>8,SUM(K99-X99),"") | Z99: =VLOOKUP(A99,#REF!,7,FALSE) -> #REF! | AA99: =VLOOKUP(A99,#REF!,8,FALSE) -> #REF! | AB99: =IFERROR(VLOOKUP(A99,Table13[[#Headers],[#Data]],7,FALSE),0) -> 0 | AC99: =SUM(Z99:AB99) -> #REF! | AD99: =Z99*C99 -> #REF! | AE99: =AA99*C99*1.5 -> #REF! | AF99: =AB99*C99*2 -> 0 | AG99: =AD99+AE99+AF99 -> #REF!
A100: MENDOZA, CONSUELO SOLIS | B100: Electrician | C100: =VLOOKUP('6002 2nd'!$B100,Table6[],2,FALSE)+15 -> 165 | D100: 0 | E100: 0 | F100: 0 | G100: 0 | H100: 0 | I100: 0 | J100: 0 | K100: 0 | L100: =(IF(E100>0,MIN(8,E100),"")) | M100: =IF((E100)>8,SUM(E100-L100),"") | N100: =(IF(F100>0,MIN(8,F100),"")) | O100: =IF((F100)>8,SUM(F100-N100),"") | P100: =(IF(G100>0,MIN(8,G100),"")) | Q100: =IF((G100)>8,SUM(G100-P100),"") | R100: =(IF(H100>0,MIN(8,H100),"")) | S100: =IF((H100)>8,SUM(H100-R100),"") | T100: =(IF(I100>0,MIN(8,I100),"")) | U100: =IF((I100)>8,SUM(I100-T100),"") | V100: =(IF(J100>0,MIN(8,J100),"")) | W100: =IF((J100)>8,SUM(J100-V100),"") | X100: =(IF(K100>0,MIN(8,K100),"")) | Y100: =IF((K100)>8,SUM(K100-X100),"") | Z100: =VLOOKUP(A100,#REF!,7,FALSE) -> #REF! | AA100: =VLOOKUP(A100,#REF!,8,FALSE) -> #REF! | AB100: =IFERROR(VLOOKUP(A100,Table13[[#Headers],[#Data]],7,FALSE),0) -> 0 | AC100: =SUM(Z100:AB100) -> #REF! | AD100: =Z100*C100 -> #REF! | AE100: =AA100*C100*1.5 -> #REF! | AF100: =AB100*C100*2 -> 0 | AG100: =AD100+AE100+AF100 -> #REF!
A101: MENDOZA, YANETH PENA | B101: Electrician | C101: =VLOOKUP('6002 2nd'!$B101,Table6[],2,FALSE)+15 -> 165 | D101: 0 | E101: 0 | F101: 0 | G101: 0 | H101: 0 | I101: 0 | J101: 0 | K101: 0 | L101: =(IF(E101>0,MIN(8,E101),"")) | M101: =IF((E101)>8,SUM(E101-L101),"") | N101: =(IF(F101>0,MIN(8,F101),"")) | O101: =IF((F101)>8,SUM(F101-N101),"") | P101: =(IF(G101>0,MIN(8,G101),"")) | Q101: =IF((G101)>8,SUM(G101-P101),"") | R101: =(IF(H101>0,MIN(8,H101),"")) | S101: =IF((H101)>8,SUM(H101-R101),"") | T101: =(IF(I101>0,MIN(8,I101),"")) | U101: =IF((I101)>8,SUM(I101-T101),"") | V101: =(IF(J101>0,MIN(8,J101),"")) | W101: =IF((J101)>8,SUM(J101-V101),"") | X101: =(IF(K101>0,MIN(8,K101),"")) | Y101: =IF((K101)>8,SUM(K101-X101),"") | Z101: =VLOOKUP(A101,#REF!,7,FALSE) -> #REF! | AA101: =VLOOKUP(A101,#REF!,8,FALSE) -> #REF! | AB101: =IFERROR(VLOOKUP(A101,Table13[[#Headers],[#Data]],7,FALSE),0) -> 0 | AC101: =SUM(Z101:AB101) -> #REF! | AD101: =Z101*C101 -> #REF! | AE101: =AA101*C101*1.5 -> #REF! | AF101: =AB101*C101*2 -> 0 | AG101: =AD101+AE101+AF101 -> #REF!
A102: MEREGILDO, BAYRON | B102: Electrician | C102: =VLOOKUP('6002 2nd'!$B102,Table6[],2,FALSE)+15 -> 165 | D102: 0 | E102: 0 | F102: 0 | G102: 0 | H102: 0 | I102: 0 | J102: 0 | K102: 0 | L102: =(IF(E102>0,MIN(8,E102),"")) | M102: =IF((E102)>8,SUM(E102-L102),"") | N102: =(IF(F102>0,MIN(8,F102),"")) | O102: =IF((F102)>8,SUM(F102-N102),"") | P102: =(IF(G102>0,MIN(8,G102),"")) | Q102: =IF((G102)>8,SUM(G102-P102),"") | R102: =(IF(H102>0,MIN(8,H102),"")) | S102: =IF((H102)>8,SUM(H102-R102),"") | T102: =(IF(I102>0,MIN(8,I102),"")) | U102: =IF((I102)>8,SUM(I102-T102),"") | V102: =(IF(J102>0,MIN(8,J102),"")) | W102: =IF((J102)>8,SUM(J102-V102),"") | X102: =(IF(K102>0,MIN(8,K102),"")) | Y102: =IF((K102)>8,SUM(K102-X102),"") | Z102: =VLOOKUP(A102,#REF!,7,FALSE) -> #REF! | AA102: =VLOOKUP(A102,#REF!,8,FALSE) -> #REF! | AB102: =IFERROR(VLOOKUP(A102,Table13[[#Headers],[#Data]],7,FALSE),0) -> 0 | AC102: =SUM(Z102:AB102) -> #REF! | AD102: =Z102*C102 -> #REF! | AE102: =AA102*C102*1.5 -> #REF! | AF102: =AB102*C102*2 -> 0 | AG102: =AD102+AE102+AF102 -> #REF!
... A127: RANGEL, JOAQUIN | B127: Safety | C127: =VLOOKUP('6002 2nd'!$B127,Table6[],2,FALSE)+15 -> 150 | D127: 0 | E127: 0 | F127: 0 | G127: 0 | H127: 0 | I127: 0 | J127: 0 | K127: 0 | L127: =(IF(E127>0,MIN(8,E127),"")) | M127: =IF((E127)>8,SUM(E127-L127),"") | N127: =(IF(F127>0,MIN(8,F127),"")) | O127: =IF((F127)>8,SUM(F127-N127),"") | P127: =(IF(G127>0,MIN(8,G127),"")) | Q127: =IF((G127)>8,SUM(G127-P127),"") | R127: =(IF(H127>0,MIN(8,H127),"")) | S127: =IF((H127)>8,SUM(H127-R127),"") | T127: =(IF(I127>0,MIN(8,I127),"")) | U127: =IF((I127)>8,SUM(I127-T127),"") | V127: =(IF(J127>0,MIN(8,J127),"")) | W127: =IF((J127)>8,SUM(J127-V127),"") | X127: =(IF(K127>0,MIN(8,K127),"")) | Y127: =IF((K127)>8,SUM(K127-X127),"") | Z127: =VLOOKUP(A127,#REF!,7,FALSE) -> #REF! | AA127: =VLOOKUP(A127,#REF!,8,FALSE) -> #REF! | AB127: =IFERROR(VLOOKUP(A127,Table13[[#Headers],[#Data]],7,FALSE),0) -> 0 | AC127: =SUM(Z127:AB127) -> #REF! | AD127: =Z127*C127 -> #REF! | AE127: =AA127*C127*1.5 -> #REF! | AF127: =AB127*C127*2 -> 0 | AG127: =AD127+AE127+AF127 -> #REF!
A128: REED, BARBARA | B128: Electrician | C128: 165 | Z128: =VLOOKUP(A128,#REF!,7,FALSE) -> #REF! | AA128: =VLOOKUP(A128,#REF!,8,FALSE) -> #REF! | AB128: =IFERROR(VLOOKUP(A128,Table13[[#Headers],[#Data]],7,FALSE),0) -> 0 | AC128: =SUM(Z128:AB128) -> #REF! | AD128: =Z128*C128 -> #REF! | AE128: =AA128*C128*1.5 -> #REF! | AF128: =AB128*C128*2 -> 0 | AG128: =AD128+AE128+AF128 -> #REF!
A129: REYES, AARON | B129: Electrician | C129: =VLOOKUP('6002 2nd'!$B129,Table6[],2,FALSE)+15 -> 165 | D129: 0 | E129: 0 | F129: 0 | G129: 0 | H129: 0 | I129: 0 | J129: 0 | K129: 0 | L129: =(IF(E129>0,MIN(8,E129),"")) | M129: =IF((E129)>8,SUM(E129-L129),"") | N129: =(IF(F129>0,MIN(8,F129),"")) | O129: =IF((F129)>8,SUM(F129-N129),"") | P129: =(IF(G129>0,MIN(8,G129),"")) | Q129: =IF((G129)>8,SUM(G129-P129),"") | R129: =(IF(H129>0,MIN(8,H129),"")) | S129: =IF((H129)>8,SUM(H129-R129),"") | T129: =(IF(I129>0,MIN(8,I129),"")) | U129: =IF((I129)>8,SUM(I129-T129),"") | V129: =(IF(J129>0,MIN(8,J129),"")) | W129: =IF((J129)>8,SUM(J129-V129),"") | X129: =(IF(K129>0,MIN(8,K129),"")) | Y129: =IF((K129)>8,SUM(K129-X129),"") | Z129: =VLOOKUP(A129,#REF!,7,FALSE) -> #REF! | AA129: =VLOOKUP(A129,#REF!,8,FALSE) -> #REF! | AB129: =IFERROR(VLOOKUP(A129,Table13[[#Headers],[#Data]],7,FALSE),0) -> 0 | AC129: =SUM(Z129:AB129) -> #REF! | AD129: =Z129*C129 -> #REF! | AE129: =AA129*C129*1.5 -> #REF! | AF129: =AB129*C129*2 -> 0 | AG129: =AD129+AE129+AF129 -> #REF!
A130: RIVERA, KARLA ORTIZ | B130: Electrician | C130: =VLOOKUP('6002 2nd'!$B130,Table6[],2,FALSE)+15 -> 165 | D130: 0 | E130: 0 | F130: 0 | G130: 0 | H130: 0 | I130: 0 | J130: 0 | K130: 0 | L130: =(IF(E130>0,MIN(8,E130),"")) | M130: =IF((E130)>8,SUM(E130-L130),"") | N130: =(IF(F130>0,MIN(8,F130),"")) | O130: =IF((F130)>8,SUM(F130-N130),"") | P130: =(IF(G130>0,MIN(8,G130),"")) | Q130: =IF((G130)>8,SUM(G130-P130),"") | R130: =(IF(H130>0,MIN(8,H130),"")) | S130: =IF((H130)>8,SUM(H130-R130),"") | T130: =(IF(I130>0,MIN(8,I130),"")) | U130: =IF((I130)>8,SUM(I130-T130),"") | V130: =(IF(J130>0,MIN(8,J130),"")) | W130: =IF((J130)>8,SUM(J130-V130),"") | X130: =(IF(K130>0,MIN(8,K130),"")) | Y130: =IF((K130)>8,SUM(K130-X130),"") | Z130: =VLOOKUP(A130,#REF!,7,FALSE) -> #REF! | AA130: =VLOOKUP(A130,#REF!,8,FALSE) -> #REF! | AB130: =IFERROR(VLOOKUP(A130,Table13[[#Headers],[#Data]],7,FALSE),0) -> 0 | AC130: =SUM(Z130:AB130) -> #REF! | AD130: =Z130*C130 -> #REF! | AE130: =AA130*C130*1.5 -> #REF! | AF130: =AB130*C130*2 -> 0 | AG130: =AD130+AE130+AF130 -> #REF!
A131: RIZZICA, DANIEL | B131: Project Engineer | C131: =VLOOKUP('6002 2nd'!$B131,Table6[],2,FALSE)+15 -> 155 | D131: 0 | E131: 0 | F131: 0 | G131: 0 | H131: 0 | I131: 0 | J131: 0 | K131: 0 | L131: =(IF(E131>0,MIN(8,E131),"")) | M131: =IF((E131)>8,SUM(E131-L131),"") | N131: =(IF(F131>0,MIN(8,F131),"")) | O131: =IF((F131)>8,SUM(F131-N131),"") | P131: =(IF(G131>0,MIN(8,G131),"")) | Q131: =IF((G131)>8,SUM(G131-P131),"") | R131: =(IF(H131>0,MIN(8,H131),"")) | S131: =IF((H131)>8,SUM(H131-R131),"") | T131: =(IF(I131>0,MIN(8,I131),"")) | U131: =IF((I131)>8,SUM(I131-T131),"") | V131: =(IF(J131>0,MIN(8,J131),"")) | W131: =IF((J131)>8,SUM(J131-V131),"") | X131: =(IF(K131>0,MIN(8,K131),"")) | Y131: =IF((K131)>8,SUM(K131-X131),"") | Z131: =VLOOKUP(A131,#REF!,7,FALSE) -> #REF! | AA131: =VLOOKUP(A131,#REF!,8,FALSE) -> #REF! | AB131: =IFERROR(VLOOKUP(A131,Table13[[#Headers],[#Data]],7,FALSE),0) -> 0 | AC131: =SUM(Z131:AB131) -> #REF! | AD131: =Z131*C131 -> #REF! | AE131: =AA131*C131*1.5 -> #REF! | AF131: =AB131*C131*2 -> 0 | AG131: =AD131+AE131+AF131 -> #REF!
A132: RODRIGUEZ, MARLON SANCHEZ | B132: Electrician | C132: =VLOOKUP('6002 2nd'!$B132,Table6[],2,FALSE)+15 -> 165 | D132: 0 | E132: 0 | F132: 0 | G132: 0 | H132: 0 | I132: 0 | J132: 0 | K132: 0 | L132: =(IF(E132>0,MIN(8,E132),"")) | M132: =IF((E132)>8,SUM(E132-L132),"") | N132: =(IF(F132>0,MIN(8,F132),"")) | O132: =IF((F132)>8,SUM(F132-N132),"") | P132: =(IF(G132>0,MIN(8,G132),"")) | Q132: =IF((G132)>8,SUM(G132-P132),"") | R132: =(IF(H132>0,MIN(8,H132),"")) | S132: =IF((H132)>8,SUM(H132-R132),"") | T132: =(IF(I132>0,MIN(8,I132),"")) | U132: =IF((I132)>8,SUM(I132-T132),"") | V132: =(IF(J132>0,MIN(8,J132),"")) | W132: =IF((J132)>8,SUM(J132-V132),"") | X132: =(IF(K132>0,MIN(8,K132),"")) | Y132: =IF((K132)>8,SUM(K132-X132),"") | Z132: =VLOOKUP(A132,#REF!,7,FALSE) -> #REF! | AA132: =VLOOKUP(A132,#REF!,8,FALSE) -> #REF! | AB132: =IFERROR(VLOOKUP(A132,Table13[[#Headers],[#Data]],7,FALSE),0) -> 0 | AC132: =SUM(Z132:AB132) -> #REF! | AD132: =Z132*C132 -> #REF! | AE132: =AA132*C132*1.5 -> #REF! | AF132: =AB132*C132*2 -> 0 | AG132: =AD132+AE132+AF132 -> #REF!
A133: SAENZ, BERNARDO | B133: Electrician | C133: =VLOOKUP('6002 2nd'!$B133,Table6[],2,FALSE)+15 -> 165 | D133: 0 | E133: 0 | F133: 0 | G133: 0 | H133: 0 | I133: 0 | J133: 0 | K133: 0 | L133: =(IF(E133>0,MIN(8,E133),"")) | M133: =IF((E133)>8,SUM(E133-L133),"") | N133: =(IF(F133>0,MIN(8,F133),"")) | O133: =IF((F133)>8,SUM(F133-N133),"") | P133: =(IF(G133>0,MIN(8,G133),"")) | Q133: =IF((G133)>8,SUM(G133-P133),"") | R133: =(IF(H133>0,MIN(8,H133),"")) | S133: =IF((H133)>8,SUM(H133-R133),"") | T133: =(IF(I133>0,MIN(8,I133),"")) | U133: =IF((I133)>8,SUM(I133-T133),"") | V133: =(IF(J133>0,MIN(8,J133),"")) | W133: =IF((J133)>8,SUM(J133-V133),"") | X133: =(IF(K133>0,MIN(8,K133),"")) | Y133: =IF((K133)>8,SUM(K133-X133),"") | Z133: =VLOOKUP(A133,#REF!,7,FALSE) -> #REF! | AA133: =VLOOKUP(A133,#REF!,8,FALSE) -> #REF! | AB133: =IFERROR(VLOOKUP(A133,Table13[[#Headers],[#Data]],7,FALSE),0) -> 0 | AC133: =SUM(Z133:AB133) -> #REF! | AD133: =Z133*C133 -> #REF! | AE133: =AA133*C133*1.5 -> #REF! | AF133: =AB133*C133*2 -> 0 | AG133: =AD133+AE133+AF133 -> #REF!
A134: SALINAS, ISRAEL | B134: Electrician | C134: =VLOOKUP('6002 2nd'!$B134,Table6[],2,FALSE)+15 -> 165 | D134: 0 | E134: 0 | F134: 0 | G134: 0 | H134: 0 | I134: 0 | J134: 0 | K134: 0 | L134: =(IF(E134>0,MIN(8,E134),"")) | M134: =IF((E134)>8,SUM(E134-L134),"") | N134: =(IF(F134>0,MIN(8,F134),"")) | O134: =IF((F134)>8,SUM(F134-N134),"") | P134: =(IF(G134>0,MIN(8,G134),"")) | Q134: =IF((G134)>8,SUM(G134-P134),"") | R134: =(IF(H134>0,MIN(8,H134),"")) | S134: =IF((H134)>8,SUM(H134-R134),"") | T134: =(IF(I134>0,MIN(8,I134),"")) | U134: =IF((I134)>8,SUM(I134-T134),"") | V134: =(IF(J134>0,MIN(8,J134),"")) | W134: =IF((J134)>8,SUM(J134-V134),"") | X134: =(IF(K134>0,MIN(8,K134),"")) | Y134: =IF((K134)>8,SUM(K134-X134),"") | Z134: =VLOOKUP(A134,#REF!,7,FALSE) -> #REF! | AA134: =VLOOKUP(A134,#REF!,8,FALSE) -> #REF! | AB134: =IFERROR(VLOOKUP(A134,Table13[[#Headers],[#Data]],7,FALSE),0) -> 0 | AC134: =SUM(Z134:AB134) -> #REF! | AD134: =Z134*C134 -> #REF! | AE134: =AA134*C134*1.5 -> #REF! | AF134: =AB134*C134*2 -> 0 | AG134: =AD134+AE134+AF134 -> #REF!
A135: SANCHEZ, DANNY | B135: Electrician | C135: =VLOOKUP('6002 2nd'!$B135,Table6[],2,FALSE)+15 -> 165 | D135: 0 | E135: 0 | F135: 0 | G135: 0 | H135: 0 | I135: 0 | J135: 0 | K135: 0 | L135: =(IF(E135>0,MIN(8,E135),"")) | M135: =IF((E135)>8,SUM(E135-L135),"") | N135: =(IF(F135>0,MIN(8,F135),"")) | O135: =IF((F135)>8,SUM(F135-N135),"") | P135: =(IF(G135>0,MIN(8,G135),"")) | Q135: =IF((G135)>8,SUM(G135-P135),"") | R135: =(IF(H135>0,MIN(8,H135),"")) | S135: =IF((H135)>8,SUM(H135-R135),"") | T135: =(IF(I135>0,MIN(8,I135),"")) | U135: =IF((I135)>8,SUM(I135-T135),"") | V135: =(IF(J135>0,MIN(8,J135),"")) | W135: =IF((J135)>8,SUM(J135-V135),"") | X135: =(IF(K135>0,MIN(8,K135),"")) | Y135: =IF((K135)>8,SUM(K135-X135),"") | Z135: =VLOOKUP(A135,#REF!,7,FALSE) -> #REF! | AA135: =VLOOKUP(A135,#REF!,8,FALSE) -> #REF! | AB135: =IFERROR(VLOOKUP(A135,Table13[[#Headers],[#Data]],7,FALSE),0) -> 0 | AC135: =SUM(Z135:AB135) -> #REF! | AD135: =Z135*C135 -> #REF! | AE135: =AA135*C135*1.5 -> #REF! | AF135: =AB135*C135*2 -> 0 | AG135: =AD135+AE135+AF135 -> #REF!
A136: SANCHEZ, NORJE | B136: Electrician | C136: =VLOOKUP('6002 2nd'!$B136,Table6[],2,FALSE)+15 -> 165 | D136: 0 | E136: 0 | F136: 0 | G136: 0 | H136: 0 | I136: 0 | J136: 0 | K136: 0 | L136: =(IF(E136>0,MIN(8,E136),"")) | M136: =IF((E136)>8,SUM(E136-L136),"") | N136: =(IF(F136>0,MIN(8,F136),"")) | O136: =IF((F136)>8,SUM(F136-N136),"") | P136: =(IF(G136>0,MIN(8,G136),"")) | Q136: =IF((G136)>8,SUM(G136-P136),"") | R136: =(IF(H136>0,MIN(8,H136),"")) | S136: =IF((H136)>8,SUM(H136-R136),"") | T136: =(IF(I136>0,MIN(8,I136),"")) | U136: =IF((I136)>8,SUM(I136-T136),"") | V136: =(IF(J136>0,MIN(8,J136),"")) | W136: =IF((J136)>8,SUM(J136-V136),"") | X136: =(IF(K136>0,MIN(8,K136),"")) | Y136: =IF((K136)>8,SUM(K136-X136),"") | Z136: =VLOOKUP(A136,#REF!,7,FALSE) -> #REF! | AA136: =VLOOKUP(A136,#REF!,8,FALSE) -> #REF! | AB136: =IFERROR(VLOOKUP(A136,Table13[[#Headers],[#Data]],7,FALSE),0) -> 0 | AC136: =SUM(Z136:AB136) -> #REF! | AD136: =Z136*C136 -> #REF! | AE136: =AA136*C136*1.5 -> #REF! | AF136: =AB136*C136*2 -> 0 | AG136: =AD136+AE136+AF136 -> #REF!
A137: SANTIAGO, HUGO | B137: Electrician | C137: =VLOOKUP('6002 2nd'!$B137,Table6[],2,FALSE)+15 -> 165 | D137: 0 | E137: 0 | F137: 0 | G137: 0 | H137: 0 | I137: 0 | J137: 0 | K137: 0 | L137: =(IF(E137>0,MIN(8,E137),"")) | M137: =IF((E137)>8,SUM(E137-L137),"") | N137: =(IF(F137>0,MIN(8,F137),"")) | O137: =IF((F137)>8,SUM(F137-N137),"") | P137: =(IF(G137>0,MIN(8,G137),"")) | Q137: =IF((G137)>8,SUM(G137-P137),"") | R137: =(IF(H137>0,MIN(8,H137),"")) | S137: =IF((H137)>8,SUM(H137-R137),"") | T137: =(IF(I137>0,MIN(8,I137),"")) | U137: =IF((I137)>8,SUM(I137-T137),"") | V137: =(IF(J137>0,MIN(8,J137),"")) | W137: =IF((J137)>8,SUM(J137-V137),"") | X137: =(IF(K137>0,MIN(8,K137),"")) | Y137: =IF((K137)>8,SUM(K137-X137),"") | Z137: =VLOOKUP(A137,#REF!,7,FALSE) -> #REF! | AA137: =VLOOKUP(A137,#REF!,8,FALSE) -> #REF! | AB137: =IFERROR(VLOOKUP(A137,Table13[[#Headers],[#Data]],7,FALSE),0) -> 0 | AC137: =SUM(Z137:AB137) -> #REF! | AD137: =Z137*C137 -> #REF! | AE137: =AA137*C137*1.5 -> #REF! | AF137: =AB137*C137*2 -> 0 | AG137: =AD137+AE137+AF137 -> #REF!
A138: SANCHEZ, RAQUEL | B138: Electrician | C138: =VLOOKUP('6002 2nd'!$B138,Table6[],2,FALSE)+15 -> 165 | D138: 0 | E138: 0 | F138: 0 | G138: 0 | H138: 0 | I138: 0 | J138: 0 | K138: 0 | L138: =(IF(E138>0,MIN(8,E138),"")) | M138: =IF((E138)>8,SUM(E138-L138),"") | N138: =(IF(F138>0,MIN(8,F138),"")) | O138: =IF((F138)>8,SUM(F138-N138),"") | P138: =(IF(G138>0,MIN(8,G138),"")) | Q138: =IF((G138)>8,SUM(G138-P138),"") | R138: =(IF(H138>0,MIN(8,H138),"")) | S138: =IF((H138)>8,SUM(H138-R138),"") | T138: =(IF(I138>0,MIN(8,I138),"")) | U138: =IF((I138)>8,SUM(I138-T138),"") | V138: =(IF(J138>0,MIN(8,J138),"")) | W138: =IF((J138)>8,SUM(J138-V138),"") | X138: =(IF(K138>0,MIN(8,K138),"")) | Y138: =IF((K138)>8,SUM(K138-X138),"") | Z138: =VLOOKUP(A138,#REF!,7,FALSE) -> #REF! | AA138: =VLOOKUP(A138,#REF!,8,FALSE) -> #REF! | AB138: =IFERROR(VLOOKUP(A138,Table13[[#Headers],[#Data]],7,FALSE),0) -> 0 | AC138: =SUM(Z138:AB138) -> #REF! | AD138: =Z138*C138 -> #REF! | AE138: =AA138*C138*1.5 -> #REF! | AF138: =AB138*C138*2 -> 0 | AG138: =AD138+AE138+AF138 -> #REF!
A139: SCHESKE, TRENT | B139: Project Manager | C139: =VLOOKUP('6002 2nd'!$B139,Table6[],2,FALSE)+15 -> 190 | D139: 0 | E139: 0 | F139: 0 | G139: 0 | H139: 0 | I139: 0 | J139: 0 | K139: 0 | L139: =(IF(E139>0,MIN(8,E139),"")) | M139: =IF((E139)>8,SUM(E139-L139),"") | N139: =(IF(F139>0,MIN(8,F139),"")) | O139: =IF((F139)>8,SUM(F139-N139),"") | P139: =(IF(G139>0,MIN(8,G139),"")) | Q139: =IF((G139)>8,SUM(G139-P139),"") | R139: =(IF(H139>0,MIN(8,H139),"")) | S139: =IF((H139)>8,SUM(H139-R139),"") | T139: =(IF(I139>0,MIN(8,I139),"")) | U139: =IF((I139)>8,SUM(I139-T139),"") | V139: =(IF(J139>0,MIN(8,J139),"")) | W139: =IF((J139)>8,SUM(J139-V139),"") | X139: =(IF(K139>0,MIN(8,K139),"")) | Y139: =IF((K139)>8,SUM(K139-X139),"") | Z139: =VLOOKUP(A139,#REF!,7,FALSE) -> #REF! | AA139: =VLOOKUP(A139,#REF!,8,FALSE) -> #REF! | AB139: =IFERROR(VLOOKUP(A139,Table13[[#Headers],[#Data]],7,FALSE),0) -> 0 | AC139: =SUM(Z139:AB139) -> #REF! | AD139: =Z139*C139 -> #REF! | AE139: =AA139*C139*1.5 -> #REF! | AF139: =AB139*C139*2 -> 0 | AG139: =AD139+AE139+AF139 -> #REF! | AN139: 2 | AO139: 2 | AP139: =AN139+AC139-AO139 -> #REF!
A140: SERRANO, JOSE QUINTERO | B140: Electrician | C140: =VLOOKUP('6002 2nd'!$B140,Table6[],2,FALSE)+15 -> 165 | D140: 0 | E140: 0 | F140: 0 | G140: 0 | H140: 0 | I140: 0 | J140: 0 | K140: 0 | L140: =(IF(E140>0,MIN(8,E140),"")) | M140: =IF((E140)>8,SUM(E140-L140),"") | N140: =(IF(F140>0,MIN(8,F140),"")) | O140: =IF((F140)>8,SUM(F140-N140),"") | P140: =(IF(G140>0,MIN(8,G140),"")) | Q140: =IF((G140)>8,SUM(G140-P140),"") | R140: =(IF(H140>0,MIN(8,H140),"")) | S140: =IF((H140)>8,SUM(H140-R140),"") | T140: =(IF(I140>0,MIN(8,I140),"")) | U140: =IF((I140)>8,SUM(I140-T140),"") | V140: =(IF(J140>0,MIN(8,J140),"")) | W140: =IF((J140)>8,SUM(J140-V140),"") | X140: =(IF(K140>0,MIN(8,K140),"")) | Y140: =IF((K140)>8,SUM(K140-X140),"") | Z140: =VLOOKUP(A140,#REF!,7,FALSE) -> #REF! | AA140: =VLOOKUP(A140,#REF!,8,FALSE) -> #REF! | AB140: =IFERROR(VLOOKUP(A140,Table13[[#Headers],[#Data]],7,FALSE),0) -> 0 | AC140: =SUM(Z140:AB140) -> #REF! | AD140: =Z140*C140 -> #REF! | AE140: =AA140*C140*1.5 -> #REF! | AF140: =AB140*C140*2 -> 0 | AG140: =AD140+AE140+AF140 -> #REF!
A141: SESOCK, NATHAN | B141: Electrician | C141: =VLOOKUP('6002 2nd'!$B141,Table6[],2,FALSE)+15 -> 165 | D141: 0 | E141: 0 | F141: 0 | G141: 0 | H141: 0 | I141: 0 | J141: 0 | K141: 0 | L141: =(IF(E141>0,MIN(8,E141),"")) | M141: =IF((E141)>8,SUM(E141-L141),"") | N141: =(IF(F141>0,MIN(8,F141),"")) | O141: =IF((F141)>8,SUM(F141-N141),"") | P141: =(IF(G141>0,MIN(8,G141),"")) | Q141: =IF((G141)>8,SUM(G141-P141),"") | R141: =(IF(H141>0,MIN(8,H141),"")) | S141: =IF((H141)>8,SUM(H141-R141),"") | T141: =(IF(I141>0,MIN(8,I141),"")) | U141: =IF((I141)>8,SUM(I141-T141),"") | V141: =(IF(J141>0,MIN(8,J141),"")) | W141: =IF((J141)>8,SUM(J141-V141),"") | X141: =(IF(K141>0,MIN(8,K141),"")) | Y141: =IF((K141)>8,SUM(K141-X141),"") | Z141: =VLOOKUP(A141,#REF!,7,FALSE) -> #REF! | AA141: =VLOOKUP(A141,#REF!,8,FALSE) -> #REF! | AB141: =IFERROR(VLOOKUP(A141,Table13[[#Headers],[#Data]],7,FALSE),0) -> 0 | AC141: =SUM(Z141:AB141) -> #REF! | AD141: =Z141*C141 -> #REF! | AE141: =AA141*C141*1.5 -> #REF! | AF141: =AB141*C141*2 -> 0 | AG141: =AD141+AE141+AF141 -> #REF!
A142: SESOCK, ROBIN | B142: Electrician | C142: =VLOOKUP('6002 2nd'!$B142,Table6[],2,FALSE)+15 -> 165 | D142: 0 | E142: 0 | F142: 0 | G142: 0 | H142: 0 | I142: 0 | J142: 0 | K142: 0 | L142: =(IF(E142>0,MIN(8,E142),"")) | M142: =IF((E142)>8,SUM(E142-L142),"") | N142: =(IF(F142>0,MIN(8,F142),"")) | O142: =IF((F142)>8,SUM(F142-N142),"") | P142: =(IF(G142>0,MIN(8,G142),"")) | Q142: =IF((G142)>8,SUM(G142-P142),"") | R142: =(IF(H142>0,MIN(8,H142),"")) | S142: =IF((H142)>8,SUM(H142-R142),"") | T142: =(IF(I142>0,MIN(8,I142),"")) | U142: =IF((I142)>8,SUM(I142-T142),"") | V142: =(IF(J142>0,MIN(8,J142),"")) | W142: =IF((J142)>8,SUM(J142-V142),"") | X142: =(IF(K142>0,MIN(8,K142),"")) | Y142: =IF((K142)>8,SUM(K142-X142),"") | Z142: =VLOOKUP(A142,#REF!,7,FALSE) -> #REF! | AA142: =VLOOKUP(A142,#REF!,8,FALSE) -> #REF! | AB142: =IFERROR(VLOOKUP(A142,Table13[[#Headers],[#Data]],7,FALSE),0) -> 0 | AC142: =SUM(Z142:AB142) -> #REF! | AD142: =Z142*C142 -> #REF! | AE142: =AA142*C142*1.5 -> #REF! | AF142: =AB142*C142*2 -> 0 | AG142: =AD142+AE142+AF142 -> #REF!
A143: SNYDER, KEVIN | B143: Electrician | C143: =VLOOKUP('6002 2nd'!$B143,Table6[],2,FALSE)+15 -> 165 | D143: 0 | E143: 0 | F143: 0 | G143: 0 | H143: 0 | I143: 0 | J143: 0 | K143: 0 | L143: =(IF(E143>0,MIN(8,E143),"")) | M143: =IF((E143)>8,SUM(E143-L143),"") | N143: =(IF(F143>0,MIN(8,F143),"")) | O143: =IF((F143)>8,SUM(F143-N143),"") | P143: =(IF(G143>0,MIN(8,G143),"")) | Q143: =IF((G143)>8,SUM(G143-P143),"") | R143: =(IF(H143>0,MIN(8,H143),"")) | S143: =IF((H143)>8,SUM(H143-R143),"") | T143: =(IF(I143>0,MIN(8,I143),"")) | U143: =IF((I143)>8,SUM(I143-T143),"") | V143: =(IF(J143>0,MIN(8,J143),"")) | W143: =IF((J143)>8,SUM(J143-V143),"") | X143: =(IF(K143>0,MIN(8,K143),"")) | Y143: =IF((K143)>8,SUM(K143-X143),"") | Z143: =VLOOKUP(A143,#REF!,7,FALSE) -> #REF! | AA143: =VLOOKUP(A143,#REF!,8,FALSE) -> #REF! | AB143: =IFERROR(VLOOKUP(A143,Table13[[#Headers],[#Data]],7,FALSE),0) -> 0 | AC143: =SUM(Z143:AB143) -> #REF! | AD143: =Z143*C143 -> #REF! | AE143: =AA143*C143*1.5 -> #REF! | AF143: =AB143*C143*2 -> 0 | AG143: =AD143+AE143+AF143 -> #REF!
A144: STONER, AUSTIN | B144: Project Manager | C144: =VLOOKUP('6002 2nd'!$B144,Table6[],2,FALSE)+15 -> 190 | D144: 0 | E144: 0 | F144: 0 | G144: 0 | H144: 0 | I144: 0 | J144: 0 | K144: 0 | L144: =(IF(E144>0,MIN(8,E144),"")) | M144: =IF((E144)>8,SUM(E144-L144),"") | N144: =(IF(F144>0,MIN(8,F144),"")) | O144: =IF((F144)>8,SUM(F144-N144),"") | P144: =(IF(G144>0,MIN(8,G144),"")) | Q144: =IF((G144)>8,SUM(G144-P144),"") | R144: =(IF(H144>0,MIN(8,H144),"")) | S144: =IF((H144)>8,SUM(H144-R144),"") | T144: =(IF(I144>0,MIN(8,I144),"")) | U144: =IF((I144)>8,SUM(I144-T144),"") | V144: =(IF(J144>0,MIN(8,J144),"")) | W144: =IF((J144)>8,SUM(J144-V144),"") | X144: =(IF(K144>0,MIN(8,K144),"")) | Y144: =IF((K144)>8,SUM(K144-X144),"") | Z144: =VLOOKUP(A144,#REF!,7,FALSE) -> #REF! | AA144: =VLOOKUP(A144,#REF!,8,FALSE) -> #REF! | AB144: =IFERROR(VLOOKUP(A144,Table13[[#Headers],[#Data]],7,FALSE),0) -> 0 | AC144: =SUM(Z144:AB144) -> #REF! | AD144: =Z144*C144 -> #REF! | AE144: =AA144*C144*1.5 -> #REF! | AF144: =AB144*C144*2 -> 0 | AG144: =AD144+AE144+AF144 -> #REF! | AN144: 0 | AO144: 8 | AP144: =AN144+AC144-AO144 -> #REF!
A145: SUAREZ, JUAN GUERERRO | B145: Electrician | C145: =VLOOKUP('6002 2nd'!$B145,Table6[],2,FALSE)+15 -> 165 | D145: 0 | E145: 0 | F145: 0 | G145: 0 | H145: 0 | I145: 0 | J145: 0 | K145: 0 | L145: =(IF(E145>0,MIN(8,E145),"")) | M145: =IF((E145)>8,SUM(E145-L145),"") | N145: =(IF(F145>0,MIN(8,F145),"")) | O145: =IF((F145)>8,SUM(F145-N145),"") | P145: =(IF(G145>0,MIN(8,G145),"")) | Q145: =IF((G145)>8,SUM(G145-P145),"") | R145: =(IF(H145>0,MIN(8,H145),"")) | S145: =IF((H145)>8,SUM(H145-R145),"") | T145: =(IF(I145>0,MIN(8,I145),"")) | U145: =IF((I145)>8,SUM(I145-T145),"") | V145: =(IF(J145>0,MIN(8,J145),"")) | W145: =IF((J145)>8,SUM(J145-V145),"") | X145: =(IF(K145>0,MIN(8,K145),"")) | Y145: =IF((K145)>8,SUM(K145-X145),"") | Z145: =VLOOKUP(A145,#REF!,7,FALSE) -> #REF! | AA145: =VLOOKUP(A145,#REF!,8,FALSE) -> #REF! | AB145: =IFERROR(VLOOKUP(A145,Table13[[#Headers],[#Data]],7,FALSE),0) -> 0 | AC145: =SUM(Z145:AB145) -> #REF! | AD145: =Z145*C145 -> #REF! | AE145: =AA145*C145*1.5 -> #REF! | AF145: =AB145*C145*2 -> 0 | AG145: =AD145+AE145+AF145 -> #REF!
A146: SUDANO, ANTONIO | B146: Electrician | C146: =VLOOKUP('6002 2nd'!$B146,Table6[],2,FALSE)+15 -> 165 | D146: 0 | E146: 0 | F146: 0 | G146: 0 | H146: 0 | I146: 0 | J146: 0 | K146: 0 | L146: =(IF(E146>0,MIN(8,E146),"")) | M146: =IF((E146)>8,SUM(E146-L146),"") | N146: =(IF(F146>0,MIN(8,F146),"")) | O146: =IF((F146)>8,SUM(F146-N146),"") | P146: =(IF(G146>0,MIN(8,G146),"")) | Q146: =IF((G146)>8,SUM(G146-P146),"") | R146: =(IF(H146>0,MIN(8,H146),"")) | S146: =IF((H146)>8,SUM(H146-R146),"") | T146: =(IF(I146>0,MIN(8,I146),"")) | U146: =IF((I146)>8,SUM(I146-T146),"") | V146: =(IF(J146>0,MIN(8,J146),"")) | W146: =IF((J146)>8,SUM(J146-V146),"") | X146: =(IF(K146>0,MIN(8,K146),"")) | Y146: =IF((K146)>8,SUM(K146-X146),"") | Z146: =VLOOKUP(A146,#REF!,7,FALSE) -> #REF! | AA146: =VLOOKUP(A146,#REF!,8,FALSE) -> #REF! | AB146: =IFERROR(VLOOKUP(A146,Table13[[#Headers],[#Data]],7,FALSE),0) -> 0 | AC146: =SUM(Z146:AB146) -> #REF! | AD146: =Z146*C146 -> #REF! | AE146: =AA146*C146*1.5 -> #REF! | AF146: =AB146*C146*2 -> 0 | AG146: =AD146+AE146+AF146 -> #REF!
A147: TAPIA, FRANKLIN | B147: Electrician | C147: =VLOOKUP('6002 2nd'!$B147,Table6[],2,FALSE)+15 -> 165 | D147: 0 | E147: 0 | F147: 0 | G147: 0 | H147: 0 | I147: 0 | J147: 0 | K147: 0 | L147: =(IF(E147>0,MIN(8,E147),"")) | M147: =IF((E147)>8,SUM(E147-L147),"") | N147: =(IF(F147>0,MIN(8,F147),"")) | O147: =IF((F147)>8,SUM(F147-N147),"") | P147: =(IF(G147>0,MIN(8,G147),"")) | Q147: =IF((G147)>8,SUM(G147-P147),"") | R147: =(IF(H147>0,MIN(8,H147),"")) | S147: =IF((H147)>8,SUM(H147-R147),"") | T147: =(IF(I147>0,MIN(8,I147),"")) | U147: =IF((I147)>8,SUM(I147-T147),"") | V147: =(IF(J147>0,MIN(8,J147),"")) | W147: =IF((J147)>8,SUM(J147-V147),"") | X147: =(IF(K147>0,MIN(8,K147),"")) | Y147: =IF((K147)>8,SUM(K147-X147),"") | Z147: =VLOOKUP(A147,#REF!,7,FALSE) -> #REF! | AA147: =VLOOKUP(A147,#REF!,8,FALSE) -> #REF! | AB147: =IFERROR(VLOOKUP(A147,Table13[[#Headers],[#Data]],7,FALSE),0) -> 0 | AC147: =SUM(Z147:AB147) -> #REF! | AD147: =Z147*C147 -> #REF! | AE147: =AA147*C147*1.5 -> #REF! | AF147: =AB147*C147*2 -> 0 | AG147: =AD147+AE147+AF147 -> #REF!
A148: TOBAR, RAUL | B148: Electrician | C148: =VLOOKUP('6002 2nd'!$B148,Table6[],2,FALSE)+15 -> 165 | D148: 0 | E148: 0 | F148: 0 | G148: 0 | H148: 0 | I148: 0 | J148: 0 | K148: 0 | L148: =(IF(E148>0,MIN(8,E148),"")) | M148: =IF((E148)>8,SUM(E148-L148),"") | N148: =(IF(F148>0,MIN(8,F148),"")) | O148: =IF((F148)>8,SUM(F148-N148),"") | P148: =(IF(G148>0,MIN(8,G148),"")) | Q148: =IF((G148)>8,SUM(G148-P148),"") | R148: =(IF(H148>0,MIN(8,H148),"")) | S148: =IF((H148)>8,SUM(H148-R148),"") | T148: =(IF(I148>0,MIN(8,I148),"")) | U148: =IF((I148)>8,SUM(I148-T148),"") | V148: =(IF(J148>0,MIN(8,J148),"")) | W148: =IF((J148)>8,SUM(J148-V148),"") | X148: =(IF(K148>0,MIN(8,K148),"")) | Y148: =IF((K148)>8,SUM(K148-X148),"") | Z148: =VLOOKUP(A148,#REF!,7,FALSE) -> #REF! | AA148: =VLOOKUP(A148,#REF!,8,FALSE) -> #REF! | AB148: =IFERROR(VLOOKUP(A148,Table13[[#Headers],[#Data]],7,FALSE),0) -> 0 | AC148: =SUM(Z148:AB148) -> #REF! | AD148: =Z148*C148 -> #REF! | AE148: =AA148*C148*1.5 -> #REF! | AF148: =AB148*C148*2 -> 0 | AG148: =AD148+AE148+AF148 -> #REF!
A149: TORRES, EVER | B149: Electrician | C149: =VLOOKUP('6002 2nd'!$B149,Table6[],2,FALSE)+15 -> 165 | D149: 0 | E149: 0 | F149: 0 | G149: 0 | H149: 0 | I149: 0 | J149: 0 | K149: 0 | L149: =(IF(E149>0,MIN(8,E149),"")) | M149: =IF((E149)>8,SUM(E149-L149),"") | N149: =(IF(F149>0,MIN(8,F149),"")) | O149: =IF((F149)>8,SUM(F149-N149),"") | P149: =(IF(G149>0,MIN(8,G149),"")) | Q149: =IF((G149)>8,SUM(G149-P149),"") | R149: =(IF(H149>0,MIN(8,H149),"")) | S149: =IF((H149)>8,SUM(H149-R149),"") | T149: =(IF(I149>0,MIN(8,I149),"")) | U149: =IF((I149)>8,SUM(I149-T149),"") | V149: =(IF(J149>0,MIN(8,J149),"")) | W149: =IF((J149)>8,SUM(J149-V149),"") | X149: =(IF(K149>0,MIN(8,K149),"")) | Y149: =IF((K149)>8,SUM(K149-X149),"") | Z149: =VLOOKUP(A149,#REF!,7,FALSE) -> #REF! | AA149: =VLOOKUP(A149,#REF!,8,FALSE) -> #REF! | AB149: =IFERROR(VLOOKUP(A149,Table13[[#Headers],[#Data]],7,FALSE),0) -> 0 | AC149: =SUM(Z149:AB149) -> #REF! | AD149: =Z149*C149 -> #REF! | AE149: =AA149*C149*1.5 -> #REF! | AF149: =AB149*C149*2 -> 0 | AG149: =AD149+AE149+AF149 -> #REF!
